Workbook

Sheet CUSTOS
A1: OUTUBRO - 2025
A3: PREV | B3: (Tudo)
B5: .
A6: Valores | B6: CARRETA | C6: COLHEITADEIRA | D6: PLANTADEIRA | E6: PLATAFORMA | F6: PULVERIZADOR | G6: TRATOR
A7: Media Proprio | C7: 1077.7778 | D7: 1122 | E7: 371.42857 | F7: 1056 | G7: 1098.5
A8: Media Terceiro | B8: 300 | C8: 1390 | D8: 2000 | E8: 670 | F8: 9600 | G8: 1122.9
A9: Qtd Proprio | C9: 9 | D9: 1 | E9: 7 | F9: 2 | G9: 36
A10: Qtd Terceiro | B10: 2 | C10: 5 | D10: 1 | E10: 5 | F10: 1 | G10: 17
A11: G01 | B11: CARRETA | C11: COLHEITADEIRA | D11: PLANTADEIRA | E11: PLATAFORMA | F11: PULVERIZADOR | G11: TRATOR
A12: Meta Frete 2026 | C12: 2200 | D12: 1850 | E12: 800 | F12: 2000 | G12: 1500
A13: Média (P+T) | B13: =IFERROR((B7*B9 + B8*B10) / (B9 + B10), "") -> 300 | C13: =IFERROR((C7*C9 + C8*C10) / (C9 + C10), "") -> 1189.2857 | D13: =IFERROR((D7*D9 + D8*D10) / (D9 + D10), "") -> 1561 | E13: =IFERROR((E7*E9 + E8*E10) / (E9 + E10), "") -> 495.83333 | F13: =IFERROR((F7*F9 + F8*F10) / (F9 + F10), "") -> 3904 | G13: =IFERROR((G7*G9 + G8*G10) / (G9 + G10), "") -> 1106.3264
A15: PREV | B15: (Tudo) | C15: G02
A17: Rótulos de Linha | B17: Soma Proprio | C17: Soma Terceiro | D17: Qtd Frete
A18: TRATOR | B18: 39546 | C18: 19089.3 | D18: 55
A19: PULVERIZADOR | B19: 2112 | C19: 9600 | D19: 3
A20: COLHEITADEIRA | B20: 9700 | C20: 6950 | D20: 15
A21: PLATAFORMA | B21: 2600 | C21: 3350 | D21: 12
A22: PLANTADEIRA | B22: 1122 | C22: 2000 | D22: 2
A23: CARRETA | C23: 600 | D23: 2
C26: G03
A28: TERCEIRO | B28: Valor Total | C28: Total KM
A29: TERCEIRO MAZETTO | B29: 12051.3 | C29: 1914
A30: TERCEIRO COLOMBO | B30: 9600 | C30: 733
A31: TERCEIRO AGROMAQ | B31: 7200 | C31: 1374
A32: TERCEIRO ZORTEA | B32: 5400 | C32: 956
A33: TERCEIRO DEMETRIO | B33: 2830 | C33: 748
A34: TERCEIRO NELSON | B34: 2270 | C34: 315
A35: TERCEIRO JAPONES | B35: 1328 | C35: 166
A36: TERCEIRO STOSKI | B36: 910 | C36: 70
A43: DATA | B43: (Tudo) | D43: DATA | E43: (Tudo) | G43: DATA | H43: (Tudo)
A44: TIPO | B44: Munck | D44: TIPO | E44: Frete Peças M | G44: TIPO | H44: Frete Peças T
B45: G04 | E45: G05 | H45: G06
A46: MUNCK | B46: R$ | D46: MOTOBOY | E46: R$ | G46: TRANSPORTADORA | H46: R$
A47: ARAPOTI | B47: 2745 | D47: PG | E47: 9345.62 | G47: PG | H47: 7232
A48: IRATI | B48: 1262 | D48: CASTRO | E48: 4770 | G48: ARAPOTI | H48: 1100
A49: PG | B49: 440 | D49: GRPVA | E49: 1800 | G49: GRPVA | H49: 1100
A50: GRPVA | B50: 270 | D50: TIBAGI | E50: 1760 | G50: CASTRO | H50: 850
A51: Total Geral | B51: 4717 | D51: PRUDE | E51: 1095 | G51: TIBAGI | H51: 830
D52: ARAPOTI | E52: 990 | G52: IRATI | H52: 602
D53: IRATI | E53: 360 | G53: PRUDE | H53: 550
D54: Total Geral | E54: 20120.62 | G54: Total Geral | H54: 12264
A58: DATA | B58: (Tudo) | D58: DATA | E58: (Tudo) | G58: DATA | H58: (Tudo)
A59: TIPO | B59: Frete Peças M | D59: TIPO | E59: Frete Peças T | H59: G09
B60: G07 | E60: G08 | G60: MOTOBOY | H60: R$
A61: MOTOBOY | B61: R$ | D61: TRANSPORTADORA | E61: R$ | G61: DAF Implemento | H61: 4175
A62: DELTA MOTOS COURIER | B62: 11420 | D62: CARGADEDICADA -TR PEÇA | E62: 6190.03 | G62: DAF Multa | H62: 250.79
A63: JOSEAMILTON1 COURIER | B63: 2390 | D63: ESC -TR PEÇA | E63: 5580 | G63: Total Geral | H63: 4425.79
A64: MARCOS D. COURIER | B64: 1970 | D64: PRINCESA -TR PEÇA | E64: 441.97
A65: UNIBOY COURIER | B65: 1860 | D65: TX LOG -TR PEÇA | E65: 52
A66: PRINCESA -TR PEÇA | B66: 900.62 | D66: Total Geral | E66: 12264
A67: JORGE LUIZ 2 COURIER | B67: 880
A68: ANDREIA R. COURIER | B68: 550
A69: JOHN ELVIS COURIER | B69: 150
A70: Total Geral | B70: 20120.62
G71: DATA | H71: (Tudo)
H72: G10
G73: MOTOBOY | H73: R$
G74: VW Implemento | H74: 800.04
G75: VW Licença DER AET | H75: 133.13
G76: VW Licença DNIT AET | H76: 87.62
G77: VW Manutenção | H77: 4853
G78: Total Geral | H78: 5873.79
A83: PREV | B83: (Tudo) | C83: G11
A85: Responsável | B85: VALOR | C85: QTD | D85: KMs | E85: COMBUSTIVEL | F85: VALOR KM | G85: KM EM HR
A86: PROPRIO VW | B86: 15228 | C86: 15 | D86: 2538 | E86: 6520 | F86: =B86/D86 -> 6 | G86: =IFERROR((D86*1.5)/1440, "?") -> 2.64375
A87: PROPRIO DAF | B87: 13966 | C87: 12 | D87: 2961 | E87: 8720 | F87: =B87/D87 -> 4.7166498 | G87: =IFERROR((D87*1.5)/1440, "?") -> 3.084375
A89: 612
A90: Coluna1 | B90: APROVEITAMENTO
A91: PROPRIO VW | B91: =IFERROR((G86*24)/(C86*8),0) -> 0.52875
A92: PROPRIO DAF | B92: =IFERROR((G87*24)/(C87*8),0) -> 0.77109375
E200: .

Sheet FRETE MÁQUINAS
A1: STATUS | B1: FRETE | C1: HR | D1: KM | E1: R$ PROP | F1: R$ TERC | G1: CHASSI | H1: PREV | I1: REAL | J1: CLIENTE/NOTA | K1: SOLICITANTE | L1: ESTÁ: | M1: VAI: | N1: TIPO | O1: ESTÁ EM: | P1: VAI PARA: | Q1: OBS | R1: FILIAL CUSTOS | S1: EQUIP
A2: CONCLUIDO | B2: TERCEIRO DEMETRIO | C2: =IFERROR((D2*1.5)/1440, "?") -> 0.10208333 | D2: 98 | F2: 300 | G2: 1BM5060ECN4103629 | H2: 45964 | I2: 45964 | J2: MANUTENÇÃO → CLIENTE | K2: daisy.kakol | L2: IRATI | M2: CLIENTE | N2: DE LOJA PARA CLIENTE | O2: MPA | P2: https://maps.app.goo.gl/MLVchYQrLvQGhWWp6 | Q2: cezar | R2: IRATI | S2: TRATOR | T2: =IF( OR( IFERROR(FIND("BM",G2),0)>0, IFERROR(FIND("PY",G2),0)>0 ), MID(TRIM(SUBSTITUTE(SUBSTITUTE(G2,CHAR(160),""),CHAR(9),"")),4,5), MID(TRIM(SUBSTITUTE(SUBSTITUTE(G2,CHAR(160),""),CHAR(9),"")),4,4) ) -> 5060E | U2: {=_xlfn.LET( _xlpm.ch, TRIM(SUBSTITUTE(G2,CHAR(160),"")), _xlpm.ehTrator, OR(IFERROR(FIND("BM",_xlpm.ch),0)>0, IFERROR(FIND("PY",_xlpm.ch),0)>0), _xlpm.chave, IF(_xlpm.ehTrator, MID(_xlpm.ch,4,5), MID(_xlpm.ch,4,4)), _xlpm.fonte, IF(LEN(_xlpm.chave)=5, UTIL!BS:BS, UTIL!BR:BR), _xlpm.modelo, TRIM(SUBSTITUTE(T2,CHAR(160),"")), _xlpm.nomeMod, IFERROR(_xlfn.XLOOKUP("*"&_xlpm.modelo&"*", UTIL!D:D, UTIL!B:B, "", 2), IFERROR(_xlfn.XLOOKUP("*"&_xlpm.modelo&"*", UTIL!E:E, UTIL!B:B, "", 2), "")), _xlpm.tipoMod, IF(_xlpm.nomeMod="", "", IFERROR(LEFT(_xlpm.nomeMod, FIND(" ", _xlpm.nomeMod)-1), _xlpm.nomeMod)), _xlpm.dimMod, IFERROR(_xlfn.XLOOKUP("*"&_xlpm.modelo&"*", UTIL!D:D, UTIL!K:K, "", 2), IFERROR(_xlfn.XLOOKUP("*"&_xlpm.modelo&"*", UTIL!E:E, UTIL!K:K, "", 2), "")), _xlpm.tipotxt_antigo, IF(_xlpm.ehTrator, "TRATOR", IFERROR(_xlfn.XLOOKUP(_xlpm.chave, _xlpm.fonte, UTIL!BP:BP, "", 0), IFERROR(_xlfn.XLOOKUP("*"&_xlpm.chave&"*", _xlpm.fonte, UTIL!BP:BP, "", 2), "Não encontrado"))), _xlpm.dimtxt_antigo, IFERROR(_xlfn.XLOOKUP(_xlpm.chave, _xlpm.fonte, UTIL!BY:BY, "", 0), IFERROR(_xlfn.XLOOKUP("*"&_xlpm.chave&"*", _xlpm.fonte, UTIL!BY:BY, "", 2), "Não encontrado")), _xlpm.tipotxt, IF(_xlpm.tipoMod<>"", _xlpm.tipoMod, _xlpm.tipotxt_antigo), _xlpm.dimtxt, IF(_xlpm.dimMod<>"", _xlpm.dimMod, _xlpm.dimtxt_antigo), _xlpm.deTxt, IF(L2="CLIENTE", O2, IF(LEFT(L2,4)="http", L2, "MACPONTA AGRO DE "&L2)), _xlpm.paraBase, IF(M2="CLIENTE", P2, M2), _xlpm.paraTxt, IF(LEFT(_xlpm.paraBase,4)="http", _xlpm.paraBase, "MACPONTA AGRO DE "&_xlpm.paraBase), _xlpm.nfParte, IF(LEN(TRIM(I2))=0, "", " -NF "&TRIM(I2)), "- " & _xlpm.tipotxt & ": *" & G2 & "*" & CHAR(13)&CHAR(10) & "- " & _xlpm.dimtxt & CHAR(13)&CHAR(10) & "- *Cliente*: " & J2 & _xlpm.nfParte & CHAR(13)&CHAR(10) & "- *Obs:* " & Q2 & CHAR(13)&CHAR(10) & CHAR(10) & "- *De*: " & _xlpm.deTxt & CHAR(13)&CHAR(10) & "- *Para*: " & _xlpm.paraTxt & CHAR(13)&CHAR(10) & "- *Ida e volta*: +/- " & TEXT(((D2*1.5)/1440),"h:mm") & "h | " & D2 & "km" )} -> - TRATOR: *1BM5060ECN4103629*_x000D_ - _x000D_ - *Cliente*: MANUTENÇÃO → CLIENTE -NF 45964_x000D_ - *Obs:* cezar_x000D_ - *De*: MACPONTA AGRO DE IRATI_x000D_ - *Para*: https://maps.app.goo.gl/MLVchYQrLvQGhWWp6_x000D_ - *Ida e volta*: +/- 2:27h | 98km
A3: CONCLUIDO | B3: TERCEIRO DEMETRIO | C3: =IFERROR((D3*1.5)/1440, "?") -> 0.11979167 | D3: 115 | F3: 500 | G3: 1BM5080ECP4111950 | H3: 45964 | I3: 45964 | J3: MANUTENÇÃO → CLIENTE | K3: daisy.kakol | L3: IRATI | M3: CLIENTE | N3: DE LOJA PARA CLIENTE | O3: MPA | P3: https://maps.app.goo.gl/rYQLkSMERduCoffL8 | Q3: RICARDO DRANKA | R3: IRATI | S3: TRATOR | T3: =IF( OR( IFERROR(FIND("BM",G3),0)>0, IFERROR(FIND("PY",G3),0)>0 ), MID(TRIM(SUBSTITUTE(SUBSTITUTE(G3,CHAR(160),""),CHAR(9),"")),4,5), MID(TRIM(SUBSTITUTE(SUBSTITUTE(G3,CHAR(160),""),CHAR(9),"")),4,4) ) -> 5080E | U3: {=_xlfn.LET( _xlpm.ch, TRIM(SUBSTITUTE(G3,CHAR(160),"")), _xlpm.ehTrator, OR(IFERROR(FIND("BM",_xlpm.ch),0)>0, IFERROR(FIND("PY",_xlpm.ch),0)>0), _xlpm.chave, IF(_xlpm.ehTrator, MID(_xlpm.ch,4,5), MID(_xlpm.ch,4,4)), _xlpm.fonte, IF(LEN(_xlpm.chave)=5, UTIL!BS:BS, UTIL!BR:BR), _xlpm.modelo, TRIM(SUBSTITUTE(T3,CHAR(160),"")), _xlpm.nomeMod, IFERROR(_xlfn.XLOOKUP("*"&_xlpm.modelo&"*", UTIL!D:D, UTIL!B:B, "", 2), IFERROR(_xlfn.XLOOKUP("*"&_xlpm.modelo&"*", UTIL!E:E, UTIL!B:B, "", 2), "")), _xlpm.tipoMod, IF(_xlpm.nomeMod="", "", IFERROR(LEFT(_xlpm.nomeMod, FIND(" ", _xlpm.nomeMod)-1), _xlpm.nomeMod)), _xlpm.dimMod, IFERROR(_xlfn.XLOOKUP("*"&_xlpm.modelo&"*", UTIL!D:D, UTIL!K:K, "", 2), IFERROR(_xlfn.XLOOKUP("*"&_xlpm.modelo&"*", UTIL!E:E, UTIL!K:K, "", 2), "")), _xlpm.tipotxt_antigo, IF(_xlpm.ehTrator, "TRATOR", IFERROR(_xlfn.XLOOKUP(_xlpm.chave, _xlpm.fonte, UTIL!BP:BP, "", 0), IFERROR(_xlfn.XLOOKUP("*"&_xlpm.chave&"*", _xlpm.fonte, UTIL!BP:BP, "", 2), "Não encontrado"))), _xlpm.dimtxt_antigo, IFERROR(_xlfn.XLOOKUP(_xlpm.chave, _xlpm.fonte, UTIL!BY:BY, "", 0), IFERROR(_xlfn.XLOOKUP("*"&_xlpm.chave&"*", _xlpm.fonte, UTIL!BY:BY, "", 2), "Não encontrado")), _xlpm.tipotxt, IF(_xlpm.tipoMod<>"", _xlpm.tipoMod, _xlpm.tipotxt_antigo), _xlpm.dimtxt, IF(_xlpm.dimMod<>"", _xlpm.dimMod, _xlpm.dimtxt_antigo), _xlpm.deTxt, IF(L3="CLIENTE", O3, IF(LEFT(L3,4)="http", L3, "MACPONTA AGRO DE "&L3)), _xlpm.paraBase, IF(M3="CLIENTE", P3, M3), _xlpm.paraTxt, IF(LEFT(_xlpm.paraBase,4)="http", _xlpm.paraBase, "MACPONTA AGRO DE "&_xlpm.paraBase), _xlpm.nfParte, IF(LEN(TRIM(I3))=0, "", " -NF "&TRIM(I3)), "- " & _xlpm.tipotxt & ": *" & G3 & "*" & CHAR(13)&CHAR(10) & "- " & _xlpm.dimtxt & CHAR(13)&CHAR(10) & "- *Cliente*: " & J3 & _xlpm.nfParte & CHAR(13)&CHAR(10) & "- *Obs:* " & Q3 & CHAR(13)&CHAR(10) & CHAR(10) & "- *De*: " & _xlpm.deTxt & CHAR(13)&CHAR(10) & "- *Para*: " & _xlpm.paraTxt & CHAR(13)&CHAR(10) & "- *Ida e volta*: +/- " & TEXT(((D3*1.5)/1440),"h:mm") & "h | " & D3 & "km" )} -> - TRATOR: *1BM5080ECP4111950*_x000D_ - _x000D_ - *Cliente*: MANUTENÇÃO → CLIENTE -NF 45964_x000D_ - *Obs:* RICARDO DRANKA_x000D_ - *De*: MACPONTA AGRO DE IRATI_x000D_ - *Para*: https://maps.app.goo.gl/rYQLkSMERduCoffL8_x000D_ - *Ida e volta*: +/- 2:52h | 115km
A4: CONCLUIDO | B4: TERCEIRO DEMETRIO | C4: =IFERROR((D4*1.5)/1440, "?") -> 0.11979167 | D4: 115 | F4: 300 | G4: 1BM5080EEP4112594 | H4: 45964 | I4: 45964 | J4: CLIENTE → MANUTENÇÃO | K4: daisy.kakol | L4: CLIENTE | M4: IRATI | N4: DE CLIENTE PARA LOJA | O4: https://maps.app.goo.gl/MTXwpjxVEM4SBPA46 | P4: MPA | Q4: jose | R4: IRATI | S4: TRATOR | T4: =IF( OR( IFERROR(FIND("BM",G4),0)>0, IFERROR(FIND("PY",G4),0)>0 ), MID(TRIM(SUBSTITUTE(SUBSTITUTE(G4,CHAR(160),""),CHAR(9),"")),4,5), MID(TRIM(SUBSTITUTE(SUBSTITUTE(G4,CHAR(160),""),CHAR(9),"")),4,4) ) -> 5080E | U4: {=_xlfn.LET( _xlpm.ch, TRIM(SUBSTITUTE(G4,CHAR(160),"")), _xlpm.ehTrator, OR(IFERROR(FIND("BM",_xlpm.ch),0)>0, IFERROR(FIND("PY",_xlpm.ch),0)>0), _xlpm.chave, IF(_xlpm.ehTrator, MID(_xlpm.ch,4,5), MID(_xlpm.ch,4,4)), _xlpm.fonte, IF(LEN(_xlpm.chave)=5, UTIL!BS:BS, UTIL!BR:BR), _xlpm.modelo, TRIM(SUBSTITUTE(T4,CHAR(160),"")), _xlpm.nomeMod, IFERROR(_xlfn.XLOOKUP("*"&_xlpm.modelo&"*", UTIL!D:D, UTIL!B:B, "", 2), IFERROR(_xlfn.XLOOKUP("*"&_xlpm.modelo&"*", UTIL!E:E, UTIL!B:B, "", 2), "")), _xlpm.tipoMod, IF(_xlpm.nomeMod="", "", IFERROR(LEFT(_xlpm.nomeMod, FIND(" ", _xlpm.nomeMod)-1), _xlpm.nomeMod)), _xlpm.dimMod, IFERROR(_xlfn.XLOOKUP("*"&_xlpm.modelo&"*", UTIL!D:D, UTIL!K:K, "", 2), IFERROR(_xlfn.XLOOKUP("*"&_xlpm.modelo&"*", UTIL!E:E, UTIL!K:K, "", 2), "")), _xlpm.tipotxt_antigo, IF(_xlpm.ehTrator, "TRATOR", IFERROR(_xlfn.XLOOKUP(_xlpm.chave, _xlpm.fonte, UTIL!BP:BP, "", 0), IFERROR(_xlfn.XLOOKUP("*"&_xlpm.chave&"*", _xlpm.fonte, UTIL!BP:BP, "", 2), "Não encontrado"))), _xlpm.dimtxt_antigo, IFERROR(_xlfn.XLOOKUP(_xlpm.chave, _xlpm.fonte, UTIL!BY:BY, "", 0), IFERROR(_xlfn.XLOOKUP("*"&_xlpm.chave&"*", _xlpm.fonte, UTIL!BY:BY, "", 2), "Não encontrado")), _xlpm.tipotxt, IF(_xlpm.tipoMod<>"", _xlpm.tipoMod, _xlpm.tipotxt_antigo), _xlpm.dimtxt, IF(_xlpm.dimMod<>"", _xlpm.dimMod, _xlpm.dimtxt_antigo), _xlpm.deTxt, IF(L4="CLIENTE", O4, IF(LEFT(L4,4)="http", L4, "MACPONTA AGRO DE "&L4)), _xlpm.paraBase, IF(M4="CLIENTE", P4, M4), _xlpm.paraTxt, IF(LEFT(_xlpm.paraBase,4)="http", _xlpm.paraBase, "MACPONTA AGRO DE "&_xlpm.paraBase), _xlpm.nfParte, IF(LEN(TRIM(I4))=0, "", " -NF "&TRIM(I4)), "- " & _xlpm.tipotxt & ": *" & G4 & "*" & CHAR(13)&CHAR(10) & "- " & _xlpm.dimtxt & CHAR(13)&CHAR(10) & "- *Cliente*: " & J4 & _xlpm.nfParte & CHAR(13)&CHAR(10) & "- *Obs:* " & Q4 & CHAR(13)&CHAR(10) & CHAR(10) & "- *De*: " & _xlpm.deTxt & CHAR(13)&CHAR(10) & "- *Para*: " & _xlpm.paraTxt & CHAR(13)&CHAR(10) & "- *Ida e volta*: +/- " & TEXT(((D4*1.5)/1440),"h:mm") & "h | " & D4 & "km" )} -> - TRATOR: *1BM5080EEP4112594*_x000D_ - _x000D_ - *Cliente*: CLIENTE → MANUTENÇÃO -NF 45964_x000D_ - *Obs:* jose_x000D_ - *De*: https://maps.app.goo.gl/MTXwpjxVEM4SBPA46_x000D_ - *Para*: MACPONTA AGRO DE IRATI_x000D_ - *Ida e volta*: +/- 2:52h | 115km
A5: CONCLUIDO | B5: TERCEIRO MAZETTO | C5: =IFERROR((D5*1.5)/1440, "?") -> 0.15625 | D5: 150 | F5: 1352 | G5: 1BM5080EPS4204124 | H5: 45964 | I5: 45964 | J5: LUIZ HENRIQUE GREIN -NF107347 | K5: euclides.junior | L5: GUARAPUAVA | M5: CLIENTE | N5: DE LOJA PARA CLIENTE | O5: MPA | P5: https://maps.app.goo.gl/jZEWqzLvNcpTnRBE8 | Q5: Emerson | R5: GUARAPUAVA | S5: TRATOR | T5: =IF( OR( IFERROR(FIND("BM",G5),0)>0, IFERROR(FIND("PY",G5),0)>0 ), MID(TRIM(SUBSTITUTE(SUBSTITUTE(G5,CHAR(160),""),CHAR(9),"")),4,5), MID(TRIM(SUBSTITUTE(SUBSTITUTE(G5,CHAR(160),""),CHAR(9),"")),4,4) ) -> 5080E | U5: {=_xlfn.LET( _xlpm.ch, TRIM(SUBSTITUTE(G5,CHAR(160),"")), _xlpm.ehTrator, OR(IFERROR(FIND("BM",_xlpm.ch),0)>0, IFERROR(FIND("PY",_xlpm.ch),0)>0), _xlpm.chave, IF(_xlpm.ehTrator, MID(_xlpm.ch,4,5), MID(_xlpm.ch,4,4)), _xlpm.fonte, IF(LEN(_xlpm.chave)=5, UTIL!BS:BS, UTIL!BR:BR), _xlpm.modelo, TRIM(SUBSTITUTE(T5,CHAR(160),"")), _xlpm.nomeMod, IFERROR(_xlfn.XLOOKUP("*"&_xlpm.modelo&"*", UTIL!D:D, UTIL!B:B, "", 2), IFERROR(_xlfn.XLOOKUP("*"&_xlpm.modelo&"*", UTIL!E:E, UTIL!B:B, "", 2), "")), _xlpm.tipoMod, IF(_xlpm.nomeMod="", "", IFERROR(LEFT(_xlpm.nomeMod, FIND(" ", _xlpm.nomeMod)-1), _xlpm.nomeMod)), _xlpm.dimMod, IFERROR(_xlfn.XLOOKUP("*"&_xlpm.modelo&"*", UTIL!D:D, UTIL!K:K, "", 2), IFERROR(_xlfn.XLOOKUP("*"&_xlpm.modelo&"*", UTIL!E:E, UTIL!K:K, "", 2), "")), _xlpm.tipotxt_antigo, IF(_xlpm.ehTrator, "TRATOR", IFERROR(_xlfn.XLOOKUP(_xlpm.chave, _xlpm.fonte, UTIL!BP:BP, "", 0), IFERROR(_xlfn.XLOOKUP("*"&_xlpm.chave&"*", _xlpm.fonte, UTIL!BP:BP, "", 2), "Não encontrado"))), _xlpm.dimtxt_antigo, IFERROR(_xlfn.XLOOKUP(_xlpm.chave, _xlpm.fonte, UTIL!BY:BY, "", 0), IFERROR(_xlfn.XLOOKUP("*"&_xlpm.chave&"*", _xlpm.fonte, UTIL!BY:BY, "", 2), "Não encontrado")), _xlpm.tipotxt, IF(_xlpm.tipoMod<>"", _xlpm.tipoMod, _xlpm.tipotxt_antigo), _xlpm.dimtxt, IF(_xlpm.dimMod<>"", _xlpm.dimMod, _xlpm.dimtxt_antigo), _xlpm.deTxt, IF(L5="CLIENTE", O5, IF(LEFT(L5,4)="http", L5, "MACPONTA AGRO DE "&L5)), _xlpm.paraBase, IF(M5="CLIENTE", P5, M5), _xlpm.paraTxt, IF(LEFT(_xlpm.paraBase,4)="http", _xlpm.paraBase, "MACPONTA AGRO DE "&_xlpm.paraBase), _xlpm.nfParte, IF(LEN(TRIM(I5))=0, "", " -NF "&TRIM(I5)), "- " & _xlpm.tipotxt & ": *" & G5 & "*" & CHAR(13)&CHAR(10) & "- " & _xlpm.dimtxt & CHAR(13)&CHAR(10) & "- *Cliente*: " & J5 & _xlpm.nfParte & CHAR(13)&CHAR(10) & "- *Obs:* " & Q5 & CHAR(13)&CHAR(10) & CHAR(10) & "- *De*: " & _xlpm.deTxt & CHAR(13)&CHAR(10) & "- *Para*: " & _xlpm.paraTxt & CHAR(13)&CHAR(10) & "- *Ida e volta*: +/- " & TEXT(((D5*1.5)/1440),"h:mm") & "h | " & D5 & "km" )} -> - TRATOR: *1BM5080EPS4204124*_x000D_ - _x000D_ - *Cliente*: LUIZ HENRIQUE GREIN -NF107347 -NF 45964_x000D_ - *Obs:* Emerson_x000D_ - *De*: MACPONTA AGRO DE GUARAPUAVA_x000D_ - *Para*: https://maps.app.goo.gl/jZEWqzLvNcpTnRBE8_x000D_ - *Ida e volta*: +/- 3:45h | 150km
A6: CONCLUIDO | B6: TERCEIRO MAZETTO | C6: =IFERROR((D6*1.5)/1440, "?") -> 0.17916667 | D6: 172 | F6: 650 | G6: 1CQFA30AAS0160114 | H6: 45964 | I6: 45964 | J6: ARNALDO STOCK -NF107847 | K6: euclides.junior | L6: GUARAPUAVA | M6: CLIENTE | N6: DE LOJA PARA CLIENTE | O6: MPA | P6: https://maps.app.goo.gl/kFwUPivsMpYS8pGd8 | Q6: Fabio | R6: GUARAPUAVA | S6: PLATAFORMA | T6: =IF( OR( IFERROR(FIND("BM",G6),0)>0, IFERROR(FIND("PY",G6),0)>0 ), MID(TRIM(SUBSTITUTE(SUBSTITUTE(G6,CHAR(160),""),CHAR(9),"")),4,5), MID(TRIM(SUBSTITUTE(SUBSTITUTE(G6,CHAR(160),""),CHAR(9),"")),4,4) ) -> FA30 | U6: {=_xlfn.LET( _xlpm.ch, TRIM(SUBSTITUTE(G6,CHAR(160),"")), _xlpm.ehTrator, OR(IFERROR(FIND("BM",_xlpm.ch),0)>0, IFERROR(FIND("PY",_xlpm.ch),0)>0), _xlpm.chave, IF(_xlpm.ehTrator, MID(_xlpm.ch,4,5), MID(_xlpm.ch,4,4)), _xlpm.fonte, IF(LEN(_xlpm.chave)=5, UTIL!BS:BS, UTIL!BR:BR), _xlpm.modelo, TRIM(SUBSTITUTE(T6,CHAR(160),"")), _xlpm.nomeMod, IFERROR(_xlfn.XLOOKUP("*"&_xlpm.modelo&"*", UTIL!D:D, UTIL!B:B, "", 2), IFERROR(_xlfn.XLOOKUP("*"&_xlpm.modelo&"*", UTIL!E:E, UTIL!B:B, "", 2), "")), _xlpm.tipoMod, IF(_xlpm.nomeMod="", "", IFERROR(LEFT(_xlpm.nomeMod, FIND(" ", _xlpm.nomeMod)-1), _xlpm.nomeMod)), _xlpm.dimMod, IFERROR(_xlfn.XLOOKUP("*"&_xlpm.modelo&"*", UTIL!D:D, UTIL!K:K, "", 2), IFERROR(_xlfn.XLOOKUP("*"&_xlpm.modelo&"*", UTIL!E:E, UTIL!K:K, "", 2), "")), _xlpm.tipotxt_antigo, IF(_xlpm.ehTrator, "TRATOR", IFERROR(_xlfn.XLOOKUP(_xlpm.chave, _xlpm.fonte, UTIL!BP:BP, "", 0), IFERROR(_xlfn.XLOOKUP("*"&_xlpm.chave&"*", _xlpm.fonte, UTIL!BP:BP, "", 2), "Não encontrado"))), _xlpm.dimtxt_antigo, IFERROR(_xlfn.XLOOKUP(_xlpm.chave, _xlpm.fonte, UTIL!BY:BY, "", 0), IFERROR(_xlfn.XLOOKUP("*"&_xlpm.chave&"*", _xlpm.fonte, UTIL!BY:BY, "", 2), "Não encontrado")), _xlpm.tipotxt, IF(_xlpm.tipoMod<>"", _xlpm.tipoMod, _xlpm.tipotxt_antigo), _xlpm.dimtxt, IF(_xlpm.dimMod<>"", _xlpm.dimMod, _xlpm.dimtxt_antigo), _xlpm.deTxt, IF(L6="CLIENTE", O6, IF(LEFT(L6,4)="http", L6, "MACPONTA AGRO DE "&L6)), _xlpm.paraBase, IF(M6="CLIENTE", P6, M6), _xlpm.paraTxt, IF(LEFT(_xlpm.paraBase,4)="http", _xlpm.paraBase, "MACPONTA AGRO DE "&_xlpm.paraBase), _xlpm.nfParte, IF(LEN(TRIM(I6))=0, "", " -NF "&TRIM(I6)), "- " & _xlpm.tipotxt & ": *" & G6 & "*" & CHAR(13)&CHAR(10) & "- " & _xlpm.dimtxt & CHAR(13)&CHAR(10) & "- *Cliente*: " & J6 & _xlpm.nfParte & CHAR(13)&CHAR(10) & "- *Obs:* " & Q6 & CHAR(13)&CHAR(10) & CHAR(10) & "- *De*: " & _xlpm.deTxt & CHAR(13)&CHAR(10) & "- *Para*: " & _xlpm.paraTxt & CHAR(13)&CHAR(10) & "- *Ida e volta*: +/- " & TEXT(((D6*1.5)/1440),"h:mm") & "h | " & D6 & "km" )} -> - PLATAFORMA: *1CQFA30AAS0160114*_x000D_ - A:1,60 x C:9,14 x L:1,80-1,80 x P:2.900kg_x000D_ - *Cliente*: ARNALDO STOCK -NF107847 -NF 45964_x000D_ - *Obs:* Fabio _x000D_ - *De*: MACPONTA AGRO DE GUARAPUAVA_x000D_ - *Para*: https://maps.app.goo.gl/kFwUPivsMpYS8pGd8_x000D_ - *Ida e volta*: +/- 4:18h | 172km
A7: CONCLUIDO | B7: TERCEIRO MAZETTO | C7: =IFERROR((D7*1.5)/1440, "?") -> 0.17916667 | D7: 172 | F7: 650 | G7: 1CQS760ACS0160134 | H7: 45964 | I7: 45964 | J7: ARNALDO STOCK -NF107847 | K7: euclides.junior | L7: GUARAPUAVA | M7: CLIENTE | N7: DE LOJA PARA CLIENTE | O7: MPA | P7: https://maps.app.goo.gl/Kk5FKYUBPHUbo26P8 | Q7: Fabio | R7: GUARAPUAVA | S7: COLHEITADEIRA | T7: =IF( OR( IFERROR(FIND("BM",G7),0)>0, IFERROR(FIND("PY",G7),0)>0 ), MID(TRIM(SUBSTITUTE(SUBSTITUTE(G7,CHAR(160),""),CHAR(9),"")),4,5), MID(TRIM(SUBSTITUTE(SUBSTITUTE(G7,CHAR(160),""),CHAR(9),"")),4,4) ) -> S760 | U7: {=_xlfn.LET( _xlpm.ch, TRIM(SUBSTITUTE(G7,CHAR(160),"")), _xlpm.ehTrator, OR(IFERROR(FIND("BM",_xlpm.ch),0)>0, IFERROR(FIND("PY",_xlpm.ch),0)>0), _xlpm.chave, IF(_xlpm.ehTrator, MID(_xlpm.ch,4,5), MID(_xlpm.ch,4,4)), _xlpm.fonte, IF(LEN(_xlpm.chave)=5, UTIL!BS:BS, UTIL!BR:BR), _xlpm.modelo, TRIM(SUBSTITUTE(T7,CHAR(160),"")), _xlpm.nomeMod, IFERROR(_xlfn.XLOOKUP("*"&_xlpm.modelo&"*", UTIL!D:D, UTIL!B:B, "", 2), IFERROR(_xlfn.XLOOKUP("*"&_xlpm.modelo&"*", UTIL!E:E, UTIL!B:B, "", 2), "")), _xlpm.tipoMod, IF(_xlpm.nomeMod="", "", IFERROR(LEFT(_xlpm.nomeMod, FIND(" ", _xlpm.nomeMod)-1), _xlpm.nomeMod)), _xlpm.dimMod, IFERROR(_xlfn.XLOOKUP("*"&_xlpm.modelo&"*", UTIL!D:D, UTIL!K:K, "", 2), IFERROR(_xlfn.XLOOKUP("*"&_xlpm.modelo&"*", UTIL!E:E, UTIL!K:K, "", 2), "")), _xlpm.tipotxt_antigo, IF(_xlpm.ehTrator, "TRATOR", IFERROR(_xlfn.XLOOKUP(_xlpm.chave, _xlpm.fonte, UTIL!BP:BP, "", 0), IFERROR(_xlfn.XLOOKUP("*"&_xlpm.chave&"*", _xlpm.fonte, UTIL!BP:BP, "", 2), "Não encontrado"))), _xlpm.dimtxt_antigo, IFERROR(_xlfn.XLOOKUP(_xlpm.chave, _xlpm.fonte, UTIL!BY:BY, "", 0), IFERROR(_xlfn.XLOOKUP("*"&_xlpm.chave&"*", _xlpm.fonte, UTIL!BY:BY, "", 2), "Não encontrado")), _xlpm.tipotxt, IF(_xlpm.tipoMod<>"", _xlpm.tipoMod, _xlpm.tipotxt_antigo), _xlpm.dimtxt, IF(_xlpm.dimMod<>"", _xlpm.dimMod, _xlpm.dimtxt_antigo), _xlpm.deTxt, IF(L7="CLIENTE", O7, IF(LEFT(L7,4)="http", L7, "MACPONTA AGRO DE "&L7)), _xlpm.paraBase, IF(M7="CLIENTE", P7, M7), _xlpm.paraTxt, IF(LEFT(_xlpm.paraBase,4)="http", _xlpm.paraBase, "MACPONTA AGRO DE "&_xlpm.paraBase), _xlpm.nfParte, IF(LEN(TRIM(I7))=0, "", " -NF "&TRIM(I7)), "- " & _xlpm.tipotxt & ": *" & G7 & "*" & CHAR(13)&CHAR(10) & "- " & _xlpm.dimtxt & CHAR(13)&CHAR(10) & "- *Cliente*: " & J7 & _xlpm.nfParte & CHAR(13)&CHAR(10) & "- *Obs:* " & Q7 & CHAR(13)&CHAR(10) & CHAR(10) & "- *De*: " & _xlpm.deTxt & CHAR(13)&CHAR(10) & "- *Para*: " & _xlpm.paraTxt & CHAR(13)&CHAR(10) & "- *Ida e volta*: +/- " & TEXT(((D7*1.5)/1440),"h:mm") & "h | " & D7 & "km" )} -> - COLHEITADEIRA: *1CQS760ACS0160134*_x000D_ - A:4,00 x C:10,60 x L:3,50-5,20 x P:18.599kg_x000D_ - *Cliente*: ARNALDO STOCK -NF107847 -NF 45964_x000D_ - *Obs:* Fabio _x000D_ - *De*: MACPONTA AGRO DE GUARAPUAVA_x000D_ - *Para*: https://maps.app.goo.gl/Kk5FKYUBPHUbo26P8_x000D_ - *Ida e volta*: +/- 4:18h | 172km
A8: CONCLUIDO | B8: TERCEIRO STOSKI | C8: =IFERROR((D8*1.5)/1440, "?") -> 0.072916667 | D8: 70 | F8: 910 | G8: 1BM6135MPSH000596 | H8: 45964 | I8: 45964 | J8: LAURO MIGUEL STRONA -NF76755 | K8: marcio.jacovossi | L8: IRATI | M8: CLIENTE | N8: DE LOJA PARA CLIENTE | O8: MPA | P8: https://maps.app.goo.gl/JxzGitfYRrvxzYUL9 | Q8: LAURO MIGUEL STRONA 42 999269190 | R8: IRATI | S8: TRATOR | T8: =IF( OR( IFERROR(FIND("BM",G8),0)>0, IFERROR(FIND("PY",G8),0)>0 ), MID(TRIM(SUBSTITUTE(SUBSTITUTE(G8,CHAR(160),""),CHAR(9),"")),4,5), MID(TRIM(SUBSTITUTE(SUBSTITUTE(G8,CHAR(160),""),CHAR(9),"")),4,4) ) -> 6135M | U8: {=_xlfn.LET( _xlpm.ch, TRIM(SUBSTITUTE(G8,CHAR(160),"")), _xlpm.ehTrator, OR(IFERROR(FIND("BM",_xlpm.ch),0)>0, IFERROR(FIND("PY",_xlpm.ch),0)>0), _xlpm.chave, IF(_xlpm.ehTrator, MID(_xlpm.ch,4,5), MID(_xlpm.ch,4,4)), _xlpm.fonte, IF(LEN(_xlpm.chave)=5, UTIL!BS:BS, UTIL!BR:BR), _xlpm.modelo, TRIM(SUBSTITUTE(T8,CHAR(160),"")), _xlpm.nomeMod, IFERROR(_xlfn.XLOOKUP("*"&_xlpm.modelo&"*", UTIL!D:D, UTIL!B:B, "", 2), IFERROR(_xlfn.XLOOKUP("*"&_xlpm.modelo&"*", UTIL!E:E, UTIL!B:B, "", 2), "")), _xlpm.tipoMod, IF(_xlpm.nomeMod="", "", IFERROR(LEFT(_xlpm.nomeMod, FIND(" ", _xlpm.nomeMod)-1), _xlpm.nomeMod)), _xlpm.dimMod, IFERROR(_xlfn.XLOOKUP("*"&_xlpm.modelo&"*", UTIL!D:D, UTIL!K:K, "", 2), IFERROR(_xlfn.XLOOKUP("*"&_xlpm.modelo&"*", UTIL!E:E, UTIL!K:K, "", 2), "")), _xlpm.tipotxt_antigo, IF(_xlpm.ehTrator, "TRATOR", IFERROR(_xlfn.XLOOKUP(_xlpm.chave, _xlpm.fonte, UTIL!BP:BP, "", 0), IFERROR(_xlfn.XLOOKUP("*"&_xlpm.chave&"*", _xlpm.fonte, UTIL!BP:BP, "", 2), "Não encontrado"))), _xlpm.dimtxt_antigo, IFERROR(_xlfn.XLOOKUP(_xlpm.chave, _xlpm.fonte, UTIL!BY:BY, "", 0), IFERROR(_xlfn.XLOOKUP("*"&_xlpm.chave&"*", _xlpm.fonte, UTIL!BY:BY, "", 2), "Não encontrado")), _xlpm.tipotxt, IF(_xlpm.tipoMod<>"", _xlpm.tipoMod, _xlpm.tipotxt_antigo), _xlpm.dimtxt, IF(_xlpm.dimMod<>"", _xlpm.dimMod, _xlpm.dimtxt_antigo), _xlpm.deTxt, IF(L8="CLIENTE", O8, IF(LEFT(L8,4)="http", L8, "MACPONTA AGRO DE "&L8)), _xlpm.paraBase, IF(M8="CLIENTE", P8, M8), _xlpm.paraTxt, IF(LEFT(_xlpm.paraBase,4)="http", _xlpm.paraBase, "MACPONTA AGRO DE "&_xlpm.paraBase), _xlpm.nfParte, IF(LEN(TRIM(I8))=0, "", " -NF "&TRIM(I8)), "- " & _xlpm.tipotxt & ": *" & G8 & "*" & CHAR(13)&CHAR(10) & "- " & _xlpm.dimtxt & CHAR(13)&CHAR(10) & "- *Cliente*: " & J8 & _xlpm.nfParte & CHAR(13)&CHAR(10) & "- *Obs:* " & Q8 & CHAR(13)&CHAR(10) & CHAR(10) & "- *De*: " & _xlpm.deTxt & CHAR(13)&CHAR(10) & "- *Para*: " & _xlpm.paraTxt & CHAR(13)&CHAR(10) & "- *Ida e volta*: +/- " & TEXT(((D8*1.5)/1440),"h:mm") & "h | " & D8 & "km" )} -> - TRATOR: *1BM6135MPSH000596*_x000D_ - _x000D_ - *Cliente*: LAURO MIGUEL STRONA -NF76755 -NF 45964_x000D_ - *Obs:* LAURO MIGUEL STRONA 42 999269190_x000D_ - *De*: MACPONTA AGRO DE IRATI_x000D_ - *Para*: https://maps.app.goo.gl/JxzGitfYRrvxzYUL9_x000D_ - *Ida e volta*: +/- 1:45h | 70km
A9: CONCLUIDO | B9: PROPRIO VW | C9: =IFERROR((D9*1.5)/1440, "?") -> 0.34375 | D9: 330 | E9: =IFERROR((D9*6),"?") -> 1980 | G9: 1NW4025MVKF190132 | H9: 45965 | I9: 45965 | J9: MARLON BONILHA -NF61707 | K9: edenilson.mattos | L9: PONTA GROSSA | M9: CLIENTE | N9: DE LOJA PARA CLIENTE | O9: MPA | P9: https://maps.app.goo.gl/F6zwbnVFirHNNuCLA | Q9: Contato CEN Alison 43.98409-2094 | R9: PONTA GROSSA | S9: PULVERIZADOR | T9: =IF( OR( IFERROR(FIND("BM",G9),0)>0, IFERROR(FIND("PY",G9),0)>0 ), MID(TRIM(SUBSTITUTE(SUBSTITUTE(G9,CHAR(160),""),CHAR(9),"")),4,5), MID(TRIM(SUBSTITUTE(SUBSTITUTE(G9,CHAR(160),""),CHAR(9),"")),4,4) ) -> 4025 | U9: {=_xlfn.LET( _xlpm.ch, TRIM(SUBSTITUTE(G9,CHAR(160),"")), _xlpm.ehTrator, OR(IFERROR(FIND("BM",_xlpm.ch),0)>0, IFERROR(FIND("PY",_xlpm.ch),0)>0), _xlpm.chave, IF(_xlpm.ehTrator, MID(_xlpm.ch,4,5), MID(_xlpm.ch,4,4)), _xlpm.fonte, IF(LEN(_xlpm.chave)=5, UTIL!BS:BS, UTIL!BR:BR), _xlpm.modelo, TRIM(SUBSTITUTE(T9,CHAR(160),"")), _xlpm.nomeMod, IFERROR(_xlfn.XLOOKUP("*"&_xlpm.modelo&"*", UTIL!D:D, UTIL!B:B, "", 2), IFERROR(_xlfn.XLOOKUP("*"&_xlpm.modelo&"*", UTIL!E:E, UTIL!B:B, "", 2), "")), _xlpm.tipoMod, IF(_xlpm.nomeMod="", "", IFERROR(LEFT(_xlpm.nomeMod, FIND(" ", _xlpm.nomeMod)-1), _xlpm.nomeMod)), _xlpm.dimMod, IFERROR(_xlfn.XLOOKUP("*"&_xlpm.modelo&"*", UTIL!D:D, UTIL!K:K, "", 2), IFERROR(_xlfn.XLOOKUP("*"&_xlpm.modelo&"*", UTIL!E:E, UTIL!K:K, "", 2), "")), _xlpm.tipotxt_antigo, IF(_xlpm.ehTrator, "TRATOR", IFERROR(_xlfn.XLOOKUP(_xlpm.chave, _xlpm.fonte, UTIL!BP:BP, "", 0), IFERROR(_xlfn.XLOOKUP("*"&_xlpm.chave&"*", _xlpm.fonte, UTIL!BP:BP, "", 2), "Não encontrado"))), _xlpm.dimtxt_antigo, IFERROR(_xlfn.XLOOKUP(_xlpm.chave, _xlpm.fonte, UTIL!BY:BY, "", 0), IFERROR(_xlfn.XLOOKUP("*"&_xlpm.chave&"*", _xlpm.fonte, UTIL!BY:BY, "", 2), "Não encontrado")), _xlpm.tipotxt, IF(_xlpm.tipoMod<>"", _xlpm.tipoMod, _xlpm.tipotxt_antigo), _xlpm.dimtxt, IF(_xlpm.dimMod<>"", _xlpm.dimMod, _xlpm.dimtxt_antigo), _xlpm.deTxt, IF(L9="CLIENTE", O9, IF(LEFT(L9,4)="http", L9, "MACPONTA AGRO DE "&L9)), _xlpm.paraBase, IF(M9="CLIENTE", P9, M9), _xlpm.paraTxt, IF(LEFT(_xlpm.paraBase,4)="http", _xlpm.paraBase, "MACPONTA AGRO DE "&_xlpm.paraBase), _xlpm.nfParte, IF(LEN(TRIM(I9))=0, "", " -NF "&TRIM(I9)), "- " & _xlpm.tipotxt & ": *" & G9 & "*" & CHAR(13)&CHAR(10) & "- " & _xlpm.dimtxt & CHAR(13)&CHAR(10) & "- *Cliente*: " & J9 & _xlpm.nfParte & CHAR(13)&CHAR(10) & "- *Obs:* " & Q9 & CHAR(13)&CHAR(10) & CHAR(10) & "- *De*: " & _xlpm.deTxt & CHAR(13)&CHAR(10) & "- *Para*: " & _xlpm.paraTxt & CHAR(13)&CHAR(10) & "- *Ida e volta*: +/- " & TEXT(((D9*1.5)/1440),"h:mm") & "h | " & D9 & "km" )} -> - PULVERIZADOR: *1NW4025MVKF190132*_x000D_ - A:3,34 x C:7,00 x L:2,72-3,30 x P:9.703kg_x000D_ - *Cliente*: MARLON BONILHA -NF61707 -NF 45965_x000D_ - *Obs:* Contato CEN Alison 43.98409-2094_x000D_ - *De*: MACPONTA AGRO DE PONTA GROSSA_x000D_ - *Para*: https://maps.app.goo.gl/F6zwbnVFirHNNuCLA_x000D_ - *Ida e volta*: +/- 8:15h | 330km
A10: CONCLUIDO | B10: PROPRIO VW | C10: =IFERROR((D10*1.5)/1440, "?") -> 0.058333333 | D10: 56 | E10: =IFERROR((D10*6),"?") -> 336 | G10: 1BM5060EES4201594 | H10: 45965 | I10: 45964 | J10: JOAQUIM MASCARENHAS -NF278279 | K10: marcos.ribas | L10: PONTA GROSSA | M10: CLIENTE | N10: DE LOJA PARA CLIENTE | O10: MPA | P10: https://maps.app.goo.gl/s5tPSxgcuWhSkcKc7 | Q10: PAULO - +55 42 9991-2229 - AVISAR ANGELO PARA ACOMPANHAR | R10: PONTA GROSSA | S10: TRATOR | T10: =IF( OR( IFERROR(FIND("BM",G10),0)>0, IFERROR(FIND("PY",G10),0)>0 ), MID(TRIM(SUBSTITUTE(SUBSTITUTE(G10,CHAR(160),""),CHAR(9),"")),4,5), MID(TRIM(SUBSTITUTE(SUBSTITUTE(G10,CHAR(160),""),CHAR(9),"")),4,4) ) -> 5060E | U10: {=_xlfn.LET( _xlpm.ch, TRIM(SUBSTITUTE(G10,CHAR(160),"")), _xlpm.ehTrator, OR(IFERROR(FIND("BM",_xlpm.ch),0)>0, IFERROR(FIND("PY",_xlpm.ch),0)>0), _xlpm.chave, IF(_xlpm.ehTrator, MID(_xlpm.ch,4,5), MID(_xlpm.ch,4,4)), _xlpm.fonte, IF(LEN(_xlpm.chave)=5, UTIL!BS:BS, UTIL!BR:BR), _xlpm.modelo, TRIM(SUBSTITUTE(T10,CHAR(160),"")), _xlpm.nomeMod, IFERROR(_xlfn.XLOOKUP("*"&_xlpm.modelo&"*", UTIL!D:D, UTIL!B:B, "", 2), IFERROR(_xlfn.XLOOKUP("*"&_xlpm.modelo&"*", UTIL!E:E, UTIL!B:B, "", 2), "")), _xlpm.tipoMod, IF(_xlpm.nomeMod="", "", IFERROR(LEFT(_xlpm.nomeMod, FIND(" ", _xlpm.nomeMod)-1), _xlpm.nomeMod)), _xlpm.dimMod, IFERROR(_xlfn.XLOOKUP("*"&_xlpm.modelo&"*", UTIL!D:D, UTIL!K:K, "", 2), IFERROR(_xlfn.XLOOKUP("*"&_xlpm.modelo&"*", UTIL!E:E, UTIL!K:K, "", 2), "")), _xlpm.tipotxt_antigo, IF(_xlpm.ehTrator, "TRATOR", IFERROR(_xlfn.XLOOKUP(_xlpm.chave, _xlpm.fonte, UTIL!BP:BP, "", 0), IFERROR(_xlfn.XLOOKUP("*"&_xlpm.chave&"*", _xlpm.fonte, UTIL!BP:BP, "", 2), "Não encontrado"))), _xlpm.dimtxt_antigo, IFERROR(_xlfn.XLOOKUP(_xlpm.chave, _xlpm.fonte, UTIL!BY:BY, "", 0), IFERROR(_xlfn.XLOOKUP("*"&_xlpm.chave&"*", _xlpm.fonte, UTIL!BY:BY, "", 2), "Não encontrado")), _xlpm.tipotxt, IF(_xlpm.tipoMod<>"", _xlpm.tipoMod, _xlpm.tipotxt_antigo), _xlpm.dimtxt, IF(_xlpm.dimMod<>"", _xlpm.dimMod, _xlpm.dimtxt_antigo), _xlpm.deTxt, IF(L10="CLIENTE", O10, IF(LEFT(L10,4)="http", L10, "MACPONTA AGRO DE "&L10)), _xlpm.paraBase, IF(M10="CLIENTE", P10, M10), _xlpm.paraTxt, IF(LEFT(_xlpm.paraBase,4)="http", _xlpm.paraBase, "MACPONTA AGRO DE "&_xlpm.paraBase), _xlpm.nfParte, IF(LEN(TRIM(I10))=0, "", " -NF "&TRIM(I10)), "- " & _xlpm.tipotxt & ": *" & G10 & "*" & CHAR(13)&CHAR(10) & "- " & _xlpm.dimtxt & CHAR(13)&CHAR(10) & "- *Cliente*: " & J10 & _xlpm.nfParte & CHAR(13)&CHAR(10) & "- *Obs:* " & Q10 & CHAR(13)&CHAR(10) & CHAR(10) & "- *De*: " & _xlpm.deTxt & CHAR(13)&CHAR(10) & "- *Para*: " & _xlpm.paraTxt & CHAR(13)&CHAR(10) & "- *Ida e volta*: +/- " & TEXT(((D10*1.5)/1440),"h:mm") & "h | " & D10 & "km" )} -> - TRATOR: *1BM5060EES4201594*_x000D_ - _x000D_ - *Cliente*: JOAQUIM MASCARENHAS -NF278279 -NF 45964_x000D_ - *Obs:* PAULO - +55 42 9991-2229 - AVISAR ANGELO PARA ACOMPANHAR_x000D_ - *De*: MACPONTA AGRO DE PONTA GROSSA_x000D_ - *Para*: https://maps.app.goo.gl/s5tPSxgcuWhSkcKc7_x000D_ - *Ida e volta*: +/- 1:24h | 56km
A11: CONCLUIDO | B11: TERCEIRO NELSON | C11: =IFERROR((D11*1.5)/1440, "?") -> 0.19270833 | D11: 185 | F11: 1295 | G11: 1BM5060EAP4104558 | H11: 45965 | I11: 45965 | J11: MANUTENÇÃO → CLIENTE | K11: rafael.santos | L11: CLIENTE | M11: ARAPOTI | N11: DE CLIENTE PARA LOJA | O11: https://maps.app.goo.gl/PXTmMqoYPtx48Gex6 | P11: MPA | Q11: LUCIANO DE FREITAS - 43 99624-6946 | R11: ARAPOTI | S11: TRATOR | T11: =IF( OR( IFERROR(FIND("BM",G11),0)>0, IFERROR(FIND("PY",G11),0)>0 ), MID(TRIM(SUBSTITUTE(SUBSTITUTE(G11,CHAR(160),""),CHAR(9),"")),4,5), MID(TRIM(SUBSTITUTE(SUBSTITUTE(G11,CHAR(160),""),CHAR(9),"")),4,4) ) -> 5060E | U11: {=_xlfn.LET( _xlpm.ch, TRIM(SUBSTITUTE(G11,CHAR(160),"")), _xlpm.ehTrator, OR(IFERROR(FIND("BM",_xlpm.ch),0)>0, IFERROR(FIND("PY",_xlpm.ch),0)>0), _xlpm.chave, IF(_xlpm.ehTrator, MID(_xlpm.ch,4,5), MID(_xlpm.ch,4,4)), _xlpm.fonte, IF(LEN(_xlpm.chave)=5, UTIL!BS:BS, UTIL!BR:BR), _xlpm.modelo, TRIM(SUBSTITUTE(T11,CHAR(160),"")), _xlpm.nomeMod, IFERROR(_xlfn.XLOOKUP("*"&_xlpm.modelo&"*", UTIL!D:D, UTIL!B:B, "", 2), IFERROR(_xlfn.XLOOKUP("*"&_xlpm.modelo&"*", UTIL!E:E, UTIL!B:B, "", 2), "")), _xlpm.tipoMod, IF(_xlpm.nomeMod="", "", IFERROR(LEFT(_xlpm.nomeMod, FIND(" ", _xlpm.nomeMod)-1), _xlpm.nomeMod)), _xlpm.dimMod, IFERROR(_xlfn.XLOOKUP("*"&_xlpm.modelo&"*", UTIL!D:D, UTIL!K:K, "", 2), IFERROR(_xlfn.XLOOKUP("*"&_xlpm.modelo&"*", UTIL!E:E, UTIL!K:K, "", 2), "")), _xlpm.tipotxt_antigo, IF(_xlpm.ehTrator, "TRATOR", IFERROR(_xlfn.XLOOKUP(_xlpm.chave, _xlpm.fonte, UTIL!BP:BP, "", 0), IFERROR(_xlfn.XLOOKUP("*"&_xlpm.chave&"*", _xlpm.fonte, UTIL!BP:BP, "", 2), "Não encontrado"))), _xlpm.dimtxt_antigo, IFERROR(_xlfn.XLOOKUP(_xlpm.chave, _xlpm.fonte, UTIL!BY:BY, "", 0), IFERROR(_xlfn.XLOOKUP("*"&_xlpm.chave&"*", _xlpm.fonte, UTIL!BY:BY, "", 2), "Não encontrado")), _xlpm.tipotxt, IF(_xlpm.tipoMod<>"", _xlpm.tipoMod, _xlpm.tipotxt_antigo), _xlpm.dimtxt, IF(_xlpm.dimMod<>"", _xlpm.dimMod, _xlpm.dimtxt_antigo), _xlpm.deTxt, IF(L11="CLIENTE", O11, IF(LEFT(L11,4)="http", L11, "MACPONTA AGRO DE "&L11)), _xlpm.paraBase, IF(M11="CLIENTE", P11, M11), _xlpm.paraTxt, IF(LEFT(_xlpm.paraBase,4)="http", _xlpm.paraBase, "MACPONTA AGRO DE "&_xlpm.paraBase), _xlpm.nfParte, IF(LEN(TRIM(I11))=0, "", " -NF "&TRIM(I11)), "- " & _xlpm.tipotxt & ": *" & G11 & "*" & CHAR(13)&CHAR(10) & "- " & _xlpm.dimtxt & CHAR(13)&CHAR(10) & "- *Cliente*: " & J11 & _xlpm.nfParte & CHAR(13)&CHAR(10) & "- *Obs:* " & Q11 & CHAR(13)&CHAR(10) & CHAR(10) & "- *De*: " & _xlpm.deTxt & CHAR(13)&CHAR(10) & "- *Para*: " & _xlpm.paraTxt & CHAR(13)&CHAR(10) & "- *Ida e volta*: +/- " & TEXT(((D11*1.5)/1440),"h:mm") & "h | " & D11 & "km" )} -> - TRATOR: *1BM5060EAP4104558*_x000D_ - _x000D_ - *Cliente*: MANUTENÇÃO → CLIENTE -NF 45965_x000D_ - *Obs:* LUCIANO DE FREITAS - 43 99624-6946_x000D_ - *De*: https://maps.app.goo.gl/PXTmMqoYPtx48Gex6_x000D_ - *Para*: MACPONTA AGRO DE ARAPOTI_x000D_ - *Ida e volta*: +/- 4:37h | 185km
A12: CONCLUIDO | B12: PROPRIO DAF | C12: =IFERROR((D12*1.5)/1440, "?") -> 0.053125 | D12: 51 | E12: =IFERROR((D12*6),"?") -> 306 | G12: 1BM7215CVR3000057 | H12: 45966 | I12: 45967 | J12: MANUTENÇÃO → CLIENTE | K12: marcelo.ferreira | L12: PONTA GROSSA | M12: CLIENTE | N12: DE LOJA PARA CLIENTE | O12: MPA | P12: https://maps.app.goo.gl/pQZUg9LPg5sgdyLs8 | Q12: GABRIEL - 42 -99972-7464 | R12: PONTA GROSSA | S12: TRATOR | T12: =IF( OR( IFERROR(FIND("BM",G12),0)>0, IFERROR(FIND("PY",G12),0)>0 ), MID(TRIM(SUBSTITUTE(SUBSTITUTE(G12,CHAR(160),""),CHAR(9),"")),4,5), MID(TRIM(SUBSTITUTE(SUBSTITUTE(G12,CHAR(160),""),CHAR(9),"")),4,4) ) -> 7215C | U12: {=_xlfn.LET( _xlpm.ch, TRIM(SUBSTITUTE(G12,CHAR(160),"")), _xlpm.ehTrator, OR(IFERROR(FIND("BM",_xlpm.ch),0)>0, IFERROR(FIND("PY",_xlpm.ch),0)>0), _xlpm.chave, IF(_xlpm.ehTrator, MID(_xlpm.ch,4,5), MID(_xlpm.ch,4,4)), _xlpm.fonte, IF(LEN(_xlpm.chave)=5, UTIL!BS:BS, UTIL!BR:BR), _xlpm.modelo, TRIM(SUBSTITUTE(T12,CHAR(160),"")), _xlpm.nomeMod, IFERROR(_xlfn.XLOOKUP("*"&_xlpm.modelo&"*", UTIL!D:D, UTIL!B:B, "", 2), IFERROR(_xlfn.XLOOKUP("*"&_xlpm.modelo&"*", UTIL!E:E, UTIL!B:B, "", 2), "")), _xlpm.tipoMod, IF(_xlpm.nomeMod="", "", IFERROR(LEFT(_xlpm.nomeMod, FIND(" ", _xlpm.nomeMod)-1), _xlpm.nomeMod)), _xlpm.dimMod, IFERROR(_xlfn.XLOOKUP("*"&_xlpm.modelo&"*", UTIL!D:D, UTIL!K:K, "", 2), IFERROR(_xlfn.XLOOKUP("*"&_xlpm.modelo&"*", UTIL!E:E, UTIL!K:K, "", 2), "")), _xlpm.tipotxt_antigo, IF(_xlpm.ehTrator, "TRATOR", IFERROR(_xlfn.XLOOKUP(_xlpm.chave, _xlpm.fonte, UTIL!BP:BP, "", 0), IFERROR(_xlfn.XLOOKUP("*"&_xlpm.chave&"*", _xlpm.fonte, UTIL!BP:BP, "", 2), "Não encontrado"))), _xlpm.dimtxt_antigo, IFERROR(_xlfn.XLOOKUP(_xlpm.chave, _xlpm.fonte, UTIL!BY:BY, "", 0), IFERROR(_xlfn.XLOOKUP("*"&_xlpm.chave&"*", _xlpm.fonte, UTIL!BY:BY, "", 2), "Não encontrado")), _xlpm.tipotxt, IF(_xlpm.tipoMod<>"", _xlpm.tipoMod, _xlpm.tipotxt_antigo), _xlpm.dimtxt, IF(_xlpm.dimMod<>"", _xlpm.dimMod, _xlpm.dimtxt_antigo), _xlpm.deTxt, IF(L12="CLIENTE", O12, IF(LEFT(L12,4)="http", L12, "MACPONTA AGRO DE "&L12)), _xlpm.paraBase, IF(M12="CLIENTE", P12, M12), _xlpm.paraTxt, IF(LEFT(_xlpm.paraBase,4)="http", _xlpm.paraBase, "MACPONTA AGRO DE "&_xlpm.paraBase), _xlpm.nfParte, IF(LEN(TRIM(I12))=0, "", " -NF "&TRIM(I12)), "- " & _xlpm.tipotxt & ": *" & G12 & "*" & CHAR(13)&CHAR(10) & "- " & _xlpm.dimtxt & CHAR(13)&CHAR(10) & "- *Cliente*: " & J12 & _xlpm.nfParte & CHAR(13)&CHAR(10) & "- *Obs:* " & Q12 & CHAR(13)&CHAR(10) & CHAR(10) & "- *De*: " & _xlpm.deTxt & CHAR(13)&CHAR(10) & "- *Para*: " & _xlpm.paraTxt & CHAR(13)&CHAR(10) & "- *Ida e volta*: +/- " & TEXT(((D12*1.5)/1440),"h:mm") & "h | " & D12 & "km" )} -> - TRATOR: *1BM7215CVR3000057*_x000D_ - _x000D_ - *Cliente*: MANUTENÇÃO → CLIENTE -NF 45967_x000D_ - *Obs:* GABRIEL - 42 -99972-7464_x000D_ - *De*: MACPONTA AGRO DE PONTA GROSSA_x000D_ - *Para*: https://maps.app.goo.gl/pQZUg9LPg5sgdyLs8_x000D_ - *Ida e volta*: +/- 1:16h | 51km
A13: CONCLUIDO | B13: PROPRIO VW | C13: =IFERROR((D13*1.5)/1440, "?") -> 0.022916667 | D13: 22 | E13: =IFERROR((D13*6),"?") -> 132 | G13: 1P06110DABA021136 | H13: 45966 | I13: 45967 | J13: MANUTENÇÃO → CLIENTE | K13: leonardo.ramos | L13: PONTA GROSSA | M13: CLIENTE | N13: DE LOJA PARA CLIENTE | O13: MPA | P13: https://maps.app.goo.gl/zzmzdRt4m8WXMVjg9 | Q13: JUNIOR +55 42 8866-3271 | R13: PONTA GROSSA | S13: PULVERIZADOR | T13: =IF( OR( IFERROR(FIND("BM",G13),0)>0, IFERROR(FIND("PY",G13),0)>0 ), MID(TRIM(SUBSTITUTE(SUBSTITUTE(G13,CHAR(160),""),CHAR(9),"")),4,5), MID(TRIM(SUBSTITUTE(SUBSTITUTE(G13,CHAR(160),""),CHAR(9),"")),4,4) ) -> 6110 | U13: {=_xlfn.LET( _xlpm.ch, TRIM(SUBSTITUTE(G13,CHAR(160),"")), _xlpm.ehTrator, OR(IFERROR(FIND("BM",_xlpm.ch),0)>0, IFERROR(FIND("PY",_xlpm.ch),0)>0), _xlpm.chave, IF(_xlpm.ehTrator, MID(_xlpm.ch,4,5), MID(_xlpm.ch,4,4)), _xlpm.fonte, IF(LEN(_xlpm.chave)=5, UTIL!BS:BS, UTIL!BR:BR), _xlpm.modelo, TRIM(SUBSTITUTE(T13,CHAR(160),"")), _xlpm.nomeMod, IFERROR(_xlfn.XLOOKUP("*"&_xlpm.modelo&"*", UTIL!D:D, UTIL!B:B, "", 2), IFERROR(_xlfn.XLOOKUP("*"&_xlpm.modelo&"*", UTIL!E:E, UTIL!B:B, "", 2), "")), _xlpm.tipoMod, IF(_xlpm.nomeMod="", "", IFERROR(LEFT(_xlpm.nomeMod, FIND(" ", _xlpm.nomeMod)-1), _xlpm.nomeMod)), _xlpm.dimMod, IFERROR(_xlfn.XLOOKUP("*"&_xlpm.modelo&"*", UTIL!D:D, UTIL!K:K, "", 2), IFERROR(_xlfn.XLOOKUP("*"&_xlpm.modelo&"*", UTIL!E:E, UTIL!K:K, "", 2), "")), _xlpm.tipotxt_antigo, IF(_xlpm.ehTrator, "TRATOR", IFERROR(_xlfn.XLOOKUP(_xlpm.chave, _xlpm.fonte, UTIL!BP:BP, "", 0), IFERROR(_xlfn.XLOOKUP("*"&_xlpm.chave&"*", _xlpm.fonte, UTIL!BP:BP, "", 2), "Não encontrado"))), _xlpm.dimtxt_antigo, IFERROR(_xlfn.XLOOKUP(_xlpm.chave, _xlpm.fonte, UTIL!BY:BY, "", 0), IFERROR(_xlfn.XLOOKUP("*"&_xlpm.chave&"*", _xlpm.fonte, UTIL!BY:BY, "", 2), "Não encontrado")), _xlpm.tipotxt, IF(_xlpm.tipoMod<>"", _xlpm.tipoMod, _xlpm.tipotxt_antigo), _xlpm.dimtxt, IF(_xlpm.dimMod<>"", _xlpm.dimMod, _xlpm.dimtxt_antigo), _xlpm.deTxt, IF(L13="CLIENTE", O13, IF(LEFT(L13,4)="http", L13, "MACPONTA AGRO DE "&L13)), _xlpm.paraBase, IF(M13="CLIENTE", P13, M13), _xlpm.paraTxt, IF(LEFT(_xlpm.paraBase,4)="http", _xlpm.paraBase, "MACPONTA AGRO DE "&_xlpm.paraBase), _xlpm.nfParte, IF(LEN(TRIM(I13))=0, "", " -NF "&TRIM(I13)), "- " & _xlpm.tipotxt & ": *" & G13 & "*" & CHAR(13)&CHAR(10) & "- " & _xlpm.dimtxt & CHAR(13)&CHAR(10) & "- *Cliente*: " & J13 & _xlpm.nfParte & CHAR(13)&CHAR(10) & "- *Obs:* " & Q13 & CHAR(13)&CHAR(10) & CHAR(10) & "- *De*: " & _xlpm.deTxt & CHAR(13)&CHAR(10) & "- *Para*: " & _xlpm.paraTxt & CHAR(13)&CHAR(10) & "- *Ida e volta*: +/- " & TEXT(((D13*1.5)/1440),"h:mm") & "h | " & D13 & "km" )} -> - : *1P06110DABA021136*_x000D_ - _x000D_ - *Cliente*: MANUTENÇÃO → CLIENTE -NF 45967_x000D_ - *Obs:* JUNIOR +55 42 8866-3271_x000D_ - *De*: MACPONTA AGRO DE PONTA GROSSA_x000D_ - *Para*: https://maps.app.goo.gl/zzmzdRt4m8WXMVjg9_x000D_ - *Ida e volta*: +/- 0:33h | 22km
A14: CONCLUIDO | B14: TERCEIRO MAZETTO | C14: =IFERROR((D14*1.5)/1440, "?") -> 0.16666667 | D14: 160 | F14: 1458 | G14: 1BM6135MASH000623 | H14: 45966 | I14: 45966 | J14: VLADEMIR STORTI -NF107917 | K14: euclides.junior | L14: GUARAPUAVA | M14: CLIENTE | N14: DE LOJA PARA CLIENTE | O14: MPA | P14: https://maps.app.goo.gl/giUyNXP6omVdANbb6 | Q14: Vladmir | R14: GUARAPUAVA | S14: TRATOR | T14: =IF( OR( IFERROR(FIND("BM",G14),0)>0, IFERROR(FIND("PY",G14),0)>0 ), MID(TRIM(SUBSTITUTE(SUBSTITUTE(G14,CHAR(160),""),CHAR(9),"")),4,5), MID(TRIM(SUBSTITUTE(SUBSTITUTE(G14,CHAR(160),""),CHAR(9),"")),4,4) ) -> 6135M | U14: {=_xlfn.LET( _xlpm.ch, TRIM(SUBSTITUTE(G14,CHAR(160),"")), _xlpm.ehTrator, OR(IFERROR(FIND("BM",_xlpm.ch),0)>0, IFERROR(FIND("PY",_xlpm.ch),0)>0), _xlpm.chave, IF(_xlpm.ehTrator, MID(_xlpm.ch,4,5), MID(_xlpm.ch,4,4)), _xlpm.fonte, IF(LEN(_xlpm.chave)=5, UTIL!BS:BS, UTIL!BR:BR), _xlpm.modelo, TRIM(SUBSTITUTE(T14,CHAR(160),"")), _xlpm.nomeMod, IFERROR(_xlfn.XLOOKUP("*"&_xlpm.modelo&"*", UTIL!D:D, UTIL!B:B, "", 2), IFERROR(_xlfn.XLOOKUP("*"&_xlpm.modelo&"*", UTIL!E:E, UTIL!B:B, "", 2), "")), _xlpm.tipoMod, IF(_xlpm.nomeMod="", "", IFERROR(LEFT(_xlpm.nomeMod, FIND(" ", _xlpm.nomeMod)-1), _xlpm.nomeMod)), _xlpm.dimMod, IFERROR(_xlfn.XLOOKUP("*"&_xlpm.modelo&"*", UTIL!D:D, UTIL!K:K, "", 2), IFERROR(_xlfn.XLOOKUP("*"&_xlpm.modelo&"*", UTIL!E:E, UTIL!K:K, "", 2), "")), _xlpm.tipotxt_antigo, IF(_xlpm.ehTrator, "TRATOR", IFERROR(_xlfn.XLOOKUP(_xlpm.chave, _xlpm.fonte, UTIL!BP:BP, "", 0), IFERROR(_xlfn.XLOOKUP("*"&_xlpm.chave&"*", _xlpm.fonte, UTIL!BP:BP, "", 2), "Não encontrado"))), _xlpm.dimtxt_antigo, IFERROR(_xlfn.XLOOKUP(_xlpm.chave, _xlpm.fonte, UTIL!BY:BY, "", 0), IFERROR(_xlfn.XLOOKUP("*"&_xlpm.chave&"*", _xlpm.fonte, UTIL!BY:BY, "", 2), "Não encontrado")), _xlpm.tipotxt, IF(_xlpm.tipoMod<>"", _xlpm.tipoMod, _xlpm.tipotxt_antigo), _xlpm.dimtxt, IF(_xlpm.dimMod<>"", _xlpm.dimMod, _xlpm.dimtxt_antigo), _xlpm.deTxt, IF(L14="CLIENTE", O14, IF(LEFT(L14,4)="http", L14, "MACPONTA AGRO DE "&L14)), _xlpm.paraBase, IF(M14="CLIENTE", P14, M14), _xlpm.paraTxt, IF(LEFT(_xlpm.paraBase,4)="http", _xlpm.paraBase, "MACPONTA AGRO DE "&_xlpm.paraBase), _xlpm.nfParte, IF(LEN(TRIM(I14))=0, "", " -NF "&TRIM(I14)), "- " & _xlpm.tipotxt & ": *" & G14 & "*" & CHAR(13)&CHAR(10) & "- " & _xlpm.dimtxt & CHAR(13)&CHAR(10) & "- *Cliente*: " & J14 & _xlpm.nfParte & CHAR(13)&CHAR(10) & "- *Obs:* " & Q14 & CHAR(13)&CHAR(10) & CHAR(10) & "- *De*: " & _xlpm.deTxt & CHAR(13)&CHAR(10) & "- *Para*: " & _xlpm.paraTxt & CHAR(13)&CHAR(10) & "- *Ida e volta*: +/- " & TEXT(((D14*1.5)/1440),"h:mm") & "h | " & D14 & "km" )} -> - TRATOR: *1BM6135MASH000623*_x000D_ - _x000D_ - *Cliente*: VLADEMIR STORTI -NF107917 -NF 45966_x000D_ - *Obs:* Vladmir_x000D_ - *De*: MACPONTA AGRO DE GUARAPUAVA_x000D_ - *Para*: https://maps.app.goo.gl/giUyNXP6omVdANbb6_x000D_ - *Ida e volta*: +/- 4:00h | 160km
A15: CONCLUIDO | B15: TERCEIRO NELSON | C15: =IFERROR((D15*1.5)/1440, "?") -> 0.13541667 | D15: 130 | F15: 975 | G15: 1BM5080EKS4203735 | H15: 45966 | I15: 45966 | J15: VERIDIANA POSS DE LIMA -NF61217 | K15: josiane.oliveira | L15: ARAPOTI | M15: CLIENTE | N15: DE LOJA PARA CLIENTE | O15: MPA | P15: https://maps.app.goo.gl/oLpnxFw9huVdueSf7 | Q15: Veridiana 043984053787 -CEN Alison Russi | R15: ARAPOTI | S15: TRATOR | T15: =IF( OR( IFERROR(FIND("BM",G15),0)>0, IFERROR(FIND("PY",G15),0)>0 ), MID(TRIM(SUBSTITUTE(SUBSTITUTE(G15,CHAR(160),""),CHAR(9),"")),4,5), MID(TRIM(SUBSTITUTE(SUBSTITUTE(G15,CHAR(160),""),CHAR(9),"")),4,4) ) -> 5080E | U15: {=_xlfn.LET( _xlpm.ch, TRIM(SUBSTITUTE(G15,CHAR(160),"")), _xlpm.ehTrator, OR(IFERROR(FIND("BM",_xlpm.ch),0)>0, IFERROR(FIND("PY",_xlpm.ch),0)>0), _xlpm.chave, IF(_xlpm.ehTrator, MID(_xlpm.ch,4,5), MID(_xlpm.ch,4,4)), _xlpm.fonte, IF(LEN(_xlpm.chave)=5, UTIL!BS:BS, UTIL!BR:BR), _xlpm.modelo, TRIM(SUBSTITUTE(T15,CHAR(160),"")), _xlpm.nomeMod, IFERROR(_xlfn.XLOOKUP("*"&_xlpm.modelo&"*", UTIL!D:D, UTIL!B:B, "", 2), IFERROR(_xlfn.XLOOKUP("*"&_xlpm.modelo&"*", UTIL!E:E, UTIL!B:B, "", 2), "")), _xlpm.tipoMod, IF(_xlpm.nomeMod="", "", IFERROR(LEFT(_xlpm.nomeMod, FIND(" ", _xlpm.nomeMod)-1), _xlpm.nomeMod)), _xlpm.dimMod, IFERROR(_xlfn.XLOOKUP("*"&_xlpm.modelo&"*", UTIL!D:D, UTIL!K:K, "", 2), IFERROR(_xlfn.XLOOKUP("*"&_xlpm.modelo&"*", UTIL!E:E, UTIL!K:K, "", 2), "")), _xlpm.tipotxt_antigo, IF(_xlpm.ehTrator, "TRATOR", IFERROR(_xlfn.XLOOKUP(_xlpm.chave, _xlpm.fonte, UTIL!BP:BP, "", 0), IFERROR(_xlfn.XLOOKUP("*"&_xlpm.chave&"*", _xlpm.fonte, UTIL!BP:BP, "", 2), "Não encontrado"))), _xlpm.dimtxt_antigo, IFERROR(_xlfn.XLOOKUP(_xlpm.chave, _xlpm.fonte, UTIL!BY:BY, "", 0), IFERROR(_xlfn.XLOOKUP("*"&_xlpm.chave&"*", _xlpm.fonte, UTIL!BY:BY, "", 2), "Não encontrado")), _xlpm.tipotxt, IF(_xlpm.tipoMod<>"", _xlpm.tipoMod, _xlpm.tipotxt_antigo), _xlpm.dimtxt, IF(_xlpm.dimMod<>"", _xlpm.dimMod, _xlpm.dimtxt_antigo), _xlpm.deTxt, IF(L15="CLIENTE", O15, IF(LEFT(L15,4)="http", L15, "MACPONTA AGRO DE "&L15)), _xlpm.paraBase, IF(M15="CLIENTE", P15, M15), _xlpm.paraTxt, IF(LEFT(_xlpm.paraBase,4)="http", _xlpm.paraBase, "MACPONTA AGRO DE "&_xlpm.paraBase), _xlpm.nfParte, IF(LEN(TRIM(I15))=0, "", " -NF "&TRIM(I15)), "- " & _xlpm.tipotxt & ": *" & G15 & "*" & CHAR(13)&CHAR(10) & "- " & _xlpm.dimtxt & CHAR(13)&CHAR(10) & "- *Cliente*: " & J15 & _xlpm.nfParte & CHAR(13)&CHAR(10) & "- *Obs:* " & Q15 & CHAR(13)&CHAR(10) & CHAR(10) & "- *De*: " & _xlpm.deTxt & CHAR(13)&CHAR(10) & "- *Para*: " & _xlpm.paraTxt & CHAR(13)&CHAR(10) & "- *Ida e volta*: +/- " & TEXT(((D15*1.5)/1440),"h:mm") & "h | " & D15 & "km" )} -> - TRATOR: *1BM5080EKS4203735*_x000D_ - _x000D_ - *Cliente*: VERIDIANA POSS DE LIMA -NF61217 -NF 45966_x000D_ - *Obs:* Veridiana 043984053787 -CEN Alison Russi_x000D_ - *De*: MACPONTA AGRO DE ARAPOTI_x000D_ - *Para*: https://maps.app.goo.gl/oLpnxFw9huVdueSf7_x000D_ - *Ida e volta*: +/- 3:15h | 130km
A16: CONCLUIDO (D) | B16: PROPRIO DAF | C16: =IFERROR((D16*1.5)/1440, "?") -> 0.15625 | D16: 150 | E16: 500 | G16: 1CQ0630AHR0155127 | H16: 45966 | I16: 45966 | J16: MARCELO RIBEIRO DE NARDI -NF278794 | K16: marcos.ribas | L16: PONTA GROSSA | M16: CLIENTE | N16: DE LOJA PARA CLIENTE | O16: MPA | P16: https://maps.app.goo.gl/2DJawZBMR4yqycss9 | Q16: DANILO - MARCELO | R16: PONTA GROSSA | S16: PLATAFORMA | T16: =IF( OR( IFERROR(FIND("BM",G16),0)>0, IFERROR(FIND("PY",G16),0)>0 ), MID(TRIM(SUBSTITUTE(SUBSTITUTE(G16,CHAR(160),""),CHAR(9),"")),4,5), MID(TRIM(SUBSTITUTE(SUBSTITUTE(G16,CHAR(160),""),CHAR(9),"")),4,4) ) -> 0630 | U16: {=_xlfn.LET( _xlpm.ch, TRIM(SUBSTITUTE(G16,CHAR(160),"")), _xlpm.ehTrator, OR(IFERROR(FIND("BM",_xlpm.ch),0)>0, IFERROR(FIND("PY",_xlpm.ch),0)>0), _xlpm.chave, IF(_xlpm.ehTrator, MID(_xlpm.ch,4,5), MID(_xlpm.ch,4,4)), _xlpm.fonte, IF(LEN(_xlpm.chave)=5, UTIL!BS:BS, UTIL!BR:BR), _xlpm.modelo, TRIM(SUBSTITUTE(T16,CHAR(160),"")), _xlpm.nomeMod, IFERROR(_xlfn.XLOOKUP("*"&_xlpm.modelo&"*", UTIL!D:D, UTIL!B:B, "", 2), IFERROR(_xlfn.XLOOKUP("*"&_xlpm.modelo&"*", UTIL!E:E, UTIL!B:B, "", 2), "")), _xlpm.tipoMod, IF(_xlpm.nomeMod="", "", IFERROR(LEFT(_xlpm.nomeMod, FIND(" ", _xlpm.nomeMod)-1), _xlpm.nomeMod)), _xlpm.dimMod, IFERROR(_xlfn.XLOOKUP("*"&_xlpm.modelo&"*", UTIL!D:D, UTIL!K:K, "", 2), IFERROR(_xlfn.XLOOKUP("*"&_xlpm.modelo&"*", UTIL!E:E, UTIL!K:K, "", 2), "")), _xlpm.tipotxt_antigo, IF(_xlpm.ehTrator, "TRATOR", IFERROR(_xlfn.XLOOKUP(_xlpm.chave, _xlpm.fonte, UTIL!BP:BP, "", 0), IFERROR(_xlfn.XLOOKUP("*"&_xlpm.chave&"*", _xlpm.fonte, UTIL!BP:BP, "", 2), "Não encontrado"))), _xlpm.dimtxt_antigo, IFERROR(_xlfn.XLOOKUP(_xlpm.chave, _xlpm.fonte, UTIL!BY:BY, "", 0), IFERROR(_xlfn.XLOOKUP("*"&_xlpm.chave&"*", _xlpm.fonte, UTIL!BY:BY, "", 2), "Não encontrado")), _xlpm.tipotxt, IF(_xlpm.tipoMod<>"", _xlpm.tipoMod, _xlpm.tipotxt_antigo), _xlpm.dimtxt, IF(_xlpm.dimMod<>"", _xlpm.dimMod, _xlpm.dimtxt_antigo), _xlpm.deTxt, IF(L16="CLIENTE", O16, IF(LEFT(L16,4)="http", L16, "MACPONTA AGRO DE "&L16)), _xlpm.paraBase, IF(M16="CLIENTE", P16, M16), _xlpm.paraTxt, IF(LEFT(_xlpm.paraBase,4)="http", _xlpm.paraBase, "MACPONTA AGRO DE "&_xlpm.paraBase), _xlpm.nfParte, IF(LEN(TRIM(I16))=0, "", " -NF "&TRIM(I16)), "- " & _xlpm.tipotxt & ": *" & G16 & "*" & CHAR(13)&CHAR(10) & "- " & _xlpm.dimtxt & CHAR(13)&CHAR(10) & "- *Cliente*: " & J16 & _xlpm.nfParte & CHAR(13)&CHAR(10) & "- *Obs:* " & Q16 & CHAR(13)&CHAR(10) & CHAR(10) & "- *De*: " & _xlpm.deTxt & CHAR(13)&CHAR(10) & "- *Para*: " & _xlpm.paraTxt & CHAR(13)&CHAR(10) & "- *Ida e volta*: +/- " & TEXT(((D16*1.5)/1440),"h:mm") & "h | " & D16 & "km" )} -> - PLATAFORMA: *1CQ0630AHR0155127*_x000D_ - A:1,60 x C:9,14 x L:1,80-1,80 x P:2.871kg_x000D_ - *Cliente*: MARCELO RIBEIRO DE NARDI -NF278794 -NF 45966_x000D_ - *Obs:* DANILO - MARCELO _x000D_ - *De*: MACPONTA AGRO DE PONTA GROSSA_x000D_ - *Para*: https://maps.app.goo.gl/2DJawZBMR4yqycss9_x000D_ - *Ida e volta*: +/- 3:45h | 150km
A17: CONCLUIDO (D) | B17: PROPRIO DAF | C17: =IFERROR((D17*1.5)/1440, "?") -> 0.15625 | D17: 150 | E17: 500 | G17: 1CQS550AER0155105 | H17: 45966 | I17: 45966 | J17: MARCELO RIBEIRO DE NARDI -NF278794 | K17: marcos.ribas | L17: PONTA GROSSA | M17: CLIENTE | N17: DE LOJA PARA CLIENTE | O17: MPA | P17: https://maps.app.goo.gl/2DJawZBMR4yqycss9 | Q17: DANILO - MARCELO | R17: PONTA GROSSA | S17: COLHEITADEIRA | T17: =IF( OR( IFERROR(FIND("BM",G17),0)>0, IFERROR(FIND("PY",G17),0)>0 ), MID(TRIM(SUBSTITUTE(SUBSTITUTE(G17,CHAR(160),""),CHAR(9),"")),4,5), MID(TRIM(SUBSTITUTE(SUBSTITUTE(G17,CHAR(160),""),CHAR(9),"")),4,4) ) -> S550 | U17: {=_xlfn.LET( _xlpm.ch, TRIM(SUBSTITUTE(G17,CHAR(160),"")), _xlpm.ehTrator, OR(IFERROR(FIND("BM",_xlpm.ch),0)>0, IFERROR(FIND("PY",_xlpm.ch),0)>0), _xlpm.chave, IF(_xlpm.ehTrator, MID(_xlpm.ch,4,5), MID(_xlpm.ch,4,4)), _xlpm.fonte, IF(LEN(_xlpm.chave)=5, UTIL!BS:BS, UTIL!BR:BR), _xlpm.modelo, TRIM(SUBSTITUTE(T17,CHAR(160),"")), _xlpm.nomeMod, IFERROR(_xlfn.XLOOKUP("*"&_xlpm.modelo&"*", UTIL!D:D, UTIL!B:B, "", 2), IFERROR(_xlfn.XLOOKUP("*"&_xlpm.modelo&"*", UTIL!E:E, UTIL!B:B, "", 2), "")), _xlpm.tipoMod, IF(_xlpm.nomeMod="", "", IFERROR(LEFT(_xlpm.nomeMod, FIND(" ", _xlpm.nomeMod)-1), _xlpm.nomeMod)), _xlpm.dimMod, IFERROR(_xlfn.XLOOKUP("*"&_xlpm.modelo&"*", UTIL!D:D, UTIL!K:K, "", 2), IFERROR(_xlfn.XLOOKUP("*"&_xlpm.modelo&"*", UTIL!E:E, UTIL!K:K, "", 2), "")), _xlpm.tipotxt_antigo, IF(_xlpm.ehTrator, "TRATOR", IFERROR(_xlfn.XLOOKUP(_xlpm.chave, _xlpm.fonte, UTIL!BP:BP, "", 0), IFERROR(_xlfn.XLOOKUP("*"&_xlpm.chave&"*", _xlpm.fonte, UTIL!BP:BP, "", 2), "Não encontrado"))), _xlpm.dimtxt_antigo, IFERROR(_xlfn.XLOOKUP(_xlpm.chave, _xlpm.fonte, UTIL!BY:BY, "", 0), IFERROR(_xlfn.XLOOKUP("*"&_xlpm.chave&"*", _xlpm.fonte, UTIL!BY:BY, "", 2), "Não encontrado")), _xlpm.tipotxt, IF(_xlpm.tipoMod<>"", _xlpm.tipoMod, _xlpm.tipotxt_antigo), _xlpm.dimtxt, IF(_xlpm.dimMod<>"", _xlpm.dimMod, _xlpm.dimtxt_antigo), _xlpm.deTxt, IF(L17="CLIENTE", O17, IF(LEFT(L17,4)="http", L17, "MACPONTA AGRO DE "&L17)), _xlpm.paraBase, IF(M17="CLIENTE", P17, M17), _xlpm.paraTxt, IF(LEFT(_xlpm.paraBase,4)="http", _xlpm.paraBase, "MACPONTA AGRO DE "&_xlpm.paraBase), _xlpm.nfParte, IF(LEN(TRIM(I17))=0, "", " -NF "&TRIM(I17)), "- " & _xlpm.tipotxt & ": *" & G17 & "*" & CHAR(13)&CHAR(10) & "- " & _xlpm.dimtxt & CHAR(13)&CHAR(10) & "- *Cliente*: " & J17 & _xlpm.nfParte & CHAR(13)&CHAR(10) & "- *Obs:* " & Q17 & CHAR(13)&CHAR(10) & CHAR(10) & "- *De*: " & _xlpm.deTxt & CHAR(13)&CHAR(10) & "- *Para*: " & _xlpm.paraTxt & CHAR(13)&CHAR(10) & "- *Ida e volta*: +/- " & TEXT(((D17*1.5)/1440),"h:mm") & "h | " & D17 & "km" )} -> - COLHEITADEIRA: *1CQS550AER0155105*_x000D_ - A:3,80 x C:10,00 x L:3,70-4,20 x P:15.938kg_x000D_ - *Cliente*: MARCELO RIBEIRO DE NARDI -NF278794 -NF 45966_x000D_ - *Obs:* DANILO - MARCELO _x000D_ - *De*: MACPONTA AGRO DE PONTA GROSSA_x000D_ - *Para*: https://maps.app.goo.gl/2DJawZBMR4yqycss9_x000D_ - *Ida e volta*: +/- 3:45h | 150km
A18: CONCLUIDO | B18: PROPRIO VW | C18: =IFERROR((D18*1.5)/1440, "?") -> 0.25520833 | D18: 245 | E18: =IFERROR((D18*6),"?") -> 1470 | G18: 1BM6135MCSH000563 | H18: 45967 | I18: 45967 | J18: WILLEM HENDRIK VAN DE RIET -NF109953 | K18: fernando.wiesinies | L18: IRATI | M18: CLIENTE | N18: DE LOJA PARA CLIENTE | O18: MPA | P18: https://maps.app.goo.gl/B5W3gFAkVjKrxcms8 | Q18: (42)999730047 Willen | R18: IRATI | S18: TRATOR | T18: =IF( OR( IFERROR(FIND("BM",G18),0)>0, IFERROR(FIND("PY",G18),0)>0 ), MID(TRIM(SUBSTITUTE(SUBSTITUTE(G18,CHAR(160),""),CHAR(9),"")),4,5), MID(TRIM(SUBSTITUTE(SUBSTITUTE(G18,CHAR(160),""),CHAR(9),"")),4,4) ) -> 6135M | U18: {=_xlfn.LET( _xlpm.ch, TRIM(SUBSTITUTE(G18,CHAR(160),"")), _xlpm.ehTrator, OR(IFERROR(FIND("BM",_xlpm.ch),0)>0, IFERROR(FIND("PY",_xlpm.ch),0)>0), _xlpm.chave, IF(_xlpm.ehTrator, MID(_xlpm.ch,4,5), MID(_xlpm.ch,4,4)), _xlpm.fonte, IF(LEN(_xlpm.chave)=5, UTIL!BS:BS, UTIL!BR:BR), _xlpm.modelo, TRIM(SUBSTITUTE(T18,CHAR(160),"")), _xlpm.nomeMod, IFERROR(_xlfn.XLOOKUP("*"&_xlpm.modelo&"*", UTIL!D:D, UTIL!B:B, "", 2), IFERROR(_xlfn.XLOOKUP("*"&_xlpm.modelo&"*", UTIL!E:E, UTIL!B:B, "", 2), "")), _xlpm.tipoMod, IF(_xlpm.nomeMod="", "", IFERROR(LEFT(_xlpm.nomeMod, FIND(" ", _xlpm.nomeMod)-1), _xlpm.nomeMod)), _xlpm.dimMod, IFERROR(_xlfn.XLOOKUP("*"&_xlpm.modelo&"*", UTIL!D:D, UTIL!K:K, "", 2), IFERROR(_xlfn.XLOOKUP("*"&_xlpm.modelo&"*", UTIL!E:E, UTIL!K:K, "", 2), "")), _xlpm.tipotxt_antigo, IF(_xlpm.ehTrator, "TRATOR", IFERROR(_xlfn.XLOOKUP(_xlpm.chave, _xlpm.fonte, UTIL!BP:BP, "", 0), IFERROR(_xlfn.XLOOKUP("*"&_xlpm.chave&"*", _xlpm.fonte, UTIL!BP:BP, "", 2), "Não encontrado"))), _xlpm.dimtxt_antigo, IFERROR(_xlfn.XLOOKUP(_xlpm.chave, _xlpm.fonte, UTIL!BY:BY, "", 0), IFERROR(_xlfn.XLOOKUP("*"&_xlpm.chave&"*", _xlpm.fonte, UTIL!BY:BY, "", 2), "Não encontrado")), _xlpm.tipotxt, IF(_xlpm.tipoMod<>"", _xlpm.tipoMod, _xlpm.tipotxt_antigo), _xlpm.dimtxt, IF(_xlpm.dimMod<>"", _xlpm.dimMod, _xlpm.dimtxt_antigo), _xlpm.deTxt, IF(L18="CLIENTE", O18, IF(LEFT(L18,4)="http", L18, "MACPONTA AGRO DE "&L18)), _xlpm.paraBase, IF(M18="CLIENTE", P18, M18), _xlpm.paraTxt, IF(LEFT(_xlpm.paraBase,4)="http", _xlpm.paraBase, "MACPONTA AGRO DE "&_xlpm.paraBase), _xlpm.nfParte, IF(LEN(TRIM(I18))=0, "", " -NF "&TRIM(I18)), "- " & _xlpm.tipotxt & ": *" & G18 & "*" & CHAR(13)&CHAR(10) & "- " & _xlpm.dimtxt & CHAR(13)&CHAR(10) & "- *Cliente*: " & J18 & _xlpm.nfParte & CHAR(13)&CHAR(10) & "- *Obs:* " & Q18 & CHAR(13)&CHAR(10) & CHAR(10) & "- *De*: " & _xlpm.deTxt & CHAR(13)&CHAR(10) & "- *Para*: " & _xlpm.paraTxt & CHAR(13)&CHAR(10) & "- *Ida e volta*: +/- " & TEXT(((D18*1.5)/1440),"h:mm") & "h | " & D18 & "km" )} -> - TRATOR: *1BM6135MCSH000563*_x000D_ - _x000D_ - *Cliente*: WILLEM HENDRIK VAN DE RIET -NF109953 -NF 45967_x000D_ - *Obs:* (42)999730047 Willen _x000D_ - *De*: MACPONTA AGRO DE IRATI_x000D_ - *Para*: https://maps.app.goo.gl/B5W3gFAkVjKrxcms8_x000D_ - *Ida e volta*: +/- 6:07h | 245km
A19: CONCLUIDO | B19: PROPRIO DAF | C19: =IFERROR((D19*1.5)/1440, "?") -> 0.18229167 | D19: 175 | E19: =IFERROR((D19*6),"?") -> 1050 | G19: 1CQS680ATF0110209 | H19: 45968 | I19: 45969 | J19: DOUGLAS FANCHIN TAQUES FONSECA -NF278835 | K19: marcelo.ferreira | L19: PONTA GROSSA | M19: CLIENTE | N19: DE LOJA PARA CLIENTE | O19: MPA | P19: https://maps.app.goo.gl/GfTKV558G2iXHWmg8 | Q19: VALTINHO 42-99920-3056 | R19: PONTA GROSSA | S19: COLHEITADEIRA | T19: =IF( OR( IFERROR(FIND("BM",G19),0)>0, IFERROR(FIND("PY",G19),0)>0 ), MID(TRIM(SUBSTITUTE(SUBSTITUTE(G19,CHAR(160),""),CHAR(9),"")),4,5), MID(TRIM(SUBSTITUTE(SUBSTITUTE(G19,CHAR(160),""),CHAR(9),"")),4,4) ) -> S680 | U19: {=_xlfn.LET( _xlpm.ch, TRIM(SUBSTITUTE(G19,CHAR(160),"")), _xlpm.ehTrator, OR(IFERROR(FIND("BM",_xlpm.ch),0)>0, IFERROR(FIND("PY",_xlpm.ch),0)>0), _xlpm.chave, IF(_xlpm.ehTrator, MID(_xlpm.ch,4,5), MID(_xlpm.ch,4,4)), _xlpm.fonte, IF(LEN(_xlpm.chave)=5, UTIL!BS:BS, UTIL!BR:BR), _xlpm.modelo, TRIM(SUBSTITUTE(T19,CHAR(160),"")), _xlpm.nomeMod, IFERROR(_xlfn.XLOOKUP("*"&_xlpm.modelo&"*", UTIL!D:D, UTIL!B:B, "", 2), IFERROR(_xlfn.XLOOKUP("*"&_xlpm.modelo&"*", UTIL!E:E, UTIL!B:B, "", 2), "")), _xlpm.tipoMod, IF(_xlpm.nomeMod="", "", IFERROR(LEFT(_xlpm.nomeMod, FIND(" ", _xlpm.nomeMod)-1), _xlpm.nomeMod)), _xlpm.dimMod, IFERROR(_xlfn.XLOOKUP("*"&_xlpm.modelo&"*", UTIL!D:D, UTIL!K:K, "", 2), IFERROR(_xlfn.XLOOKUP("*"&_xlpm.modelo&"*", UTIL!E:E, UTIL!K:K, "", 2), "")), _xlpm.tipotxt_antigo, IF(_xlpm.ehTrator, "TRATOR", IFERROR(_xlfn.XLOOKUP(_xlpm.chave, _xlpm.fonte, UTIL!BP:BP, "", 0), IFERROR(_xlfn.XLOOKUP("*"&_xlpm.chave&"*", _xlpm.fonte, UTIL!BP:BP, "", 2), "Não encontrado"))), _xlpm.dimtxt_antigo, IFERROR(_xlfn.XLOOKUP(_xlpm.chave, _xlpm.fonte, UTIL!BY:BY, "", 0), IFERROR(_xlfn.XLOOKUP("*"&_xlpm.chave&"*", _xlpm.fonte, UTIL!BY:BY, "", 2), "Não encontrado")), _xlpm.tipotxt, IF(_xlpm.tipoMod<>"", _xlpm.tipoMod, _xlpm.tipotxt_antigo), _xlpm.dimtxt, IF(_xlpm.dimMod<>"", _xlpm.dimMod, _xlpm.dimtxt_antigo), _xlpm.deTxt, IF(L19="CLIENTE", O19, IF(LEFT(L19,4)="http", L19, "MACPONTA AGRO DE "&L19)), _xlpm.paraBase, IF(M19="CLIENTE", P19, M19), _xlpm.paraTxt, IF(LEFT(_xlpm.paraBase,4)="http", _xlpm.paraBase, "MACPONTA AGRO DE "&_xlpm.paraBase), _xlpm.nfParte, IF(LEN(TRIM(I19))=0, "", " -NF "&TRIM(I19)), "- " & _xlpm.tipotxt & ": *" & G19 & "*" & CHAR(13)&CHAR(10) & "- " & _xlpm.dimtxt & CHAR(13)&CHAR(10) & "- *Cliente*: " & J19 & _xlpm.nfParte & CHAR(13)&CHAR(10) & "- *Obs:* " & Q19 & CHAR(13)&CHAR(10) & CHAR(10) & "- *De*: " & _xlpm.deTxt & CHAR(13)&CHAR(10) & "- *Para*: " & _xlpm.paraTxt & CHAR(13)&CHAR(10) & "- *Ida e volta*: +/- " & TEXT(((D19*1.5)/1440),"h:mm") & "h | " & D19 & "km" )} -> - COLHEITADEIRA: *1CQS680ATF0110209*_x000D_ - A:3,98 x C:12,10 x L:3,50-5,43 x P:21.921kg_x000D_ - *Cliente*: DOUGLAS FANCHIN TAQUES FONSECA -NF278835 -NF 45969_x000D_ - *Obs:* VALTINHO 42-99920-3056_x000D_ - *De*: MACPONTA AGRO DE PONTA GROSSA_x000D_ - *Para*: https://maps.app.goo.gl/GfTKV558G2iXHWmg8_x000D_ - *Ida e volta*: +/- 4:22h | 175km
A20: CONCLUIDO | B20: PROPRIO DAF | C20: =IFERROR((D20*1.5)/1440, "?") -> 0.18229167 | D20: 175 | E20: =IFERROR((D20*6),"?") -> 1050 | G20: 1BM6180JKDD001849 | H20: 45968 | I20: 45968 | J20: MANUTENÇÃO → CLIENTE | K20: gustavo.erdmann | L20: PONTA GROSSA | M20: CLIENTE | N20: DE LOJA PARA CLIENTE | O20: MPA | P20: https://maps.app.goo.gl/Yk2FrxveQ1BNpLmN8 | Q20: Cassio | R20: PONTA GROSSA | S20: TRATOR | T20: =IF( OR( IFERROR(FIND("BM",G20),0)>0, IFERROR(FIND("PY",G20),0)>0 ), MID(TRIM(SUBSTITUTE(SUBSTITUTE(G20,CHAR(160),""),CHAR(9),"")),4,5), MID(TRIM(SUBSTITUTE(SUBSTITUTE(G20,CHAR(160),""),CHAR(9),"")),4,4) ) -> 6180J | U20: {=_xlfn.LET( _xlpm.ch, TRIM(SUBSTITUTE(G20,CHAR(160),"")), _xlpm.ehTrator, OR(IFERROR(FIND("BM",_xlpm.ch),0)>0, IFERROR(FIND("PY",_xlpm.ch),0)>0), _xlpm.chave, IF(_xlpm.ehTrator, MID(_xlpm.ch,4,5), MID(_xlpm.ch,4,4)), _xlpm.fonte, IF(LEN(_xlpm.chave)=5, UTIL!BS:BS, UTIL!BR:BR), _xlpm.modelo, TRIM(SUBSTITUTE(T20,CHAR(160),"")), _xlpm.nomeMod, IFERROR(_xlfn.XLOOKUP("*"&_xlpm.modelo&"*", UTIL!D:D, UTIL!B:B, "", 2), IFERROR(_xlfn.XLOOKUP("*"&_xlpm.modelo&"*", UTIL!E:E, UTIL!B:B, "", 2), "")), _xlpm.tipoMod, IF(_xlpm.nomeMod="", "", IFERROR(LEFT(_xlpm.nomeMod, FIND(" ", _xlpm.nomeMod)-1), _xlpm.nomeMod)), _xlpm.dimMod, IFERROR(_xlfn.XLOOKUP("*"&_xlpm.modelo&"*", UTIL!D:D, UTIL!K:K, "", 2), IFERROR(_xlfn.XLOOKUP("*"&_xlpm.modelo&"*", UTIL!E:E, UTIL!K:K, "", 2), "")), _xlpm.tipotxt_antigo, IF(_xlpm.ehTrator, "TRATOR", IFERROR(_xlfn.XLOOKUP(_xlpm.chave, _xlpm.fonte, UTIL!BP:BP, "", 0), IFERROR(_xlfn.XLOOKUP("*"&_xlpm.chave&"*", _xlpm.fonte, UTIL!BP:BP, "", 2), "Não encontrado"))), _xlpm.dimtxt_antigo, IFERROR(_xlfn.XLOOKUP(_xlpm.chave, _xlpm.fonte, UTIL!BY:BY, "", 0), IFERROR(_xlfn.XLOOKUP("*"&_xlpm.chave&"*", _xlpm.fonte, UTIL!BY:BY, "", 2), "Não encontrado")), _xlpm.tipotxt, IF(_xlpm.tipoMod<>"", _xlpm.tipoMod, _xlpm.tipotxt_antigo), _xlpm.dimtxt, IF(_xlpm.dimMod<>"", _xlpm.dimMod, _xlpm.dimtxt_antigo), _xlpm.deTxt, IF(L20="CLIENTE", O20, IF(LEFT(L20,4)="http", L20, "MACPONTA AGRO DE "&L20)), _xlpm.paraBase, IF(M20="CLIENTE", P20, M20), _xlpm.paraTxt, IF(LEFT(_xlpm.paraBase,4)="http", _xlpm.paraBase, "MACPONTA AGRO DE "&_xlpm.paraBase), _xlpm.nfParte, IF(LEN(TRIM(I20))=0, "", " -NF "&TRIM(I20)), "- " & _xlpm.tipotxt & ": *" & G20 & "*" & CHAR(13)&CHAR(10) & "- " & _xlpm.dimtxt & CHAR(13)&CHAR(10) & "- *Cliente*: " & J20 & _xlpm.nfParte & CHAR(13)&CHAR(10) & "- *Obs:* " & Q20 & CHAR(13)&CHAR(10) & CHAR(10) & "- *De*: " & _xlpm.deTxt & CHAR(13)&CHAR(10) & "- *Para*: " & _xlpm.paraTxt & CHAR(13)&CHAR(10) & "- *Ida e volta*: +/- " & TEXT(((D20*1.5)/1440),"h:mm") & "h | " & D20 & "km" )} -> - TRATOR: *1BM6180JKDD001849*_x000D_ - _x000D_ - *Cliente*: MANUTENÇÃO → CLIENTE -NF 45968_x000D_ - *Obs:* Cassio_x000D_ - *De*: MACPONTA AGRO DE PONTA GROSSA_x000D_ - *Para*: https://maps.app.goo.gl/Yk2FrxveQ1BNpLmN8_x000D_ - *Ida e volta*: +/- 4:22h | 175km
A21: CONCLUIDO | B21: TERCEIRO MAZETTO | C21: =IFERROR((D21*1.5)/1440, "?") -> 0.34375 | D21: 330 | F21: 2890 | G21: 1BM6100JVSD602522 | H21: 45968 | I21: 45968 | J21: ADILSON KRASSOSKI -NF11620 | K21: euclides.junior | L21: GUARAPUAVA | M21: CLIENTE | N21: DE LOJA PARA CLIENTE | O21: MPA | P21: https://maps.app.goo.gl/nUnfbBeivgDPDFmy6 | Q21: Adilson | R21: GUARAPUAVA | S21: TRATOR | T21: =IF( OR( IFERROR(FIND("BM",G21),0)>0, IFERROR(FIND("PY",G21),0)>0 ), MID(TRIM(SUBSTITUTE(SUBSTITUTE(G21,CHAR(160),""),CHAR(9),"")),4,5), MID(TRIM(SUBSTITUTE(SUBSTITUTE(G21,CHAR(160),""),CHAR(9),"")),4,4) ) -> 6100J | U21: {=_xlfn.LET( _xlpm.ch, TRIM(SUBSTITUTE(G21,CHAR(160),"")), _xlpm.ehTrator, OR(IFERROR(FIND("BM",_xlpm.ch),0)>0, IFERROR(FIND("PY",_xlpm.ch),0)>0), _xlpm.chave, IF(_xlpm.ehTrator, MID(_xlpm.ch,4,5), MID(_xlpm.ch,4,4)), _xlpm.fonte, IF(LEN(_xlpm.chave)=5, UTIL!BS:BS, UTIL!BR:BR), _xlpm.modelo, TRIM(SUBSTITUTE(T21,CHAR(160),"")), _xlpm.nomeMod, IFERROR(_xlfn.XLOOKUP("*"&_xlpm.modelo&"*", UTIL!D:D, UTIL!B:B, "", 2), IFERROR(_xlfn.XLOOKUP("*"&_xlpm.modelo&"*", UTIL!E:E, UTIL!B:B, "", 2), "")), _xlpm.tipoMod, IF(_xlpm.nomeMod="", "", IFERROR(LEFT(_xlpm.nomeMod, FIND(" ", _xlpm.nomeMod)-1), _xlpm.nomeMod)), _xlpm.dimMod, IFERROR(_xlfn.XLOOKUP("*"&_xlpm.modelo&"*", UTIL!D:D, UTIL!K:K, "", 2), IFERROR(_xlfn.XLOOKUP("*"&_xlpm.modelo&"*", UTIL!E:E, UTIL!K:K, "", 2), "")), _xlpm.tipotxt_antigo, IF(_xlpm.ehTrator, "TRATOR", IFERROR(_xlfn.XLOOKUP(_xlpm.chave, _xlpm.fonte, UTIL!BP:BP, "", 0), IFERROR(_xlfn.XLOOKUP("*"&_xlpm.chave&"*", _xlpm.fonte, UTIL!BP:BP, "", 2), "Não encontrado"))), _xlpm.dimtxt_antigo, IFERROR(_xlfn.XLOOKUP(_xlpm.chave, _xlpm.fonte, UTIL!BY:BY, "", 0), IFERROR(_xlfn.XLOOKUP("*"&_xlpm.chave&"*", _xlpm.fonte, UTIL!BY:BY, "", 2), "Não encontrado")), _xlpm.tipotxt, IF(_xlpm.tipoMod<>"", _xlpm.tipoMod, _xlpm.tipotxt_antigo), _xlpm.dimtxt, IF(_xlpm.dimMod<>"", _xlpm.dimMod, _xlpm.dimtxt_antigo), _xlpm.deTxt, IF(L21="CLIENTE", O21, IF(LEFT(L21,4)="http", L21, "MACPONTA AGRO DE "&L21)), _xlpm.paraBase, IF(M21="CLIENTE", P21, M21), _xlpm.paraTxt, IF(LEFT(_xlpm.paraBase,4)="http", _xlpm.paraBase, "MACPONTA AGRO DE "&_xlpm.paraBase), _xlpm.nfParte, IF(LEN(TRIM(I21))=0, "", " -NF "&TRIM(I21)), "- " & _xlpm.tipotxt & ": *" & G21 & "*" & CHAR(13)&CHAR(10) & "- " & _xlpm.dimtxt & CHAR(13)&CHAR(10) & "- *Cliente*: " & J21 & _xlpm.nfParte & CHAR(13)&CHAR(10) & "- *Obs:* " & Q21 & CHAR(13)&CHAR(10) & CHAR(10) & "- *De*: " & _xlpm.deTxt & CHAR(13)&CHAR(10) & "- *Para*: " & _xlpm.paraTxt & CHAR(13)&CHAR(10) & "- *Ida e volta*: +/- " & TEXT(((D21*1.5)/1440),"h:mm") & "h | " & D21 & "km" )} -> - TRATOR: *1BM6100JVSD602522*_x000D_ - _x000D_ - *Cliente*: ADILSON KRASSOSKI -NF11620 -NF 45968_x000D_ - *Obs:* Adilson_x000D_ - *De*: MACPONTA AGRO DE GUARAPUAVA_x000D_ - *Para*: https://maps.app.goo.gl/nUnfbBeivgDPDFmy6_x000D_ - *Ida e volta*: +/- 8:15h | 330km
A22: CONCLUIDO | B22: PROPRIO DAF | C22: =IFERROR((D22*1.5)/1440, "?") -> 0.33854167 | D22: 325 | E22: =IFERROR((D22*6),"?") -> 1950 | G22: AAAP1112CGS000944 | H22: 45972 | I22: 45972 | J22: TRANSF -NF000076886 | K22: marcio.jacovossi | L22: IRATI | M22: PRUDENTÓPOLIS | N22: DE LOJA PARA LOJA | O22: MPA | P22: MPA | Q22: N/A | R22: IRATI | S22: COLHEITADEIRA | T22: =IF( OR( IFERROR(FIND("BM",G22),0)>0, IFERROR(FIND("PY",G22),0)>0 ), MID(TRIM(SUBSTITUTE(SUBSTITUTE(G22,CHAR(160),""),CHAR(9),"")),4,5), MID(TRIM(SUBSTITUTE(SUBSTITUTE(G22,CHAR(160),""),CHAR(9),"")),4,4) ) -> P111 | U22: {=_xlfn.LET( _xlpm.ch, TRIM(SUBSTITUTE(G22,CHAR(160),"")), _xlpm.ehTrator, OR(IFERROR(FIND("BM",_xlpm.ch),0)>0, IFERROR(FIND("PY",_xlpm.ch),0)>0), _xlpm.chave, IF(_xlpm.ehTrator, MID(_xlpm.ch,4,5), MID(_xlpm.ch,4,4)), _xlpm.fonte, IF(LEN(_xlpm.chave)=5, UTIL!BS:BS, UTIL!BR:BR), _xlpm.modelo, TRIM(SUBSTITUTE(T22,CHAR(160),"")), _xlpm.nomeMod, IFERROR(_xlfn.XLOOKUP("*"&_xlpm.modelo&"*", UTIL!D:D, UTIL!B:B, "", 2), IFERROR(_xlfn.XLOOKUP("*"&_xlpm.modelo&"*", UTIL!E:E, UTIL!B:B, "", 2), "")), _xlpm.tipoMod, IF(_xlpm.nomeMod="", "", IFERROR(LEFT(_xlpm.nomeMod, FIND(" ", _xlpm.nomeMod)-1), _xlpm.nomeMod)), _xlpm.dimMod, IFERROR(_xlfn.XLOOKUP("*"&_xlpm.modelo&"*", UTIL!D:D, UTIL!K:K, "", 2), IFERROR(_xlfn.XLOOKUP("*"&_xlpm.modelo&"*", UTIL!E:E, UTIL!K:K, "", 2), "")), _xlpm.tipotxt_antigo, IF(_xlpm.ehTrator, "TRATOR", IFERROR(_xlfn.XLOOKUP(_xlpm.chave, _xlpm.fonte, UTIL!BP:BP, "", 0), IFERROR(_xlfn.XLOOKUP("*"&_xlpm.chave&"*", _xlpm.fonte, UTIL!BP:BP, "", 2), "Não encontrado"))), _xlpm.dimtxt_antigo, IFERROR(_xlfn.XLOOKUP(_xlpm.chave, _xlpm.fonte, UTIL!BY:BY, "", 0), IFERROR(_xlfn.XLOOKUP("*"&_xlpm.chave&"*", _xlpm.fonte, UTIL!BY:BY, "", 2), "Não encontrado")), _xlpm.tipotxt, IF(_xlpm.tipoMod<>"", _xlpm.tipoMod, _xlpm.tipotxt_antigo), _xlpm.dimtxt, IF(_xlpm.dimMod<>"", _xlpm.dimMod, _xlpm.dimtxt_antigo), _xlpm.deTxt, IF(L22="CLIENTE", O22, IF(LEFT(L22,4)="http", L22, "MACPONTA AGRO DE "&L22)), _xlpm.paraBase, IF(M22="CLIENTE", P22, M22), _xlpm.paraTxt, IF(LEFT(_xlpm.paraBase,4)="http", _xlpm.paraBase, "MACPONTA AGRO DE "&_xlpm.paraBase), _xlpm.nfParte, IF(LEN(TRIM(I22))=0, "", " -NF "&TRIM(I22)), "- " & _xlpm.tipotxt & ": *" & G22 & "*" & CHAR(13)&CHAR(10) & "- " & _xlpm.dimtxt & CHAR(13)&CHAR(10) & "- *Cliente*: " & J22 & _xlpm.nfParte & CHAR(13)&CHAR(10) & "- *Obs:* " & Q22 & CHAR(13)&CHAR(10) & CHAR(10) & "- *De*: " & _xlpm.deTxt & CHAR(13)&CHAR(10) & "- *Para*: " & _xlpm.paraTxt & CHAR(13)&CHAR(10) & "- *Ida e volta*: +/- " & TEXT(((D22*1.5)/1440),"h:mm") & "h | " & D22 & "km" )} -> - : *AAAP1112CGS000944*_x000D_ - _x000D_ - *Cliente*: TRANSF -NF000076886 -NF 45972_x000D_ - *Obs:* N/A_x000D_ - *De*: MACPONTA AGRO DE IRATI_x000D_ - *Para*: MACPONTA AGRO DE PRUDENTÓPOLIS_x000D_ - *Ida e volta*: +/- 8:07h | 325km
A23: CONCLUIDO | B23: PROPRIO DAF | C23: =IFERROR((D23*1.5)/1440, "?") -> 0.265625 | D23: 255 | E23: =IFERROR((D23*6),"?") -> 1530 | G23: 1BM5078EHS4200616 | H23: 45972 | I23: 45972 | J23: TRANSF -NF000076884 | K23: marcio.jacovossi | L23: IRATI | M23: PRUDENTÓPOLIS | N23: DE LOJA PARA LOJA | O23: MPA | P23: MPA | Q23: N/A | R23: IRATI | S23: TRATOR | T23: =IF( OR( IFERROR(FIND("BM",G23),0)>0, IFERROR(FIND("PY",G23),0)>0 ), MID(TRIM(SUBSTITUTE(SUBSTITUTE(G23,CHAR(160),""),CHAR(9),"")),4,5), MID(TRIM(SUBSTITUTE(SUBSTITUTE(G23,CHAR(160),""),CHAR(9),"")),4,4) ) -> 5078E | U23: {=_xlfn.LET( _xlpm.ch, TRIM(SUBSTITUTE(G23,CHAR(160),"")), _xlpm.ehTrator, OR(IFERROR(FIND("BM",_xlpm.ch),0)>0, IFERROR(FIND("PY",_xlpm.ch),0)>0), _xlpm.chave, IF(_xlpm.ehTrator, MID(_xlpm.ch,4,5), MID(_xlpm.ch,4,4)), _xlpm.fonte, IF(LEN(_xlpm.chave)=5, UTIL!BS:BS, UTIL!BR:BR), _xlpm.modelo, TRIM(SUBSTITUTE(T23,CHAR(160),"")), _xlpm.nomeMod, IFERROR(_xlfn.XLOOKUP("*"&_xlpm.modelo&"*", UTIL!D:D, UTIL!B:B, "", 2), IFERROR(_xlfn.XLOOKUP("*"&_xlpm.modelo&"*", UTIL!E:E, UTIL!B:B, "", 2), "")), _xlpm.tipoMod, IF(_xlpm.nomeMod="", "", IFERROR(LEFT(_xlpm.nomeMod, FIND(" ", _xlpm.nomeMod)-1), _xlpm.nomeMod)), _xlpm.dimMod, IFERROR(_xlfn.XLOOKUP("*"&_xlpm.modelo&"*", UTIL!D:D, UTIL!K:K, "", 2), IFERROR(_xlfn.XLOOKUP("*"&_xlpm.modelo&"*", UTIL!E:E, UTIL!K:K, "", 2), "")), _xlpm.tipotxt_antigo, IF(_xlpm.ehTrator, "TRATOR", IFERROR(_xlfn.XLOOKUP(_xlpm.chave, _xlpm.fonte, UTIL!BP:BP, "", 0), IFERROR(_xlfn.XLOOKUP("*"&_xlpm.chave&"*", _xlpm.fonte, UTIL!BP:BP, "", 2), "Não encontrado"))), _xlpm.dimtxt_antigo, IFERROR(_xlfn.XLOOKUP(_xlpm.chave, _xlpm.fonte, UTIL!BY:BY, "", 0), IFERROR(_xlfn.XLOOKUP("*"&_xlpm.chave&"*", _xlpm.fonte, UTIL!BY:BY, "", 2), "Não encontrado")), _xlpm.tipotxt, IF(_xlpm.tipoMod<>"", _xlpm.tipoMod, _xlpm.tipotxt_antigo), _xlpm.dimtxt, IF(_xlpm.dimMod<>"", _xlpm.dimMod, _xlpm.dimtxt_antigo), _xlpm.deTxt, IF(L23="CLIENTE", O23, IF(LEFT(L23,4)="http", L23, "MACPONTA AGRO DE "&L23)), _xlpm.paraBase, IF(M23="CLIENTE", P23, M23), _xlpm.paraTxt, IF(LEFT(_xlpm.paraBase,4)="http", _xlpm.paraBase, "MACPONTA AGRO DE "&_xlpm.paraBase), _xlpm.nfParte, IF(LEN(TRIM(I23))=0, "", " -NF "&TRIM(I23)), "- " & _xlpm.tipotxt & ": *" & G23 & "*" & CHAR(13)&CHAR(10) & "- " & _xlpm.dimtxt & CHAR(13)&CHAR(10) & "- *Cliente*: " & J23 & _xlpm.nfParte & CHAR(13)&CHAR(10) & "- *Obs:* " & Q23 & CHAR(13)&CHAR(10) & CHAR(10) & "- *De*: " & _xlpm.deTxt & CHAR(13)&CHAR(10) & "- *Para*: " & _xlpm.paraTxt & CHAR(13)&CHAR(10) & "- *Ida e volta*: +/- " & TEXT(((D23*1.5)/1440),"h:mm") & "h | " & D23 & "km" )} -> - TRATOR: *1BM5078EHS4200616*_x000D_ - _x000D_ - *Cliente*: TRANSF -NF000076884 -NF 45972_x000D_ - *Obs:* N/A_x000D_ - *De*: MACPONTA AGRO DE IRATI_x000D_ - *Para*: MACPONTA AGRO DE PRUDENTÓPOLIS_x000D_ - *Ida e volta*: +/- 6:22h | 255km
A24: CONCLUIDO | B24: PROPRIO DAF | C24: =IFERROR((D24*1.5)/1440, "?") -> 0.265625 | D24: 255 | E24: =IFERROR((D24*6),"?") -> 1530 | G24: 1BM6150JCSD642412 | H24: 45972 | I24: 45972 | J24: TRANSF -NF000076884 | K24: marcio.jacovossi | L24: IRATI | M24: PRUDENTÓPOLIS | N24: DE LOJA PARA LOJA | O24: MPA | P24: MPA | Q24: N/A | R24: IRATI | S24: TRATOR | T24: =IF( OR( IFERROR(FIND("BM",G24),0)>0, IFERROR(FIND("PY",G24),0)>0 ), MID(TRIM(SUBSTITUTE(SUBSTITUTE(G24,CHAR(160),""),CHAR(9),"")),4,5), MID(TRIM(SUBSTITUTE(SUBSTITUTE(G24,CHAR(160),""),CHAR(9),"")),4,4) ) -> 6150J | U24: {=_xlfn.LET( _xlpm.ch, TRIM(SUBSTITUTE(G24,CHAR(160),"")), _xlpm.ehTrator, OR(IFERROR(FIND("BM",_xlpm.ch),0)>0, IFERROR(FIND("PY",_xlpm.ch),0)>0), _xlpm.chave, IF(_xlpm.ehTrator, MID(_xlpm.ch,4,5), MID(_xlpm.ch,4,4)), _xlpm.fonte, IF(LEN(_xlpm.chave)=5, UTIL!BS:BS, UTIL!BR:BR), _xlpm.modelo, TRIM(SUBSTITUTE(T24,CHAR(160),"")), _xlpm.nomeMod, IFERROR(_xlfn.XLOOKUP("*"&_xlpm.modelo&"*", UTIL!D:D, UTIL!B:B, "", 2), IFERROR(_xlfn.XLOOKUP("*"&_xlpm.modelo&"*", UTIL!E:E, UTIL!B:B, "", 2), "")), _xlpm.tipoMod, IF(_xlpm.nomeMod="", "", IFERROR(LEFT(_xlpm.nomeMod, FIND(" ", _xlpm.nomeMod)-1), _xlpm.nomeMod)), _xlpm.dimMod, IFERROR(_xlfn.XLOOKUP("*"&_xlpm.modelo&"*", UTIL!D:D, UTIL!K:K, "", 2), IFERROR(_xlfn.XLOOKUP("*"&_xlpm.modelo&"*", UTIL!E:E, UTIL!K:K, "", 2), "")), _xlpm.tipotxt_antigo, IF(_xlpm.ehTrator, "TRATOR", IFERROR(_xlfn.XLOOKUP(_xlpm.chave, _xlpm.fonte, UTIL!BP:BP, "", 0), IFERROR(_xlfn.XLOOKUP("*"&_xlpm.chave&"*", _xlpm.fonte, UTIL!BP:BP, "", 2), "Não encontrado"))), _xlpm.dimtxt_antigo, IFERROR(_xlfn.XLOOKUP(_xlpm.chave, _xlpm.fonte, UTIL!BY:BY, "", 0), IFERROR(_xlfn.XLOOKUP("*"&_xlpm.chave&"*", _xlpm.fonte, UTIL!BY:BY, "", 2), "Não encontrado")), _xlpm.tipotxt, IF(_xlpm.tipoMod<>"", _xlpm.tipoMod, _xlpm.tipotxt_antigo), _xlpm.dimtxt, IF(_xlpm.dimMod<>"", _xlpm.dimMod, _xlpm.dimtxt_antigo), _xlpm.deTxt, IF(L24="CLIENTE", O24, IF(LEFT(L24,4)="http", L24, "MACPONTA AGRO DE "&L24)), _xlpm.paraBase, IF(M24="CLIENTE", P24, M24), _xlpm.paraTxt, IF(LEFT(_xlpm.paraBase,4)="http", _xlpm.paraBase, "MACPONTA AGRO DE "&_xlpm.paraBase), _xlpm.nfParte, IF(LEN(TRIM(I24))=0, "", " -NF "&TRIM(I24)), "- " & _xlpm.tipotxt & ": *" & G24 & "*" & CHAR(13)&CHAR(10) & "- " & _xlpm.dimtxt & CHAR(13)&CHAR(10) & "- *Cliente*: " & J24 & _xlpm.nfParte & CHAR(13)&CHAR(10) & "- *Obs:* " & Q24 & CHAR(13)&CHAR(10) & CHAR(10) & "- *De*: " & _xlpm.deTxt & CHAR(13)&CHAR(10) & "- *Para*: " & _xlpm.paraTxt & CHAR(13)&CHAR(10) & "- *Ida e volta*: +/- " & TEXT(((D24*1.5)/1440),"h:mm") & "h | " & D24 & "km" )} -> - TRATOR: *1BM6150JCSD642412*_x000D_ - _x000D_ - *Cliente*: TRANSF -NF000076884 -NF 45972_x000D_ - *Obs:* N/A_x000D_ - *De*: MACPONTA AGRO DE IRATI_x000D_ - *Para*: MACPONTA AGRO DE PRUDENTÓPOLIS_x000D_ - *Ida e volta*: +/- 6:22h | 255km
A25: CONCLUIDO | B25: PROPRIO DAF | C25: =IFERROR((D25*1.5)/1440, "?") -> 0.33854167 | D25: 325 | E25: =IFERROR((D25*6),"?") -> 1950 | G25: 9AGC1007EHS000187 | H25: 45972 | I25: 45972 | J25: TRANSF -NF000076891 | K25: marcio.jacovossi | L25: IRATI | M25: PRUDENTÓPOLIS | N25: DE LOJA PARA LOJA | O25: MPA | P25: MPA | Q25: N/A | R25: IRATI | S25: TRATOR | T25: =IF( OR( IFERROR(FIND("BM",G25),0)>0, IFERROR(FIND("PY",G25),0)>0 ), MID(TRIM(SUBSTITUTE(SUBSTITUTE(G25,CHAR(160),""),CHAR(9),"")),4,5), MID(TRIM(SUBSTITUTE(SUBSTITUTE(G25,CHAR(160),""),CHAR(9),"")),4,4) ) -> C100 | U25: {=_xlfn.LET( _xlpm.ch, TRIM(SUBSTITUTE(G25,CHAR(160),"")), _xlpm.ehTrator, OR(IFERROR(FIND("BM",_xlpm.ch),0)>0, IFERROR(FIND("PY",_xlpm.ch),0)>0), _xlpm.chave, IF(_xlpm.ehTrator, MID(_xlpm.ch,4,5), MID(_xlpm.ch,4,4)), _xlpm.fonte, IF(LEN(_xlpm.chave)=5, UTIL!BS:BS, UTIL!BR:BR), _xlpm.modelo, TRIM(SUBSTITUTE(T25,CHAR(160),"")), _xlpm.nomeMod, IFERROR(_xlfn.XLOOKUP("*"&_xlpm.modelo&"*", UTIL!D:D, UTIL!B:B, "", 2), IFERROR(_xlfn.XLOOKUP("*"&_xlpm.modelo&"*", UTIL!E:E, UTIL!B:B, "", 2), "")), _xlpm.tipoMod, IF(_xlpm.nomeMod="", "", IFERROR(LEFT(_xlpm.nomeMod, FIND(" ", _xlpm.nomeMod)-1), _xlpm.nomeMod)), _xlpm.dimMod, IFERROR(_xlfn.XLOOKUP("*"&_xlpm.modelo&"*", UTIL!D:D, UTIL!K:K, "", 2), IFERROR(_xlfn.XLOOKUP("*"&_xlpm.modelo&"*", UTIL!E:E, UTIL!K:K, "", 2), "")), _xlpm.tipotxt_antigo, IF(_xlpm.ehTrator, "TRATOR", IFERROR(_xlfn.XLOOKUP(_xlpm.chave, _xlpm.fonte, UTIL!BP:BP, "", 0), IFERROR(_xlfn.XLOOKUP("*"&_xlpm.chave&"*", _xlpm.fonte, UTIL!BP:BP, "", 2), "Não encontrado"))), _xlpm.dimtxt_antigo, IFERROR(_xlfn.XLOOKUP(_xlpm.chave, _xlpm.fonte, UTIL!BY:BY, "", 0), IFERROR(_xlfn.XLOOKUP("*"&_xlpm.chave&"*", _xlpm.fonte, UTIL!BY:BY, "", 2), "Não encontrado")), _xlpm.tipotxt, IF(_xlpm.tipoMod<>"", _xlpm.tipoMod, _xlpm.tipotxt_antigo), _xlpm.dimtxt, IF(_xlpm.dimMod<>"", _xlpm.dimMod, _xlpm.dimtxt_antigo), _xlpm.deTxt, IF(L25="CLIENTE", O25, IF(LEFT(L25,4)="http", L25, "MACPONTA AGRO DE "&L25)), _xlpm.paraBase, IF(M25="CLIENTE", P25, M25), _xlpm.paraTxt, IF(LEFT(_xlpm.paraBase,4)="http", _xlpm.paraBase, "MACPONTA AGRO DE "&_xlpm.paraBase), _xlpm.nfParte, IF(LEN(TRIM(I25))=0, "", " -NF "&TRIM(I25)), "- " & _xlpm.tipotxt & ": *" & G25 & "*" & CHAR(13)&CHAR(10) & "- " & _xlpm.dimtxt & CHAR(13)&CHAR(10) & "- *Cliente*: " & J25 & _xlpm.nfParte & CHAR(13)&CHAR(10) & "- *Obs:* " & Q25 & CHAR(13)&CHAR(10) & CHAR(10) & "- *De*: " & _xlpm.deTxt & CHAR(13)&CHAR(10) & "- *Para*: " & _xlpm.paraTxt & CHAR(13)&CHAR(10) & "- *Ida e volta*: +/- " & TEXT(((D25*1.5)/1440),"h:mm") & "h | " & D25 & "km" )} -> - : *9AGC1007EHS000187*_x000D_ - _x000D_ - *Cliente*: TRANSF -NF000076891 -NF 45972_x000D_ - *Obs:* N/A_x000D_ - *De*: MACPONTA AGRO DE IRATI_x000D_ - *Para*: MACPONTA AGRO DE PRUDENTÓPOLIS_x000D_ - *Ida e volta*: +/- 8:07h | 325km
A26: CONCLUIDO | B26: TERCEIRO MAZETTO | C26: =IFERROR((D26*1.5)/1440, "?") -> 0.08125 | D26: 78 | F26: 1389 | G26: 1BM6100JESD602123 | H26: 45972 | I26: 45972 | J26: OSWALDO R BARBOSA -NF107698 | K26: euclides.junior | L26: PRUDENTÓPOLIS | M26: CLIENTE | N26: DE LOJA PARA CLIENTE | O26: MPA | P26: https://maps.app.goo.gl/3mYP9KzrASogJS3w9 | Q26: Oswaldo | R26: GUARAPUAVA | S26: TRATOR | T26: =IF( OR( IFERROR(FIND("BM",G26),0)>0, IFERROR(FIND("PY",G26),0)>0 ), MID(TRIM(SUBSTITUTE(SUBSTITUTE(G26,CHAR(160),""),CHAR(9),"")),4,5), MID(TRIM(SUBSTITUTE(SUBSTITUTE(G26,CHAR(160),""),CHAR(9),"")),4,4) ) -> 6100J | U26: {=_xlfn.LET( _xlpm.ch, TRIM(SUBSTITUTE(G26,CHAR(160),"")), _xlpm.ehTrator, OR(IFERROR(FIND("BM",_xlpm.ch),0)>0, IFERROR(FIND("PY",_xlpm.ch),0)>0), _xlpm.chave, IF(_xlpm.ehTrator, MID(_xlpm.ch,4,5), MID(_xlpm.ch,4,4)), _xlpm.fonte, IF(LEN(_xlpm.chave)=5, UTIL!BS:BS, UTIL!BR:BR), _xlpm.modelo, TRIM(SUBSTITUTE(T26,CHAR(160),"")), _xlpm.nomeMod, IFERROR(_xlfn.XLOOKUP("*"&_xlpm.modelo&"*", UTIL!D:D, UTIL!B:B, "", 2), IFERROR(_xlfn.XLOOKUP("*"&_xlpm.modelo&"*", UTIL!E:E, UTIL!B:B, "", 2), "")), _xlpm.tipoMod, IF(_xlpm.nomeMod="", "", IFERROR(LEFT(_xlpm.nomeMod, FIND(" ", _xlpm.nomeMod)-1), _xlpm.nomeMod)), _xlpm.dimMod, IFERROR(_xlfn.XLOOKUP("*"&_xlpm.modelo&"*", UTIL!D:D, UTIL!K:K, "", 2), IFERROR(_xlfn.XLOOKUP("*"&_xlpm.modelo&"*", UTIL!E:E, UTIL!K:K, "", 2), "")), _xlpm.tipotxt_antigo, IF(_xlpm.ehTrator, "TRATOR", IFERROR(_xlfn.XLOOKUP(_xlpm.chave, _xlpm.fonte, UTIL!BP:BP, "", 0), IFERROR(_xlfn.XLOOKUP("*"&_xlpm.chave&"*", _xlpm.fonte, UTIL!BP:BP, "", 2), "Não encontrado"))), _xlpm.dimtxt_antigo, IFERROR(_xlfn.XLOOKUP(_xlpm.chave, _xlpm.fonte, UTIL!BY:BY, "", 0), IFERROR(_xlfn.XLOOKUP("*"&_xlpm.chave&"*", _xlpm.fonte, UTIL!BY:BY, "", 2), "Não encontrado")), _xlpm.tipotxt, IF(_xlpm.tipoMod<>"", _xlpm.tipoMod, _xlpm.tipotxt_antigo), _xlpm.dimtxt, IF(_xlpm.dimMod<>"", _xlpm.dimMod, _xlpm.dimtxt_antigo), _xlpm.deTxt, IF(L26="CLIENTE", O26, IF(LEFT(L26,4)="http", L26, "MACPONTA AGRO DE "&L26)), _xlpm.paraBase, IF(M26="CLIENTE", P26, M26), _xlpm.paraTxt, IF(LEFT(_xlpm.paraBase,4)="http", _xlpm.paraBase, "MACPONTA AGRO DE "&_xlpm.paraBase), _xlpm.nfParte, IF(LEN(TRIM(I26))=0, "", " -NF "&TRIM(I26)), "- " & _xlpm.tipotxt & ": *" & G26 & "*" & CHAR(13)&CHAR(10) & "- " & _xlpm.dimtxt & CHAR(13)&CHAR(10) & "- *Cliente*: " & J26 & _xlpm.nfParte & CHAR(13)&CHAR(10) & "- *Obs:* " & Q26 & CHAR(13)&CHAR(10) & CHAR(10) & "- *De*: " & _xlpm.deTxt & CHAR(13)&CHAR(10) & "- *Para*: " & _xlpm.paraTxt & CHAR(13)&CHAR(10) & "- *Ida e volta*: +/- " & TEXT(((D26*1.5)/1440),"h:mm") & "h | " & D26 & "km" )} -> - TRATOR: *1BM6100JESD602123*_x000D_ - _x000D_ - *Cliente*: OSWALDO R BARBOSA -NF107698 -NF 45972_x000D_ - *Obs:* Oswaldo_x000D_ - *De*: MACPONTA AGRO DE PRUDENTÓPOLIS_x000D_ - *Para*: https://maps.app.goo.gl/3mYP9KzrASogJS3w9_x000D_ - *Ida e volta*: +/- 1:57h | 78km
A27: CONCLUIDO (D) | B27: PROPRIO DAF | C27: =IFERROR((D27*1.5)/1440, "?") -> 0.52083333 | D27: 500 | E27: 800 | G27: 1CQRD30AVS0160245 | H27: 45972 | I27: 45971 | J27: DOUGLAS FONSECA -NF 107225 | K27: marcelo.ferreira | L27: GUARAPUAVA | M27: CLIENTE | N27: DE LOJA PARA DEMONSTRAÇÃO | O27: MPA | P27: https://maps.app.goo.gl/xyQpe8BG44WqsG1v9 | Q27: N/A | R27: GUARAPUAVA | S27: PLATAFORMA | T27: =IF( OR( IFERROR(FIND("BM",G27),0)>0, IFERROR(FIND("PY",G27),0)>0 ), MID(TRIM(SUBSTITUTE(SUBSTITUTE(G27,CHAR(160),""),CHAR(9),"")),4,5), MID(TRIM(SUBSTITUTE(SUBSTITUTE(G27,CHAR(160),""),CHAR(9),"")),4,4) ) -> RD30 | U27: {=_xlfn.LET( _xlpm.ch, TRIM(SUBSTITUTE(G27,CHAR(160),"")), _xlpm.ehTrator, OR(IFERROR(FIND("BM",_xlpm.ch),0)>0, IFERROR(FIND("PY",_xlpm.ch),0)>0), _xlpm.chave, IF(_xlpm.ehTrator, MID(_xlpm.ch,4,5), MID(_xlpm.ch,4,4)), _xlpm.fonte, IF(LEN(_xlpm.chave)=5, UTIL!BS:BS, UTIL!BR:BR), _xlpm.modelo, TRIM(SUBSTITUTE(T27,CHAR(160),"")), _xlpm.nomeMod, IFERROR(_xlfn.XLOOKUP("*"&_xlpm.modelo&"*", UTIL!D:D, UTIL!B:B, "", 2), IFERROR(_xlfn.XLOOKUP("*"&_xlpm.modelo&"*", UTIL!E:E, UTIL!B:B, "", 2), "")), _xlpm.tipoMod, IF(_xlpm.nomeMod="", "", IFERROR(LEFT(_xlpm.nomeMod, FIND(" ", _xlpm.nomeMod)-1), _xlpm.nomeMod)), _xlpm.dimMod, IFERROR(_xlfn.XLOOKUP("*"&_xlpm.modelo&"*", UTIL!D:D, UTIL!K:K, "", 2), IFERROR(_xlfn.XLOOKUP("*"&_xlpm.modelo&"*", UTIL!E:E, UTIL!K:K, "", 2), "")), _xlpm.tipotxt_antigo, IF(_xlpm.ehTrator, "TRATOR", IFERROR(_xlfn.XLOOKUP(_xlpm.chave, _xlpm.fonte, UTIL!BP:BP, "", 0), IFERROR(_xlfn.XLOOKUP("*"&_xlpm.chave&"*", _xlpm.fonte, UTIL!BP:BP, "", 2), "Não encontrado"))), _xlpm.dimtxt_antigo, IFERROR(_xlfn.XLOOKUP(_xlpm.chave, _xlpm.fonte, UTIL!BY:BY, "", 0), IFERROR(_xlfn.XLOOKUP("*"&_xlpm.chave&"*", _xlpm.fonte, UTIL!BY:BY, "", 2), "Não encontrado")), _xlpm.tipotxt, IF(_xlpm.tipoMod<>"", _xlpm.tipoMod, _xlpm.tipotxt_antigo), _xlpm.dimtxt, IF(_xlpm.dimMod<>"", _xlpm.dimMod, _xlpm.dimtxt_antigo), _xlpm.deTxt, IF(L27="CLIENTE", O27, IF(LEFT(L27,4)="http", L27, "MACPONTA AGRO DE "&L27)), _xlpm.paraBase, IF(M27="CLIENTE", P27, M27), _xlpm.paraTxt, IF(LEFT(_xlpm.paraBase,4)="http", _xlpm.paraBase, "MACPONTA AGRO DE "&_xlpm.paraBase), _xlpm.nfParte, IF(LEN(TRIM(I27))=0, "", " -NF "&TRIM(I27)), "- " & _xlpm.tipotxt & ": *" & G27 & "*" & CHAR(13)&CHAR(10) & "- " & _xlpm.dimtxt & CHAR(13)&CHAR(10) & "- *Cliente*: " & J27 & _xlpm.nfParte & CHAR(13)&CHAR(10) & "- *Obs:* " & Q27 & CHAR(13)&CHAR(10) & CHAR(10) & "- *De*: " & _xlpm.deTxt & CHAR(13)&CHAR(10) & "- *Para*: " & _xlpm.paraTxt & CHAR(13)&CHAR(10) & "- *Ida e volta*: +/- " & TEXT(((D27*1.5)/1440),"h:mm") & "h | " & D27 & "km" )} -> - PLATAFORMA: *1CQRD30AVS0160245*_x000D_ - A:1,60 x C:9,14 x L:2,20-2,20 x P:4.200kg_x000D_ - *Cliente*: DOUGLAS FONSECA -NF 107225 -NF 45971_x000D_ - *Obs:* N/A_x000D_ - *De*: MACPONTA AGRO DE GUARAPUAVA_x000D_ - *Para*: https://maps.app.goo.gl/xyQpe8BG44WqsG1v9_x000D_ - *Ida e volta*: +/- 12:30h | 500km
A28: CONCLUIDO (D) | B28: PROPRIO DAF | C28: =IFERROR((D28*1.5)/1440, "?") -> 0.52083333 | D28: 500 | E28: 2200 | G28: 1CQS550APS0160136 | H28: 45972 | I28: 45971 | J28: DOUGLAS FONSECA -NF 107225 | K28: marcelo.ferreira | L28: GUARAPUAVA | M28: CLIENTE | N28: DE LOJA PARA DEMONSTRAÇÃO | O28: MPA | P28: https://maps.app.goo.gl/xyQpe8BG44WqsG1v9 | Q28: N/A | R28: GUARAPUAVA | S28: COLHEITADEIRA | T28: =IF( OR( IFERROR(FIND("BM",G28),0)>0, IFERROR(FIND("PY",G28),0)>0 ), MID(TRIM(SUBSTITUTE(SUBSTITUTE(G28,CHAR(160),""),CHAR(9),"")),4,5), MID(TRIM(SUBSTITUTE(SUBSTITUTE(G28,CHAR(160),""),CHAR(9),"")),4,4) ) -> S550 | U28: {=_xlfn.LET( _xlpm.ch, TRIM(SUBSTITUTE(G28,CHAR(160),"")), _xlpm.ehTrator, OR(IFERROR(FIND("BM",_xlpm.ch),0)>0, IFERROR(FIND("PY",_xlpm.ch),0)>0), _xlpm.chave, IF(_xlpm.ehTrator, MID(_xlpm.ch,4,5), MID(_xlpm.ch,4,4)), _xlpm.fonte, IF(LEN(_xlpm.chave)=5, UTIL!BS:BS, UTIL!BR:BR), _xlpm.modelo, TRIM(SUBSTITUTE(T28,CHAR(160),"")), _xlpm.nomeMod, IFERROR(_xlfn.XLOOKUP("*"&_xlpm.modelo&"*", UTIL!D:D, UTIL!B:B, "", 2), IFERROR(_xlfn.XLOOKUP("*"&_xlpm.modelo&"*", UTIL!E:E, UTIL!B:B, "", 2), "")), _xlpm.tipoMod, IF(_xlpm.nomeMod="", "", IFERROR(LEFT(_xlpm.nomeMod, FIND(" ", _xlpm.nomeMod)-1), _xlpm.nomeMod)), _xlpm.dimMod, IFERROR(_xlfn.XLOOKUP("*"&_xlpm.modelo&"*", UTIL!D:D, UTIL!K:K, "", 2), IFERROR(_xlfn.XLOOKUP("*"&_xlpm.modelo&"*", UTIL!E:E, UTIL!K:K, "", 2), "")), _xlpm.tipotxt_antigo, IF(_xlpm.ehTrator, "TRATOR", IFERROR(_xlfn.XLOOKUP(_xlpm.chave, _xlpm.fonte, UTIL!BP:BP, "", 0), IFERROR(_xlfn.XLOOKUP("*"&_xlpm.chave&"*", _xlpm.fonte, UTIL!BP:BP, "", 2), "Não encontrado"))), _xlpm.dimtxt_antigo, IFERROR(_xlfn.XLOOKUP(_xlpm.chave, _xlpm.fonte, UTIL!BY:BY, "", 0), IFERROR(_xlfn.XLOOKUP("*"&_xlpm.chave&"*", _xlpm.fonte, UTIL!BY:BY, "", 2), "Não encontrado")), _xlpm.tipotxt, IF(_xlpm.tipoMod<>"", _xlpm.tipoMod, _xlpm.tipotxt_antigo), _xlpm.dimtxt, IF(_xlpm.dimMod<>"", _xlpm.dimMod, _xlpm.dimtxt_antigo), _xlpm.deTxt, IF(L28="CLIENTE", O28, IF(LEFT(L28,4)="http", L28, "MACPONTA AGRO DE "&L28)), _xlpm.paraBase, IF(M28="CLIENTE", P28, M28), _xlpm.paraTxt, IF(LEFT(_xlpm.paraBase,4)="http", _xlpm.paraBase, "MACPONTA AGRO DE "&_xlpm.paraBase), _xlpm.nfParte, IF(LEN(TRIM(I28))=0, "", " -NF "&TRIM(I28)), "- " & _xlpm.tipotxt & ": *" & G28 & "*" & CHAR(13)&CHAR(10) & "- " & _xlpm.dimtxt & CHAR(13)&CHAR(10) & "- *Cliente*: " & J28 & _xlpm.nfParte & CHAR(13)&CHAR(10) & "- *Obs:* " & Q28 & CHAR(13)&CHAR(10) & CHAR(10) & "- *De*: " & _xlpm.deTxt & CHAR(13)&CHAR(10) & "- *Para*: " & _xlpm.paraTxt & CHAR(13)&CHAR(10) & "- *Ida e volta*: +/- " & TEXT(((D28*1.5)/1440),"h:mm") & "h | " & D28 & "km" )} -> - COLHEITADEIRA: *1CQS550APS0160136*_x000D_ - A:3,80 x C:10,00 x L:3,70-4,20 x P:15.938kg_x000D_ - *Cliente*: DOUGLAS FONSECA -NF 107225 -NF 45971_x000D_ - *Obs:* N/A_x000D_ - *De*: MACPONTA AGRO DE GUARAPUAVA_x000D_ - *Para*: https://maps.app.goo.gl/xyQpe8BG44WqsG1v9_x000D_ - *Ida e volta*: +/- 12:30h | 500km
A29: CONCLUIDO | B29: PROPRIO VW | C29: =IFERROR((D29*1.5)/1440, "?") -> 0.059375 | D29: 57 | E29: =IFERROR((D29*6),"?") -> 342 | G29: 1BM7230JCPH010913 | H29: 45973 | I29: 45973 | J29: CLIENTE → MANUTENÇÃO | K29: marcelo.ferreira | L29: CLIENTE | M29: PONTA GROSSA | N29: DE CLIENTE PARA LOJA | O29: https://maps.app.goo.gl/xb5MkVzoE3pEMvuw8 | P29: MPA | Q29: FABIO - 42-99921-1220 | R29: PONTA GROSSA | S29: TRATOR | T29: =IF( OR( IFERROR(FIND("BM",G29),0)>0, IFERROR(FIND("PY",G29),0)>0 ), MID(TRIM(SUBSTITUTE(SUBSTITUTE(G29,CHAR(160),""),CHAR(9),"")),4,5), MID(TRIM(SUBSTITUTE(SUBSTITUTE(G29,CHAR(160),""),CHAR(9),"")),4,4) ) -> 7230J | U29: {=_xlfn.LET( _xlpm.ch, TRIM(SUBSTITUTE(G29,CHAR(160),"")), _xlpm.ehTrator, OR(IFERROR(FIND("BM",_xlpm.ch),0)>0, IFERROR(FIND("PY",_xlpm.ch),0)>0), _xlpm.chave, IF(_xlpm.ehTrator, MID(_xlpm.ch,4,5), MID(_xlpm.ch,4,4)), _xlpm.fonte, IF(LEN(_xlpm.chave)=5, UTIL!BS:BS, UTIL!BR:BR), _xlpm.modelo, TRIM(SUBSTITUTE(T29,CHAR(160),"")), _xlpm.nomeMod, IFERROR(_xlfn.XLOOKUP("*"&_xlpm.modelo&"*", UTIL!D:D, UTIL!B:B, "", 2), IFERROR(_xlfn.XLOOKUP("*"&_xlpm.modelo&"*", UTIL!E:E, UTIL!B:B, "", 2), "")), _xlpm.tipoMod, IF(_xlpm.nomeMod="", "", IFERROR(LEFT(_xlpm.nomeMod, FIND(" ", _xlpm.nomeMod)-1), _xlpm.nomeMod)), _xlpm.dimMod, IFERROR(_xlfn.XLOOKUP("*"&_xlpm.modelo&"*", UTIL!D:D, UTIL!K:K, "", 2), IFERROR(_xlfn.XLOOKUP("*"&_xlpm.modelo&"*", UTIL!E:E, UTIL!K:K, "", 2), "")), _xlpm.tipotxt_antigo, IF(_xlpm.ehTrator, "TRATOR", IFERROR(_xlfn.XLOOKUP(_xlpm.chave, _xlpm.fonte, UTIL!BP:BP, "", 0), IFERROR(_xlfn.XLOOKUP("*"&_xlpm.chave&"*", _xlpm.fonte, UTIL!BP:BP, "", 2), "Não encontrado"))), _xlpm.dimtxt_antigo, IFERROR(_xlfn.XLOOKUP(_xlpm.chave, _xlpm.fonte, UTIL!BY:BY, "", 0), IFERROR(_xlfn.XLOOKUP("*"&_xlpm.chave&"*", _xlpm.fonte, UTIL!BY:BY, "", 2), "Não encontrado")), _xlpm.tipotxt, IF(_xlpm.tipoMod<>"", _xlpm.tipoMod, _xlpm.tipotxt_antigo), _xlpm.dimtxt, IF(_xlpm.dimMod<>"", _xlpm.dimMod, _xlpm.dimtxt_antigo), _xlpm.deTxt, IF(L29="CLIENTE", O29, IF(LEFT(L29,4)="http", L29, "MACPONTA AGRO DE "&L29)), _xlpm.paraBase, IF(M29="CLIENTE", P29, M29), _xlpm.paraTxt, IF(LEFT(_xlpm.paraBase,4)="http", _xlpm.paraBase, "MACPONTA AGRO DE "&_xlpm.paraBase), _xlpm.nfParte, IF(LEN(TRIM(I29))=0, "", " -NF "&TRIM(I29)), "- " & _xlpm.tipotxt & ": *" & G29 & "*" & CHAR(13)&CHAR(10) & "- " & _xlpm.dimtxt & CHAR(13)&CHAR(10) & "- *Cliente*: " & J29 & _xlpm.nfParte & CHAR(13)&CHAR(10) & "- *Obs:* " & Q29 & CHAR(13)&CHAR(10) & CHAR(10) & "- *De*: " & _xlpm.deTxt & CHAR(13)&CHAR(10) & "- *Para*: " & _xlpm.paraTxt & CHAR(13)&CHAR(10) & "- *Ida e volta*: +/- " & TEXT(((D29*1.5)/1440),"h:mm") & "h | " & D29 & "km" )} -> - TRATOR: *1BM7230JCPH010913*_x000D_ - _x000D_ - *Cliente*: CLIENTE → MANUTENÇÃO -NF 45973_x000D_ - *Obs:* FABIO - 42-99921-1220_x000D_ - *De*: https://maps.app.goo.gl/xb5MkVzoE3pEMvuw8_x000D_ - *Para*: MACPONTA AGRO DE PONTA GROSSA_x000D_ - *Ida e volta*: +/- 1:25h | 57km
A30: CONCLUIDO | B30: PROPRIO DAF | C30: =IFERROR((D30*1.5)/1440, "?") -> 0.10416667 | D30: 100 | E30: =IFERROR((D30*6),"?") -> 600 | G30: 1BM7225JCGH004564 | H30: 45974 | I30: 45974 | J30: CLIENTE → MANUTENÇÃO | K30: marcelo.ferreira | L30: PONTA GROSSA | M30: CLIENTE | N30: DE LOJA PARA CLIENTE | O30: MPA | P30: https://maps.app.goo.gl/TWUFTdA34fB48Hvv8 | Q30: RUBINHO 42- 99972-3850 | R30: PONTA GROSSA | S30: TRATOR | T30: =IF( OR( IFERROR(FIND("BM",G30),0)>0, IFERROR(FIND("PY",G30),0)>0 ), MID(TRIM(SUBSTITUTE(SUBSTITUTE(G30,CHAR(160),""),CHAR(9),"")),4,5), MID(TRIM(SUBSTITUTE(SUBSTITUTE(G30,CHAR(160),""),CHAR(9),"")),4,4) ) -> 7225J | U30: {=_xlfn.LET( _xlpm.ch, TRIM(SUBSTITUTE(G30,CHAR(160),"")), _xlpm.ehTrator, OR(IFERROR(FIND("BM",_xlpm.ch),0)>0, IFERROR(FIND("PY",_xlpm.ch),0)>0), _xlpm.chave, IF(_xlpm.ehTrator, MID(_xlpm.ch,4,5), MID(_xlpm.ch,4,4)), _xlpm.fonte, IF(LEN(_xlpm.chave)=5, UTIL!BS:BS, UTIL!BR:BR), _xlpm.modelo, TRIM(SUBSTITUTE(T30,CHAR(160),"")), _xlpm.nomeMod, IFERROR(_xlfn.XLOOKUP("*"&_xlpm.modelo&"*", UTIL!D:D, UTIL!B:B, "", 2), IFERROR(_xlfn.XLOOKUP("*"&_xlpm.modelo&"*", UTIL!E:E, UTIL!B:B, "", 2), "")), _xlpm.tipoMod, IF(_xlpm.nomeMod="", "", IFERROR(LEFT(_xlpm.nomeMod, FIND(" ", _xlpm.nomeMod)-1), _xlpm.nomeMod)), _xlpm.dimMod, IFERROR(_xlfn.XLOOKUP("*"&_xlpm.modelo&"*", UTIL!D:D, UTIL!K:K, "", 2), IFERROR(_xlfn.XLOOKUP("*"&_xlpm.modelo&"*", UTIL!E:E, UTIL!K:K, "", 2), "")), _xlpm.tipotxt_antigo, IF(_xlpm.ehTrator, "TRATOR", IFERROR(_xlfn.XLOOKUP(_xlpm.chave, _xlpm.fonte, UTIL!BP:BP, "", 0), IFERROR(_xlfn.XLOOKUP("*"&_xlpm.chave&"*", _xlpm.fonte, UTIL!BP:BP, "", 2), "Não encontrado"))), _xlpm.dimtxt_antigo, IFERROR(_xlfn.XLOOKUP(_xlpm.chave, _xlpm.fonte, UTIL!BY:BY, "", 0), IFERROR(_xlfn.XLOOKUP("*"&_xlpm.chave&"*", _xlpm.fonte, UTIL!BY:BY, "", 2), "Não encontrado")), _xlpm.tipotxt, IF(_xlpm.tipoMod<>"", _xlpm.tipoMod, _xlpm.tipotxt_antigo), _xlpm.dimtxt, IF(_xlpm.dimMod<>"", _xlpm.dimMod, _xlpm.dimtxt_antigo), _xlpm.deTxt, IF(L30="CLIENTE", O30, IF(LEFT(L30,4)="http", L30, "MACPONTA AGRO DE "&L30)), _xlpm.paraBase, IF(M30="CLIENTE", P30, M30), _xlpm.paraTxt, IF(LEFT(_xlpm.paraBase,4)="http", _xlpm.paraBase, "MACPONTA AGRO DE "&_xlpm.paraBase), _xlpm.nfParte, IF(LEN(TRIM(I30))=0, "", " -NF "&TRIM(I30)), "- " & _xlpm.tipotxt & ": *" & G30 & "*" & CHAR(13)&CHAR(10) & "- " & _xlpm.dimtxt & CHAR(13)&CHAR(10) & "- *Cliente*: " & J30 & _xlpm.nfParte & CHAR(13)&CHAR(10) & "- *Obs:* " & Q30 & CHAR(13)&CHAR(10) & CHAR(10) & "- *De*: " & _xlpm.deTxt & CHAR(13)&CHAR(10) & "- *Para*: " & _xlpm.paraTxt & CHAR(13)&CHAR(10) & "- *Ida e volta*: +/- " & TEXT(((D30*1.5)/1440),"h:mm") & "h | " & D30 & "km" )} -> - TRATOR: *1BM7225JCGH004564*_x000D_ - _x000D_ - *Cliente*: CLIENTE → MANUTENÇÃO -NF 45974_x000D_ - *Obs:* RUBINHO 42- 99972-3850_x000D_ - *De*: MACPONTA AGRO DE PONTA GROSSA_x000D_ - *Para*: https://maps.app.goo.gl/TWUFTdA34fB48Hvv8_x000D_ - *Ida e volta*: +/- 2:30h | 100km
A31: CONCLUIDO | B31: PROPRIO VW | C31: =IFERROR((D31*1.5)/1440, "?") -> 0.109375 | D31: 105 | E31: =IFERROR((D31*6),"?") -> 630 | G31: 1BM5060EPS4201602 | H31: 45974 | I31: 45974 | J31: CARLOS EDINEI KNAUT → MANUTENÇÃO | K31: daisy.kakol | L31: CLIENTE | M31: IRATI | N31: DE CLIENTE PARA LOJA | O31: https://maps.app.goo.gl/EGGjvMh2LpNr1STk7 | P31: MPA | Q31: OFICINA | R31: IRATI | S31: TRATOR
A32: CONCLUIDO | B32: PROPRIO VW | C32: =IFERROR((D32*1.5)/1440, "?") -> 0.075 | D32: 72 | E32: =IFERROR((D32*6),"?") -> 432 | G32: 1BM5080ECN4109659 | H32: 45974 | I32: 45974 | J32: ANSELMO WASELECHEN → MANUTENÇÃO | K32: daisy.kakol | L32: CLIENTE | M32: IRATI | N32: DE CLIENTE PARA LOJA | O32: https://maps.app.goo.gl/fhc785TjS54Vtjgc8 | P32: MPA | Q32: OFICINA | R32: IRATI | S32: TRATOR | T32: =IF( OR( IFERROR(FIND("BM",G32),0)>0, IFERROR(FIND("PY",G32),0)>0 ), MID(TRIM(SUBSTITUTE(SUBSTITUTE(G32,CHAR(160),""),CHAR(9),"")),4,5), MID(TRIM(SUBSTITUTE(SUBSTITUTE(G32,CHAR(160),""),CHAR(9),"")),4,4) ) -> 5080E | U32: {=_xlfn.LET( _xlpm.ch, TRIM(SUBSTITUTE(G32,CHAR(160),"")), _xlpm.ehTrator, OR(IFERROR(FIND("BM",_xlpm.ch),0)>0, IFERROR(FIND("PY",_xlpm.ch),0)>0), _xlpm.chave, IF(_xlpm.ehTrator, MID(_xlpm.ch,4,5), MID(_xlpm.ch,4,4)), _xlpm.fonte, IF(LEN(_xlpm.chave)=5, UTIL!BS:BS, UTIL!BR:BR), _xlpm.modelo, TRIM(SUBSTITUTE(T32,CHAR(160),"")), _xlpm.nomeMod, IFERROR(_xlfn.XLOOKUP("*"&_xlpm.modelo&"*", UTIL!D:D, UTIL!B:B, "", 2), IFERROR(_xlfn.XLOOKUP("*"&_xlpm.modelo&"*", UTIL!E:E, UTIL!B:B, "", 2), "")), _xlpm.tipoMod, IF(_xlpm.nomeMod="", "", IFERROR(LEFT(_xlpm.nomeMod, FIND(" ", _xlpm.nomeMod)-1), _xlpm.nomeMod)), _xlpm.dimMod, IFERROR(_xlfn.XLOOKUP("*"&_xlpm.modelo&"*", UTIL!D:D, UTIL!K:K, "", 2), IFERROR(_xlfn.XLOOKUP("*"&_xlpm.modelo&"*", UTIL!E:E, UTIL!K:K, "", 2), "")), _xlpm.tipotxt_antigo, IF(_xlpm.ehTrator, "TRATOR", IFERROR(_xlfn.XLOOKUP(_xlpm.chave, _xlpm.fonte, UTIL!BP:BP, "", 0), IFERROR(_xlfn.XLOOKUP("*"&_xlpm.chave&"*", _xlpm.fonte, UTIL!BP:BP, "", 2), "Não encontrado"))), _xlpm.dimtxt_antigo, IFERROR(_xlfn.XLOOKUP(_xlpm.chave, _xlpm.fonte, UTIL!BY:BY, "", 0), IFERROR(_xlfn.XLOOKUP("*"&_xlpm.chave&"*", _xlpm.fonte, UTIL!BY:BY, "", 2), "Não encontrado")), _xlpm.tipotxt, IF(_xlpm.tipoMod<>"", _xlpm.tipoMod, _xlpm.tipotxt_antigo), _xlpm.dimtxt, IF(_xlpm.dimMod<>"", _xlpm.dimMod, _xlpm.dimtxt_antigo), _xlpm.deTxt, IF(L32="CLIENTE", O32, IF(LEFT(L32,4)="http", L32, "MACPONTA AGRO DE "&L32)), _xlpm.paraBase, IF(M32="CLIENTE", P32, M32), _xlpm.paraTxt, IF(LEFT(_xlpm.paraBase,4)="http", _xlpm.paraBase, "MACPONTA AGRO DE "&_xlpm.paraBase), _xlpm.nfParte, IF(LEN(TRIM(I32))=0, "", " -NF "&TRIM(I32)), "- " & _xlpm.tipotxt & ": *" & G32 & "*" & CHAR(13)&CHAR(10) & "- " & _xlpm.dimtxt & CHAR(13)&CHAR(10) & "- *Cliente*: " & J32 & _xlpm.nfParte & CHAR(13)&CHAR(10) & "- *Obs:* " & Q32 & CHAR(13)&CHAR(10) & CHAR(10) & "- *De*: " & _xlpm.deTxt & CHAR(13)&CHAR(10) & "- *Para*: " & _xlpm.paraTxt & CHAR(13)&CHAR(10) & "- *Ida e volta*: +/- " & TEXT(((D32*1.5)/1440),"h:mm") & "h | " & D32 & "km" )} -> - TRATOR: *1BM5080ECN4109659*_x000D_ - _x000D_ - *Cliente*: ANSELMO WASELECHEN → MANUTENÇÃO -NF 45974_x000D_ - *Obs:* OFICINA_x000D_ - *De*: https://maps.app.goo.gl/fhc785TjS54Vtjgc8_x000D_ - *Para*: MACPONTA AGRO DE IRATI_x000D_ - *Ida e volta*: +/- 1:48h | 72km
A33: CONCLUIDO | B33: PROPRIO VW | C33: =IFERROR((D33*1.5)/1440, "?") -> 0.11979167 | D33: 115 | E33: =IFERROR((D33*6),"?") -> 690 | G33: 1BM5080EEP4112594 | H33: 45974 | I33: 45974 | J33: MANUTENÇÃO → JOSE VALCIR MOREIRA DA SILVA | K33: daisy.kakol | L33: IRATI | M33: CLIENTE | N33: DE LOJA PARA CLIENTE | O33: MPA | P33: https://maps.app.goo.gl/u6RQ92AcKr5YZVN5A | Q33: JOSE VALCIR | R33: IRATI | S33: TRATOR | T33: =IF( OR( IFERROR(FIND("BM",G33),0)>0, IFERROR(FIND("PY",G33),0)>0 ), MID(TRIM(SUBSTITUTE(SUBSTITUTE(G33,CHAR(160),""),CHAR(9),"")),4,5), MID(TRIM(SUBSTITUTE(SUBSTITUTE(G33,CHAR(160),""),CHAR(9),"")),4,4) ) -> 5080E | U33: {=_xlfn.LET( _xlpm.ch, TRIM(SUBSTITUTE(G33,CHAR(160),"")), _xlpm.ehTrator, OR(IFERROR(FIND("BM",_xlpm.ch),0)>0, IFERROR(FIND("PY",_xlpm.ch),0)>0), _xlpm.chave, IF(_xlpm.ehTrator, MID(_xlpm.ch,4,5), MID(_xlpm.ch,4,4)), _xlpm.fonte, IF(LEN(_xlpm.chave)=5, UTIL!BS:BS, UTIL!BR:BR), _xlpm.modelo, TRIM(SUBSTITUTE(T33,CHAR(160),"")), _xlpm.nomeMod, IFERROR(_xlfn.XLOOKUP("*"&_xlpm.modelo&"*", UTIL!D:D, UTIL!B:B, "", 2), IFERROR(_xlfn.XLOOKUP("*"&_xlpm.modelo&"*", UTIL!E:E, UTIL!B:B, "", 2), "")), _xlpm.tipoMod, IF(_xlpm.nomeMod="", "", IFERROR(LEFT(_xlpm.nomeMod, FIND(" ", _xlpm.nomeMod)-1), _xlpm.nomeMod)), _xlpm.dimMod, IFERROR(_xlfn.XLOOKUP("*"&_xlpm.modelo&"*", UTIL!D:D, UTIL!K:K, "", 2), IFERROR(_xlfn.XLOOKUP("*"&_xlpm.modelo&"*", UTIL!E:E, UTIL!K:K, "", 2), "")), _xlpm.tipotxt_antigo, IF( _xlpm.ehTrator, "TRATOR", IFERROR( _xlfn.XLOOKUP(_xlpm.chave, _xlpm.fonte, UTIL!BP:BP, "", 0), IFERROR( _xlfn.XLOOKUP("*"&_xlpm.chave&"*", _xlpm.fonte, UTIL!BP:BP, "", 2), "Não encontrado" ) ) ), _xlpm.dimtxt_antigo, IF( _xlpm.ehTrator, IFERROR( _xlfn.XLOOKUP(MID(_xlpm.ch,4,4), UTIL!BR:BR, UTIL!BY:BY, "", 0), IFERROR( _xlfn.XLOOKUP("*"&MID(_xlpm.ch,4,4)&"*", UTIL!BR:BR, UTIL!BY:BY, "", 2), "Não encontrado" ) ), IFERROR( _xlfn.XLOOKUP(_xlpm.chave, _xlpm.fonte, UTIL!BY:BY, "", 0), IFERROR( _xlfn.XLOOKUP("*"&_xlpm.chave&"*", _xlpm.fonte, UTIL!BY:BY, "", 2), "Não encontrado" ) ) ), _xlpm.tipotxt, IF(_xlpm.tipoMod<>"", _xlpm.tipoMod, _xlpm.tipotxt_antigo), _xlpm.dimtxt, IF(_xlpm.dimMod<>"", _xlpm.dimMod, _xlpm.dimtxt_antigo), _xlpm.deTxt, IF(L33="CLIENTE", O33, IF(LEFT(L33,4)="http", L33, "MACPONTA AGRO DE "&L33)), _xlpm.paraBase, IF(M33="CLIENTE", P33, M33), _xlpm.paraTxt, IF(LEFT(_xlpm.paraBase,4)="http", _xlpm.paraBase, "MACPONTA AGRO DE "&_xlpm.paraBase), _xlpm.nfParte, IF(LEN(TRIM(I33))=0, "", " -NF "&TRIM(I33)), "- " & _xlpm.tipotxt & ": *" & G33 & "*" & CHAR(13)&CHAR(10) & "- " & _xlpm.dimtxt & CHAR(13)&CHAR(10) & "- *Cliente*: " & J33 & _xlpm.nfParte & CHAR(13)&CHAR(10) & "- *Obs:* " & Q33 & CHAR(13)&CHAR(10) & CHAR(10) & "- *De*: " & _xlpm.deTxt & CHAR(13)&CHAR(10) & "- *Para*: " & _xlpm.paraTxt & CHAR(13)&CHAR(10) & "- *Ida e volta*: +/- " & TEXT(((D33*1.5)/1440),"h:mm") & "h | " & D33 & "km" )} -> - TRATOR: *1BM5080EEP4112594*_x000D_ - _x000D_ - *Cliente*: MANUTENÇÃO → JOSE VALCIR MOREIRA DA SILVA -NF 45974_x000D_ - *Obs:* JOSE VALCIR_x000D_ - *De*: MACPONTA AGRO DE IRATI_x000D_ - *Para*: https://maps.app.goo.gl/u6RQ92AcKr5YZVN5A_x000D_ - *Ida e volta*: +/- 2:52h | 115km
A34: CONCLUIDO | B34: TERCEIRO AGROMAQ | C34: =IFERROR((D34*1.5)/1440, "?") -> 0.103125 | D34: 99 | F34: 1000 | G34: 1XBDN10BHPP000280 | H34: 45974 | I34: 45974 | J34: MARLON BONILHA -NF61887 | K34: josiane.oliveira | L34: ARAPOTI | M34: CLIENTE | N34: DE LOJA PARA CLIENTE | O34: MPA | P34: https://maps.app.goo.gl/w3owGFpERZASWfsU6 | Q34: Marlon Bonilha CEN Alison Russi | R34: ARAPOTI | S34: TRATOR | T34: =IF( OR( IFERROR(FIND("BM",G34),0)>0, IFERROR(FIND("PY",G34),0)>0 ), MID(TRIM(SUBSTITUTE(SUBSTITUTE(G34,CHAR(160),""),CHAR(9),"")),4,5), MID(TRIM(SUBSTITUTE(SUBSTITUTE(G34,CHAR(160),""),CHAR(9),"")),4,4) ) -> DN10 | U34: {=_xlfn.LET( _xlpm.ch, TRIM(SUBSTITUTE(G34,CHAR(160),"")), _xlpm.ehTrator, OR(IFERROR(FIND("BM",_xlpm.ch),0)>0, IFERROR(FIND("PY",_xlpm.ch),0)>0), _xlpm.chave, IF(_xlpm.ehTrator, MID(_xlpm.ch,4,5), MID(_xlpm.ch,4,4)), _xlpm.fonte, IF(LEN(_xlpm.chave)=5, UTIL!BS:BS, UTIL!BR:BR), _xlpm.modelo, TRIM(SUBSTITUTE(T34,CHAR(160),"")), _xlpm.nomeMod, IFERROR(_xlfn.XLOOKUP("*"&_xlpm.modelo&"*", UTIL!D:D, UTIL!B:B, "", 2), IFERROR(_xlfn.XLOOKUP("*"&_xlpm.modelo&"*", UTIL!E:E, UTIL!B:B, "", 2), "")), _xlpm.tipoMod, IF(_xlpm.nomeMod="", "", IFERROR(LEFT(_xlpm.nomeMod, FIND(" ", _xlpm.nomeMod)-1), _xlpm.nomeMod)), _xlpm.dimMod, IFERROR(_xlfn.XLOOKUP("*"&_xlpm.modelo&"*", UTIL!D:D, UTIL!K:K, "", 2), IFERROR(_xlfn.XLOOKUP("*"&_xlpm.modelo&"*", UTIL!E:E, UTIL!K:K, "", 2), "")), _xlpm.tipotxt_antigo, IF(_xlpm.ehTrator, "TRATOR", IFERROR(_xlfn.XLOOKUP(_xlpm.chave, _xlpm.fonte, UTIL!BP:BP, "", 0), IFERROR(_xlfn.XLOOKUP("*"&_xlpm.chave&"*", _xlpm.fonte, UTIL!BP:BP, "", 2), "Não encontrado"))), _xlpm.dimtxt_antigo, IFERROR(_xlfn.XLOOKUP(_xlpm.chave, _xlpm.fonte, UTIL!BY:BY, "", 0), IFERROR(_xlfn.XLOOKUP("*"&_xlpm.chave&"*", _xlpm.fonte, UTIL!BY:BY, "", 2), "Não encontrado")), _xlpm.tipotxt, IF(_xlpm.tipoMod<>"", _xlpm.tipoMod, _xlpm.tipotxt_antigo), _xlpm.dimtxt, IF(_xlpm.dimMod<>"", _xlpm.dimMod, _xlpm.dimtxt_antigo), _xlpm.deTxt, IF(L34="CLIENTE", O34, IF(LEFT(L34,4)="http", L34, "MACPONTA AGRO DE "&L34)), _xlpm.paraBase, IF(M34="CLIENTE", P34, M34), _xlpm.paraTxt, IF(LEFT(_xlpm.paraBase,4)="http", _xlpm.paraBase, "MACPONTA AGRO DE "&_xlpm.paraBase), _xlpm.nfParte, IF(LEN(TRIM(I34))=0, "", " -NF "&TRIM(I34)), "- " & _xlpm.tipotxt & ": *" & G34 & "*" & CHAR(13)&CHAR(10) & "- " & _xlpm.dimtxt & CHAR(13)&CHAR(10) & "- *Cliente*: " & J34 & _xlpm.nfParte & CHAR(13)&CHAR(10) & "- *Obs:* " & Q34 & CHAR(13)&CHAR(10) & CHAR(10) & "- *De*: " & _xlpm.deTxt & CHAR(13)&CHAR(10) & "- *Para*: " & _xlpm.paraTxt & CHAR(13)&CHAR(10) & "- *Ida e volta*: +/- " & TEXT(((D34*1.5)/1440),"h:mm") & "h | " & D34 & "km" )} -> - : *1XBDN10BHPP000280*_x000D_ - _x000D_ - *Cliente*: MARLON BONILHA -NF61887 -NF 45974_x000D_ - *Obs:* Marlon Bonilha CEN Alison Russi_x000D_ - *De*: MACPONTA AGRO DE ARAPOTI_x000D_ - *Para*: https://maps.app.goo.gl/w3owGFpERZASWfsU6_x000D_ - *Ida e volta*: +/- 2:28h | 99km
A35: CONCLUIDO | B35: TERCEIRO DEMETRIO | C35: =IFERROR((D35*1.5)/1440, "?") -> 0.09375 | D35: 90 | F35: 430 | H35: 45975 | I35: 45975 | J35: CLIENTE → MANUTENÇÃO | K35: daisy.kakol | L35: CLIENTE | M35: IRATI | N35: DE CLIENTE PARA LOJA | O35: CLIENTE | P35: MPA | R35: PRUDENTOPOLIS | S35: TRATOR | T35: =IF( OR( IFERROR(FIND("BM",G35),0)>0, IFERROR(FIND("PY",G35),0)>0 ), MID(TRIM(SUBSTITUTE(SUBSTITUTE(G35,CHAR(160),""),CHAR(9),"")),4,5), MID(TRIM(SUBSTITUTE(SUBSTITUTE(G35,CHAR(160),""),CHAR(9),"")),4,4) ) | U35: {=_xlfn.LET( _xlpm.ch, TRIM(SUBSTITUTE(G35,CHAR(160),"")), _xlpm.ehTrator, OR(IFERROR(FIND("BM",_xlpm.ch),0)>0, IFERROR(FIND("PY",_xlpm.ch),0)>0), _xlpm.chave, IF(_xlpm.ehTrator, MID(_xlpm.ch,4,5), MID(_xlpm.ch,4,4)), _xlpm.fonte, IF(LEN(_xlpm.chave)=5, UTIL!BS:BS, UTIL!BR:BR), _xlpm.modelo, TRIM(SUBSTITUTE(T35,CHAR(160),"")), _xlpm.nomeMod, IFERROR(_xlfn.XLOOKUP("*"&_xlpm.modelo&"*", UTIL!D:D, UTIL!B:B, "", 2), IFERROR(_xlfn.XLOOKUP("*"&_xlpm.modelo&"*", UTIL!E:E, UTIL!B:B, "", 2), "")), _xlpm.tipoMod, IF(_xlpm.nomeMod="", "", IFERROR(LEFT(_xlpm.nomeMod, FIND(" ", _xlpm.nomeMod)-1), _xlpm.nomeMod)), _xlpm.dimMod, IFERROR(_xlfn.XLOOKUP("*"&_xlpm.modelo&"*", UTIL!D:D, UTIL!K:K, "", 2), IFERROR(_xlfn.XLOOKUP("*"&_xlpm.modelo&"*", UTIL!E:E, UTIL!K:K, "", 2), "")), _xlpm.tipotxt_antigo, IF(_xlpm.ehTrator, "TRATOR", IFERROR(_xlfn.XLOOKUP(_xlpm.chave, _xlpm.fonte, UTIL!BP:BP, "", 0), IFERROR(_xlfn.XLOOKUP("*"&_xlpm.chave&"*", _xlpm.fonte, UTIL!BP:BP, "", 2), "Não encontrado"))), _xlpm.dimtxt_antigo, IFERROR(_xlfn.XLOOKUP(_xlpm.chave, _xlpm.fonte, UTIL!BY:BY, "", 0), IFERROR(_xlfn.XLOOKUP("*"&_xlpm.chave&"*", _xlpm.fonte, UTIL!BY:BY, "", 2), "Não encontrado")), _xlpm.tipotxt, IF(_xlpm.tipoMod<>"", _xlpm.tipoMod, _xlpm.tipotxt_antigo), _xlpm.dimtxt, IF(_xlpm.dimMod<>"", _xlpm.dimMod, _xlpm.dimtxt_antigo), _xlpm.deTxt, IF(L35="CLIENTE", O35, IF(LEFT(L35,4)="http", L35, "MACPONTA AGRO DE "&L35)), _xlpm.paraBase, IF(M35="CLIENTE", P35, M35), _xlpm.paraTxt, IF(LEFT(_xlpm.paraBase,4)="http", _xlpm.paraBase, "MACPONTA AGRO DE "&_xlpm.paraBase), _xlpm.nfParte, IF(LEN(TRIM(I35))=0, "", " -NF "&TRIM(I35)), "- " & _xlpm.tipotxt & ": *" & G35 & "*" & CHAR(13)&CHAR(10) & "- " & _xlpm.dimtxt & CHAR(13)&CHAR(10) & "- *Cliente*: " & J35 & _xlpm.nfParte & CHAR(13)&CHAR(10) & "- *Obs:* " & Q35 & CHAR(13)&CHAR(10) & CHAR(10) & "- *De*: " & _xlpm.deTxt & CHAR(13)&CHAR(10) & "- *Para*: " & _xlpm.paraTxt & CHAR(13)&CHAR(10) & "- *Ida e volta*: +/- " & TEXT(((D35*1.5)/1440),"h:mm") & "h | " & D35 & "km" )} -> - NOME: **_x000D_ - SOLICITAÇÕES_x000D_ - *Cliente*: CLIENTE → MANUTENÇÃO -NF 45975_x000D_ - *Obs:* _x000D_ - *De*: CLIENTE_x000D_ - *Para*: MACPONTA AGRO DE IRATI_x000D_ - *Ida e volta*: +/- 2:15h | 90km
A36: CONCLUIDO | B36: TERCEIRO DEMETRIO | C36: =IFERROR((D36*1.5)/1440, "?") -> 0.0875 | D36: 84 | F36: 450 | G36: 1BM5080EKS4204142 | H36: 45975 | I36: 45975 | J36: ANDRE J NASCIMENTO -NF76885 | K36: marcio.jacovossi | L36: IRATI | M36: CLIENTE | N36: DE LOJA PARA CLIENTE | O36: MPA | P36: https://maps.app.goo.gl/VQtNqdXpX1Nn1Cwt8 | Q36: ANDRÉ 42 920007503 | R36: IRATI | S36: TRATOR | T36: =IF( OR( IFERROR(FIND("BM",G36),0)>0, IFERROR(FIND("PY",G36),0)>0 ), MID(TRIM(SUBSTITUTE(SUBSTITUTE(G36,CHAR(160),""),CHAR(9),"")),4,5), MID(TRIM(SUBSTITUTE(SUBSTITUTE(G36,CHAR(160),""),CHAR(9),"")),4,4) ) -> 5080E | U36: {=_xlfn.LET( _xlpm.ch, TRIM(SUBSTITUTE(G36,CHAR(160),"")), _xlpm.ehTrator, OR(IFERROR(FIND("BM",_xlpm.ch),0)>0, IFERROR(FIND("PY",_xlpm.ch),0)>0), _xlpm.chave, IF(_xlpm.ehTrator, MID(_xlpm.ch,4,5), MID(_xlpm.ch,4,4)), _xlpm.fonte, IF(LEN(_xlpm.chave)=5, UTIL!BS:BS, UTIL!BR:BR), _xlpm.modelo, TRIM(SUBSTITUTE(T36,CHAR(160),"")), _xlpm.nomeMod, IFERROR(_xlfn.XLOOKUP("*"&_xlpm.modelo&"*", UTIL!D:D, UTIL!B:B, "", 2), IFERROR(_xlfn.XLOOKUP("*"&_xlpm.modelo&"*", UTIL!E:E, UTIL!B:B, "", 2), "")), _xlpm.tipoMod, IF(_xlpm.nomeMod="", "", IFERROR(LEFT(_xlpm.nomeMod, FIND(" ", _xlpm.nomeMod)-1), _xlpm.nomeMod)), _xlpm.dimMod, IFERROR(_xlfn.XLOOKUP("*"&_xlpm.modelo&"*", UTIL!D:D, UTIL!K:K, "", 2), IFERROR(_xlfn.XLOOKUP("*"&_xlpm.modelo&"*", UTIL!E:E, UTIL!K:K, "", 2), "")), _xlpm.tipotxt_antigo, IF(_xlpm.ehTrator, "TRATOR", IFERROR(_xlfn.XLOOKUP(_xlpm.chave, _xlpm.fonte, UTIL!BP:BP, "", 0), IFERROR(_xlfn.XLOOKUP("*"&_xlpm.chave&"*", _xlpm.fonte, UTIL!BP:BP, "", 2), "Não encontrado"))), _xlpm.dimtxt_antigo, IFERROR(_xlfn.XLOOKUP(_xlpm.chave, _xlpm.fonte, UTIL!BY:BY, "", 0), IFERROR(_xlfn.XLOOKUP("*"&_xlpm.chave&"*", _xlpm.fonte, UTIL!BY:BY, "", 2), "Não encontrado")), _xlpm.tipotxt, IF(_xlpm.tipoMod<>"", _xlpm.tipoMod, _xlpm.tipotxt_antigo), _xlpm.dimtxt, IF(_xlpm.dimMod<>"", _xlpm.dimMod, _xlpm.dimtxt_antigo), _xlpm.deTxt, IF(L36="CLIENTE", O36, IF(LEFT(L36,4)="http", L36, "MACPONTA AGRO DE "&L36)), _xlpm.paraBase, IF(M36="CLIENTE", P36, M36), _xlpm.paraTxt, IF(LEFT(_xlpm.paraBase,4)="http", _xlpm.paraBase, "MACPONTA AGRO DE "&_xlpm.paraBase), _xlpm.nfParte, IF(LEN(TRIM(I36))=0, "", " -NF "&TRIM(I36)), "- " & _xlpm.tipotxt & ": *" & G36 & "*" & CHAR(13)&CHAR(10) & "- " & _xlpm.dimtxt & CHAR(13)&CHAR(10) & "- *Cliente*: " & J36 & _xlpm.nfParte & CHAR(13)&CHAR(10) & "- *Obs:* " & Q36 & CHAR(13)&CHAR(10) & CHAR(10) & "- *De*: " & _xlpm.deTxt & CHAR(13)&CHAR(10) & "- *Para*: " & _xlpm.paraTxt & CHAR(13)&CHAR(10) & "- *Ida e volta*: +/- " & TEXT(((D36*1.5)/1440),"h:mm") & "h | " & D36 & "km" )} -> - TRATOR: *1BM5080EKS4204142*_x000D_ - _x000D_ - *Cliente*: ANDRE J NASCIMENTO -NF76885 -NF 45975_x000D_ - *Obs:* ANDRÉ 42 920007503_x000D_ - *De*: MACPONTA AGRO DE IRATI_x000D_ - *Para*: https://maps.app.goo.gl/VQtNqdXpX1Nn1Cwt8_x000D_ - *Ida e volta*: +/- 2:06h | 84km
A37: CONCLUIDO | B37: TERCEIRO DEMETRIO | C37: =IFERROR((D37*1.5)/1440, "?") -> 0.11041667 | D37: 106 | F37: 300 | G37: 1BM5080EVS4203951 | H37: 45975 | I37: 45975 | J37: TIAGO J KOCHINHERKO -NF76887 | K37: marcio.jacovossi | L37: IRATI | M37: CLIENTE | N37: DE LOJA PARA CLIENTE | O37: MPA | P37: https://maps.app.goo.gl/z97gB1Y9xEQEsjNf6 | Q37: TIAGO 42 998121951 | R37: IRATI | S37: TRATOR | T37: =IF( OR( IFERROR(FIND("BM",G37),0)>0, IFERROR(FIND("PY",G37),0)>0 ), MID(TRIM(SUBSTITUTE(SUBSTITUTE(G37,CHAR(160),""),CHAR(9),"")),4,5), MID(TRIM(SUBSTITUTE(SUBSTITUTE(G37,CHAR(160),""),CHAR(9),"")),4,4) ) -> 5080E | U37: {=_xlfn.LET( _xlpm.ch, TRIM(SUBSTITUTE(G37,CHAR(160),"")), _xlpm.ehTrator, OR(IFERROR(FIND("BM",_xlpm.ch),0)>0, IFERROR(FIND("PY",_xlpm.ch),0)>0), _xlpm.chave, IF(_xlpm.ehTrator, MID(_xlpm.ch,4,5), MID(_xlpm.ch,4,4)), _xlpm.fonte, IF(LEN(_xlpm.chave)=5, UTIL!BS:BS, UTIL!BR:BR), _xlpm.modelo, TRIM(SUBSTITUTE(T37,CHAR(160),"")), _xlpm.nomeMod, IFERROR(_xlfn.XLOOKUP("*"&_xlpm.modelo&"*", UTIL!D:D, UTIL!B:B, "", 2), IFERROR(_xlfn.XLOOKUP("*"&_xlpm.modelo&"*", UTIL!E:E, UTIL!B:B, "", 2), "")), _xlpm.tipoMod, IF(_xlpm.nomeMod="", "", IFERROR(LEFT(_xlpm.nomeMod, FIND(" ", _xlpm.nomeMod)-1), _xlpm.nomeMod)), _xlpm.dimMod, IFERROR(_xlfn.XLOOKUP("*"&_xlpm.modelo&"*", UTIL!D:D, UTIL!K:K, "", 2), IFERROR(_xlfn.XLOOKUP("*"&_xlpm.modelo&"*", UTIL!E:E, UTIL!K:K, "", 2), "")), _xlpm.tipotxt_antigo, IF(_xlpm.ehTrator, "TRATOR", IFERROR(_xlfn.XLOOKUP(_xlpm.chave, _xlpm.fonte, UTIL!BP:BP, "", 0), IFERROR(_xlfn.XLOOKUP("*"&_xlpm.chave&"*", _xlpm.fonte, UTIL!BP:BP, "", 2), "Não encontrado"))), _xlpm.dimtxt_antigo, IFERROR(_xlfn.XLOOKUP(_xlpm.chave, _xlpm.fonte, UTIL!BY:BY, "", 0), IFERROR(_xlfn.XLOOKUP("*"&_xlpm.chave&"*", _xlpm.fonte, UTIL!BY:BY, "", 2), "Não encontrado")), _xlpm.tipotxt, IF(_xlpm.tipoMod<>"", _xlpm.tipoMod, _xlpm.tipotxt_antigo), _xlpm.dimtxt, IF(_xlpm.dimMod<>"", _xlpm.dimMod, _xlpm.dimtxt_antigo), _xlpm.deTxt, IF(L37="CLIENTE", O37, IF(LEFT(L37,4)="http", L37, "MACPONTA AGRO DE "&L37)), _xlpm.paraBase, IF(M37="CLIENTE", P37, M37), _xlpm.paraTxt, IF(LEFT(_xlpm.paraBase,4)="http", _xlpm.paraBase, "MACPONTA AGRO DE "&_xlpm.paraBase), _xlpm.nfParte, IF(LEN(TRIM(I37))=0, "", " -NF "&TRIM(I37)), "- " & _xlpm.tipotxt & ": *" & G37 & "*" & CHAR(13)&CHAR(10) & "- " & _xlpm.dimtxt & CHAR(13)&CHAR(10) & "- *Cliente*: " & J37 & _xlpm.nfParte & CHAR(13)&CHAR(10) & "- *Obs:* " & Q37 & CHAR(13)&CHAR(10) & CHAR(10) & "- *De*: " & _xlpm.deTxt & CHAR(13)&CHAR(10) & "- *Para*: " & _xlpm.paraTxt & CHAR(13)&CHAR(10) & "- *Ida e volta*: +/- " & TEXT(((D37*1.5)/1440),"h:mm") & "h | " & D37 & "km" )} -> - TRATOR: *1BM5080EVS4203951*_x000D_ - _x000D_ - *Cliente*: TIAGO J KOCHINHERKO -NF76887 -NF 45975_x000D_ - *Obs:* TIAGO 42 998121951_x000D_ - *De*: MACPONTA AGRO DE IRATI_x000D_ - *Para*: https://maps.app.goo.gl/z97gB1Y9xEQEsjNf6_x000D_ - *Ida e volta*: +/- 2:39h | 106km
A38: CONCLUIDO | B38: TERCEIRO JAPONES | C38: =IFERROR((D38*1.5)/1440, "?") -> 0.17291667 | D38: 166 | F38: 1328 | G38: 1BM5080EJN4108551 | H38: 45975 | I38: 45975 | J38: ADILSON P FURTADO -NF? | K38: rafael.santos | L38: CLIENTE | M38: ARAPOTI | N38: DE CLIENTE PARA LOJA | O38: https://maps.app.goo.gl/tLcmyZnTmDtxQsvb6 | P38: MPA | Q38: ADILSON APARECIDO FURTADO 43 - 99864 - 9233 | R38: ARAPOTI | S38: TRATOR | T38: =IF( OR( IFERROR(FIND("BM",G38),0)>0, IFERROR(FIND("PY",G38),0)>0 ), MID(TRIM(SUBSTITUTE(SUBSTITUTE(G38,CHAR(160),""),CHAR(9),"")),4,5), MID(TRIM(SUBSTITUTE(SUBSTITUTE(G38,CHAR(160),""),CHAR(9),"")),4,4) ) -> 5080E | U38: {=_xlfn.LET( _xlpm.ch, TRIM(SUBSTITUTE(G38,CHAR(160),"")), _xlpm.ehTrator, OR(IFERROR(FIND("BM",_xlpm.ch),0)>0, IFERROR(FIND("PY",_xlpm.ch),0)>0), _xlpm.chave, IF(_xlpm.ehTrator, MID(_xlpm.ch,4,5), MID(_xlpm.ch,4,4)), _xlpm.fonte, IF(LEN(_xlpm.chave)=5, UTIL!BS:BS, UTIL!BR:BR), _xlpm.modelo, TRIM(SUBSTITUTE(T38,CHAR(160),"")), _xlpm.nomeMod, IFERROR(_xlfn.XLOOKUP("*"&_xlpm.modelo&"*", UTIL!D:D, UTIL!B:B, "", 2), IFERROR(_xlfn.XLOOKUP("*"&_xlpm.modelo&"*", UTIL!E:E, UTIL!B:B, "", 2), "")), _xlpm.tipoMod, IF(_xlpm.nomeMod="", "", IFERROR(LEFT(_xlpm.nomeMod, FIND(" ", _xlpm.nomeMod)-1), _xlpm.nomeMod)), _xlpm.dimMod, IFERROR(_xlfn.XLOOKUP("*"&_xlpm.modelo&"*", UTIL!D:D, UTIL!K:K, "", 2), IFERROR(_xlfn.XLOOKUP("*"&_xlpm.modelo&"*", UTIL!E:E, UTIL!K:K, "", 2), "")), _xlpm.tipotxt_antigo, IF(_xlpm.ehTrator, "TRATOR", IFERROR(_xlfn.XLOOKUP(_xlpm.chave, _xlpm.fonte, UTIL!BP:BP, "", 0), IFERROR(_xlfn.XLOOKUP("*"&_xlpm.chave&"*", _xlpm.fonte, UTIL!BP:BP, "", 2), "Não encontrado"))), _xlpm.dimtxt_antigo, IFERROR(_xlfn.XLOOKUP(_xlpm.chave, _xlpm.fonte, UTIL!BY:BY, "", 0), IFERROR(_xlfn.XLOOKUP("*"&_xlpm.chave&"*", _xlpm.fonte, UTIL!BY:BY, "", 2), "Não encontrado")), _xlpm.tipotxt, IF(_xlpm.tipoMod<>"", _xlpm.tipoMod, _xlpm.tipotxt_antigo), _xlpm.dimtxt, IF(_xlpm.dimMod<>"", _xlpm.dimMod, _xlpm.dimtxt_antigo), _xlpm.deTxt, IF(L38="CLIENTE", O38, IF(LEFT(L38,4)="http", L38, "MACPONTA AGRO DE "&L38)), _xlpm.paraBase, IF(M38="CLIENTE", P38, M38), _xlpm.paraTxt, IF(LEFT(_xlpm.paraBase,4)="http", _xlpm.paraBase, "MACPONTA AGRO DE "&_xlpm.paraBase), _xlpm.nfParte, IF(LEN(TRIM(I38))=0, "", " -NF "&TRIM(I38)), "- " & _xlpm.tipotxt & ": *" & G38 & "*" & CHAR(13)&CHAR(10) & "- " & _xlpm.dimtxt & CHAR(13)&CHAR(10) & "- *Cliente*: " & J38 & _xlpm.nfParte & CHAR(13)&CHAR(10) & "- *Obs:* " & Q38 & CHAR(13)&CHAR(10) & CHAR(10) & "- *De*: " & _xlpm.deTxt & CHAR(13)&CHAR(10) & "- *Para*: " & _xlpm.paraTxt & CHAR(13)&CHAR(10) & "- *Ida e volta*: +/- " & TEXT(((D38*1.5)/1440),"h:mm") & "h | " & D38 & "km" )} -> - TRATOR: *1BM5080EJN4108551*_x000D_ - _x000D_ - *Cliente*: ADILSON P FURTADO -NF? -NF 45975_x000D_ - *Obs:* ADILSON APARECIDO FURTADO 43 - 99864 - 9233_x000D_ - *De*: https://maps.app.goo.gl/tLcmyZnTmDtxQsvb6_x000D_ - *Para*: MACPONTA AGRO DE ARAPOTI_x000D_ - *Ida e volta*: +/- 4:09h | 166km
A39: CONCLUIDO | B39: TERCEIRO MAZETTO | C39: =IFERROR((D39*1.5)/1440, "?") -> 0.4375 | D39: 420 | F39: 3662.3 | G39: 1BM6100JCSD602163 | H39: 45975 | I39: 45975 | J39: RONALDO RABBERS -NF109962 | K39: fernando.wiesinies | L39: GUARAPUAVA | M39: CLIENTE | N39: DE LOJA PARA CLIENTE | O39: MPA | P39: https://maps.app.goo.gl/6skd9a23gozJLC8q6?g_st=aw | Q39: Lucas (42)988040302 | R39: CASTRO | S39: TRATOR | T39: =IF( OR( IFERROR(FIND("BM",G39),0)>0, IFERROR(FIND("PY",G39),0)>0 ), MID(TRIM(SUBSTITUTE(SUBSTITUTE(G39,CHAR(160),""),CHAR(9),"")),4,5), MID(TRIM(SUBSTITUTE(SUBSTITUTE(G39,CHAR(160),""),CHAR(9),"")),4,4) ) -> 6100J | U39: {=_xlfn.LET( _xlpm.ch, TRIM(SUBSTITUTE(G39,CHAR(160),"")), _xlpm.ehTrator, OR(IFERROR(FIND("BM",_xlpm.ch),0)>0, IFERROR(FIND("PY",_xlpm.ch),0)>0), _xlpm.chave, IF(_xlpm.ehTrator, MID(_xlpm.ch,4,5), MID(_xlpm.ch,4,4)), _xlpm.fonte, IF(LEN(_xlpm.chave)=5, UTIL!BS:BS, UTIL!BR:BR), _xlpm.modelo, TRIM(SUBSTITUTE(T39,CHAR(160),"")), _xlpm.nomeMod, IFERROR(_xlfn.XLOOKUP("*"&_xlpm.modelo&"*", UTIL!D:D, UTIL!B:B, "", 2), IFERROR(_xlfn.XLOOKUP("*"&_xlpm.modelo&"*", UTIL!E:E, UTIL!B:B, "", 2), "")), _xlpm.tipoMod, IF(_xlpm.nomeMod="", "", IFERROR(LEFT(_xlpm.nomeMod, FIND(" ", _xlpm.nomeMod)-1), _xlpm.nomeMod)), _xlpm.dimMod, IFERROR(_xlfn.XLOOKUP("*"&_xlpm.modelo&"*", UTIL!D:D, UTIL!K:K, "", 2), IFERROR(_xlfn.XLOOKUP("*"&_xlpm.modelo&"*", UTIL!E:E, UTIL!K:K, "", 2), "")), _xlpm.tipotxt_antigo, IF(_xlpm.ehTrator, "TRATOR", IFERROR(_xlfn.XLOOKUP(_xlpm.chave, _xlpm.fonte, UTIL!BP:BP, "", 0), IFERROR(_xlfn.XLOOKUP("*"&_xlpm.chave&"*", _xlpm.fonte, UTIL!BP:BP, "", 2), "Não encontrado"))), _xlpm.dimtxt_antigo, IFERROR(_xlfn.XLOOKUP(_xlpm.chave, _xlpm.fonte, UTIL!BY:BY, "", 0), IFERROR(_xlfn.XLOOKUP("*"&_xlpm.chave&"*", _xlpm.fonte, UTIL!BY:BY, "", 2), "Não encontrado")), _xlpm.tipotxt, IF(_xlpm.tipoMod<>"", _xlpm.tipoMod, _xlpm.tipotxt_antigo), _xlpm.dimtxt, IF(_xlpm.dimMod<>"", _xlpm.dimMod, _xlpm.dimtxt_antigo), _xlpm.deTxt, IF(L39="CLIENTE", O39, IF(LEFT(L39,4)="http", L39, "MACPONTA AGRO DE "&L39)), _xlpm.paraBase, IF(M39="CLIENTE", P39, M39), _xlpm.paraTxt, IF(LEFT(_xlpm.paraBase,4)="http", _xlpm.paraBase, "MACPONTA AGRO DE "&_xlpm.paraBase), _xlpm.nfParte, IF(LEN(TRIM(I39))=0, "", " -NF "&TRIM(I39)), "- " & _xlpm.tipotxt & ": *" & G39 & "*" & CHAR(13)&CHAR(10) & "- " & _xlpm.dimtxt & CHAR(13)&CHAR(10) & "- *Cliente*: " & J39 & _xlpm.nfParte & CHAR(13)&CHAR(10) & "- *Obs:* " & Q39 & CHAR(13)&CHAR(10) & CHAR(10) & "- *De*: " & _xlpm.deTxt & CHAR(13)&CHAR(10) & "- *Para*: " & _xlpm.paraTxt & CHAR(13)&CHAR(10) & "- *Ida e volta*: +/- " & TEXT(((D39*1.5)/1440),"h:mm") & "h | " & D39 & "km" )} -> - TRATOR: *1BM6100JCSD602163*_x000D_ - _x000D_ - *Cliente*: RONALDO RABBERS -NF109962 -NF 45975_x000D_ - *Obs:* Lucas (42)988040302_x000D_ - *De*: MACPONTA AGRO DE GUARAPUAVA_x000D_ - *Para*: https://maps.app.goo.gl/6skd9a23gozJLC8q6?g_st=aw_x000D_ - *Ida e volta*: +/- 10:30h | 420km
A40: CONCLUIDO (D) | B40: PROPRIO VW | C40: =IFERROR((D40*1.5)/1440, "?") -> 0.31875 | D40: 306 | E40: =IFERROR((D40*6),"?") -> 1836 | G40: 1BM5080ETS6204305 | H40: 45975 | I40: 45975 | J40: SILO DO MALOCA -NF61894 | K40: josiane.oliveira | L40: ARAPOTI | M40: CLIENTE | N40: DE LOJA PARA DEMONSTRAÇÃO | O40: MPA | P40: https://maps.app.goo.gl/TYsDXWU4kqkeGb8D6 | Q40: Conexão JD Estática + Jantar - São José da Boa Vista | R40: ARAPOTI | S40: TRATOR | T40: =IF( OR( IFERROR(FIND("BM",G40),0)>0, IFERROR(FIND("PY",G40),0)>0 ), MID(TRIM(SUBSTITUTE(SUBSTITUTE(G40,CHAR(160),""),CHAR(9),"")),4,5), MID(TRIM(SUBSTITUTE(SUBSTITUTE(G40,CHAR(160),""),CHAR(9),"")),4,4) ) -> 5080E | U40: {=_xlfn.LET( _xlpm.ch, TRIM(SUBSTITUTE(G40,CHAR(160),"")), _xlpm.ehTrator, OR(IFERROR(FIND("BM",_xlpm.ch),0)>0, IFERROR(FIND("PY",_xlpm.ch),0)>0), _xlpm.chave, IF(_xlpm.ehTrator, MID(_xlpm.ch,4,5), MID(_xlpm.ch,4,4)), _xlpm.fonte, IF(LEN(_xlpm.chave)=5, UTIL!BS:BS, UTIL!BR:BR), _xlpm.modelo, TRIM(SUBSTITUTE(T40,CHAR(160),"")), _xlpm.nomeMod, IFERROR(_xlfn.XLOOKUP("*"&_xlpm.modelo&"*", UTIL!D:D, UTIL!B:B, "", 2), IFERROR(_xlfn.XLOOKUP("*"&_xlpm.modelo&"*", UTIL!E:E, UTIL!B:B, "", 2), "")), _xlpm.tipoMod, IF(_xlpm.nomeMod="", "", IFERROR(LEFT(_xlpm.nomeMod, FIND(" ", _xlpm.nomeMod)-1), _xlpm.nomeMod)), _xlpm.dimMod, IFERROR(_xlfn.XLOOKUP("*"&_xlpm.modelo&"*", UTIL!D:D, UTIL!K:K, "", 2), IFERROR(_xlfn.XLOOKUP("*"&_xlpm.modelo&"*", UTIL!E:E, UTIL!K:K, "", 2), "")), _xlpm.tipotxt_antigo, IF(_xlpm.ehTrator, "TRATOR", IFERROR(_xlfn.XLOOKUP(_xlpm.chave, _xlpm.fonte, UTIL!BP:BP, "", 0), IFERROR(_xlfn.XLOOKUP("*"&_xlpm.chave&"*", _xlpm.fonte, UTIL!BP:BP, "", 2), "Não encontrado"))), _xlpm.dimtxt_antigo, IFERROR(_xlfn.XLOOKUP(_xlpm.chave, _xlpm.fonte, UTIL!BY:BY, "", 0), IFERROR(_xlfn.XLOOKUP("*"&_xlpm.chave&"*", _xlpm.fonte, UTIL!BY:BY, "", 2), "Não encontrado")), _xlpm.tipotxt, IF(_xlpm.tipoMod<>"", _xlpm.tipoMod, _xlpm.tipotxt_antigo), _xlpm.dimtxt, IF(_xlpm.dimMod<>"", _xlpm.dimMod, _xlpm.dimtxt_antigo), _xlpm.deTxt, IF(L40="CLIENTE", O40, IF(LEFT(L40,4)="http", L40, "MACPONTA AGRO DE "&L40)), _xlpm.paraBase, IF(M40="CLIENTE", P40, M40), _xlpm.paraTxt, IF(LEFT(_xlpm.paraBase,4)="http", _xlpm.paraBase, "MACPONTA AGRO DE "&_xlpm.paraBase), _xlpm.nfParte, IF(LEN(TRIM(I40))=0, "", " -NF "&TRIM(I40)), "- " & _xlpm.tipotxt & ": *" & G40 & "*" & CHAR(13)&CHAR(10) & "- " & _xlpm.dimtxt & CHAR(13)&CHAR(10) & "- *Cliente*: " & J40 & _xlpm.nfParte & CHAR(13)&CHAR(10) & "- *Obs:* " & Q40 & CHAR(13)&CHAR(10) & CHAR(10) & "- *De*: " & _xlpm.deTxt & CHAR(13)&CHAR(10) & "- *Para*: " & _xlpm.paraTxt & CHAR(13)&CHAR(10) & "- *Ida e volta*: +/- " & TEXT(((D40*1.5)/1440),"h:mm") & "h | " & D40 & "km" )} -> - TRATOR: *1BM5080ETS6204305*_x000D_ - _x000D_ - *Cliente*: SILO DO MALOCA -NF61894 -NF 45975_x000D_ - *Obs:* Conexão JD Estática + Jantar - São José da Boa Vista_x000D_ - *De*: MACPONTA AGRO DE ARAPOTI_x000D_ - *Para*: https://maps.app.goo.gl/TYsDXWU4kqkeGb8D6_x000D_ - *Ida e volta*: +/- 7:39h | 306km
A41: CONCLUIDO (D) | B41: PROPRIO VW | C41: =IFERROR((D41*1.5)/1440, "?") -> 0.31875 | D41: 306 | E41: =IFERROR((D41*6),"?") -> 1836 | G41: 1BM5080EVS4204226 | H41: 45975 | I41: 45975 | J41: SILO DO MALOCA -NF61894 | K41: josiane.oliveira | L41: ARAPOTI | M41: CLIENTE | N41: DE LOJA PARA DEMONSTRAÇÃO | O41: MPA | P41: https://maps.app.goo.gl/TYsDXWU4kqkeGb8D6 | Q41: Conexão JD Estática + Jantar - São José da Boa Vista | R41: ARAPOTI | S41: TRATOR | T41: =IF( OR( IFERROR(FIND("BM",G41),0)>0, IFERROR(FIND("PY",G41),0)>0 ), MID(TRIM(SUBSTITUTE(SUBSTITUTE(G41,CHAR(160),""),CHAR(9),"")),4,5), MID(TRIM(SUBSTITUTE(SUBSTITUTE(G41,CHAR(160),""),CHAR(9),"")),4,4) ) -> 5080E | U41: {=_xlfn.LET( _xlpm.ch, TRIM(SUBSTITUTE(G41,CHAR(160),"")), _xlpm.ehTrator, OR(IFERROR(FIND("BM",_xlpm.ch),0)>0, IFERROR(FIND("PY",_xlpm.ch),0)>0), _xlpm.chave, IF(_xlpm.ehTrator, MID(_xlpm.ch,4,5), MID(_xlpm.ch,4,4)), _xlpm.fonte, IF(LEN(_xlpm.chave)=5, UTIL!BS:BS, UTIL!BR:BR), _xlpm.modelo, TRIM(SUBSTITUTE(T41,CHAR(160),"")), _xlpm.nomeMod, IFERROR(_xlfn.XLOOKUP("*"&_xlpm.modelo&"*", UTIL!D:D, UTIL!B:B, "", 2), IFERROR(_xlfn.XLOOKUP("*"&_xlpm.modelo&"*", UTIL!E:E, UTIL!B:B, "", 2), "")), _xlpm.tipoMod, IF(_xlpm.nomeMod="", "", IFERROR(LEFT(_xlpm.nomeMod, FIND(" ", _xlpm.nomeMod)-1), _xlpm.nomeMod)), _xlpm.dimMod, IFERROR(_xlfn.XLOOKUP("*"&_xlpm.modelo&"*", UTIL!D:D, UTIL!K:K, "", 2), IFERROR(_xlfn.XLOOKUP("*"&_xlpm.modelo&"*", UTIL!E:E, UTIL!K:K, "", 2), "")), _xlpm.tipotxt_antigo, IF(_xlpm.ehTrator, "TRATOR", IFERROR(_xlfn.XLOOKUP(_xlpm.chave, _xlpm.fonte, UTIL!BP:BP, "", 0), IFERROR(_xlfn.XLOOKUP("*"&_xlpm.chave&"*", _xlpm.fonte, UTIL!BP:BP, "", 2), "Não encontrado"))), _xlpm.dimtxt_antigo, IFERROR(_xlfn.XLOOKUP(_xlpm.chave, _xlpm.fonte, UTIL!BY:BY, "", 0), IFERROR(_xlfn.XLOOKUP("*"&_xlpm.chave&"*", _xlpm.fonte, UTIL!BY:BY, "", 2), "Não encontrado")), _xlpm.tipotxt, IF(_xlpm.tipoMod<>"", _xlpm.tipoMod, _xlpm.tipotxt_antigo), _xlpm.dimtxt, IF(_xlpm.dimMod<>"", _xlpm.dimMod, _xlpm.dimtxt_antigo), _xlpm.deTxt, IF(L41="CLIENTE", O41, IF(LEFT(L41,4)="http", L41, "MACPONTA AGRO DE "&L41)), _xlpm.paraBase, IF(M41="CLIENTE", P41, M41), _xlpm.paraTxt, IF(LEFT(_xlpm.paraBase,4)="http", _xlpm.paraBase, "MACPONTA AGRO DE "&_xlpm.paraBase), _xlpm.nfParte, IF(LEN(TRIM(I41))=0, "", " -NF "&TRIM(I41)), "- " & _xlpm.tipotxt & ": *" & G41 & "*" & CHAR(13)&CHAR(10) & "- " & _xlpm.dimtxt & CHAR(13)&CHAR(10) & "- *Cliente*: " & J41 & _xlpm.nfParte & CHAR(13)&CHAR(10) & "- *Obs:* " & Q41 & CHAR(13)&CHAR(10) & CHAR(10) & "- *De*: " & _xlpm.deTxt & CHAR(13)&CHAR(10) & "- *Para*: " & _xlpm.paraTxt & CHAR(13)&CHAR(10) & "- *Ida e volta*: +/- " & TEXT(((D41*1.5)/1440),"h:mm") & "h | " & D41 & "km" )} -> - TRATOR: *1BM5080EVS4204226*_x000D_ - _x000D_ - *Cliente*: SILO DO MALOCA -NF61894 -NF 45975_x000D_ - *Obs:* Conexão JD Estática + Jantar - São José da Boa Vista_x000D_ - *De*: MACPONTA AGRO DE ARAPOTI_x000D_ - *Para*: https://maps.app.goo.gl/TYsDXWU4kqkeGb8D6_x000D_ - *Ida e volta*: +/- 7:39h | 306km
A42: CONCLUIDO (D) | B42: TERCEIRO ZORTEA | C42: =IFERROR((D42*1.5)/1440, "?") -> 0.49791667 | D42: 478 | F42: 1600 | G42: 1CQFA25APS0160156 | H42: 45975 | I42: 45975 | J42: SILO DO MALOCA -NF61894 | K42: josiane.oliveira | L42: IRATI | M42: CLIENTE | N42: DE LOJA PARA DEMONSTRAÇÃO | O42: MPA | P42: https://maps.app.goo.gl/TYsDXWU4kqkeGb8D6 | Q42: Conexão JD Estática + Jantar - São José da Boa Vista | R42: ARAPOTI | S42: PLATAFORMA | T42: =IF( OR( IFERROR(FIND("BM",G42),0)>0, IFERROR(FIND("PY",G42),0)>0 ), MID(TRIM(SUBSTITUTE(SUBSTITUTE(G42,CHAR(160),""),CHAR(9),"")),4,5), MID(TRIM(SUBSTITUTE(SUBSTITUTE(G42,CHAR(160),""),CHAR(9),"")),4,4) ) -> FA25 | U42: {=_xlfn.LET( _xlpm.ch, TRIM(SUBSTITUTE(G42,CHAR(160),"")), _xlpm.ehTrator, OR(IFERROR(FIND("BM",_xlpm.ch),0)>0, IFERROR(FIND("PY",_xlpm.ch),0)>0), _xlpm.chave, IF(_xlpm.ehTrator, MID(_xlpm.ch,4,5), MID(_xlpm.ch,4,4)), _xlpm.fonte, IF(LEN(_xlpm.chave)=5, UTIL!BS:BS, UTIL!BR:BR), _xlpm.modelo, TRIM(SUBSTITUTE(T42,CHAR(160),"")), _xlpm.nomeMod, IFERROR(_xlfn.XLOOKUP("*"&_xlpm.modelo&"*", UTIL!D:D, UTIL!B:B, "", 2), IFERROR(_xlfn.XLOOKUP("*"&_xlpm.modelo&"*", UTIL!E:E, UTIL!B:B, "", 2), "")), _xlpm.tipoMod, IF(_xlpm.nomeMod="", "", IFERROR(LEFT(_xlpm.nomeMod, FIND(" ", _xlpm.nomeMod)-1), _xlpm.nomeMod)), _xlpm.dimMod, IFERROR(_xlfn.XLOOKUP("*"&_xlpm.modelo&"*", UTIL!D:D, UTIL!K:K, "", 2), IFERROR(_xlfn.XLOOKUP("*"&_xlpm.modelo&"*", UTIL!E:E, UTIL!K:K, "", 2), "")), _xlpm.tipotxt_antigo, IF(_xlpm.ehTrator, "TRATOR", IFERROR(_xlfn.XLOOKUP(_xlpm.chave, _xlpm.fonte, UTIL!BP:BP, "", 0), IFERROR(_xlfn.XLOOKUP("*"&_xlpm.chave&"*", _xlpm.fonte, UTIL!BP:BP, "", 2), "Não encontrado"))), _xlpm.dimtxt_antigo, IFERROR(_xlfn.XLOOKUP(_xlpm.chave, _xlpm.fonte, UTIL!BY:BY, "", 0), IFERROR(_xlfn.XLOOKUP("*"&_xlpm.chave&"*", _xlpm.fonte, UTIL!BY:BY, "", 2), "Não encontrado")), _xlpm.tipotxt, IF(_xlpm.tipoMod<>"", _xlpm.tipoMod, _xlpm.tipotxt_antigo), _xlpm.dimtxt, IF(_xlpm.dimMod<>"", _xlpm.dimMod, _xlpm.dimtxt_antigo), _xlpm.deTxt, IF(L42="CLIENTE", O42, IF(LEFT(L42,4)="http", L42, "MACPONTA AGRO DE "&L42)), _xlpm.paraBase, IF(M42="CLIENTE", P42, M42), _xlpm.paraTxt, IF(LEFT(_xlpm.paraBase,4)="http", _xlpm.paraBase, "MACPONTA AGRO DE "&_xlpm.paraBase), _xlpm.nfParte, IF(LEN(TRIM(I42))=0, "", " -NF "&TRIM(I42)), "- " & _xlpm.tipotxt & ": *" & G42 & "*" & CHAR(13)&CHAR(10) & "- " & _xlpm.dimtxt & CHAR(13)&CHAR(10) & "- *Cliente*: " & J42 & _xlpm.nfParte & CHAR(13)&CHAR(10) & "- *Obs:* " & Q42 & CHAR(13)&CHAR(10) & CHAR(10) & "- *De*: " & _xlpm.deTxt & CHAR(13)&CHAR(10) & "- *Para*: " & _xlpm.paraTxt & CHAR(13)&CHAR(10) & "- *Ida e volta*: +/- " & TEXT(((D42*1.5)/1440),"h:mm") & "h | " & D42 & "km" )} -> - PLATAFORMA: *1CQFA25APS0160156*_x000D_ - A:1,60 x C:7,60 x L:1,80-1,80 x P:2.100kg_x000D_ - *Cliente*: SILO DO MALOCA -NF61894 -NF 45975_x000D_ - *Obs:* Conexão JD Estática + Jantar - São José da Boa Vista_x000D_ - *De*: MACPONTA AGRO DE IRATI_x000D_ - *Para*: https://maps.app.goo.gl/TYsDXWU4kqkeGb8D6_x000D_ - *Ida e volta*: +/- 11:57h | 478km
A43: CONCLUIDO (D) | B43: TERCEIRO ZORTEA | C43: =IFERROR((D43*1.5)/1440, "?") -> 0.49791667 | D43: 478 | F43: 3800 | G43: 1CQS440ACS0155147 | H43: 45975 | I43: 45975 | J43: SILO DO MALOCA -NF61894 | K43: josiane.oliveira | L43: IRATI | M43: CLIENTE | N43: DE LOJA PARA DEMONSTRAÇÃO | O43: MPA | P43: https://maps.app.goo.gl/TYsDXWU4kqkeGb8D6 | Q43: Conexão JD Estática + Jantar - São José da Boa Vista | R43: ARAPOTI | S43: COLHEITADEIRA | T43: =IF( OR( IFERROR(FIND("BM",G43),0)>0, IFERROR(FIND("PY",G43),0)>0 ), MID(TRIM(SUBSTITUTE(SUBSTITUTE(G43,CHAR(160),""),CHAR(9),"")),4,5), MID(TRIM(SUBSTITUTE(SUBSTITUTE(G43,CHAR(160),""),CHAR(9),"")),4,4) ) -> S440 | U43: {=_xlfn.LET( _xlpm.ch, TRIM(SUBSTITUTE(G43,CHAR(160),"")), _xlpm.ehTrator, OR(IFERROR(FIND("BM",_xlpm.ch),0)>0, IFERROR(FIND("PY",_xlpm.ch),0)>0), _xlpm.chave, IF(_xlpm.ehTrator, MID(_xlpm.ch,4,5), MID(_xlpm.ch,4,4)), _xlpm.fonte, IF(LEN(_xlpm.chave)=5, UTIL!BS:BS, UTIL!BR:BR), _xlpm.modelo, TRIM(SUBSTITUTE(T43,CHAR(160),"")), _xlpm.nomeMod, IFERROR(_xlfn.XLOOKUP("*"&_xlpm.modelo&"*", UTIL!D:D, UTIL!B:B, "", 2), IFERROR(_xlfn.XLOOKUP("*"&_xlpm.modelo&"*", UTIL!E:E, UTIL!B:B, "", 2), "")), _xlpm.tipoMod, IF(_xlpm.nomeMod="", "", IFERROR(LEFT(_xlpm.nomeMod, FIND(" ", _xlpm.nomeMod)-1), _xlpm.nomeMod)), _xlpm.dimMod, IFERROR(_xlfn.XLOOKUP("*"&_xlpm.modelo&"*", UTIL!D:D, UTIL!K:K, "", 2), IFERROR(_xlfn.XLOOKUP("*"&_xlpm.modelo&"*", UTIL!E:E, UTIL!K:K, "", 2), "")), _xlpm.tipotxt_antigo, IF(_xlpm.ehTrator, "TRATOR", IFERROR(_xlfn.XLOOKUP(_xlpm.chave, _xlpm.fonte, UTIL!BP:BP, "", 0), IFERROR(_xlfn.XLOOKUP("*"&_xlpm.chave&"*", _xlpm.fonte, UTIL!BP:BP, "", 2), "Não encontrado"))), _xlpm.dimtxt_antigo, IFERROR(_xlfn.XLOOKUP(_xlpm.chave, _xlpm.fonte, UTIL!BY:BY, "", 0), IFERROR(_xlfn.XLOOKUP("*"&_xlpm.chave&"*", _xlpm.fonte, UTIL!BY:BY, "", 2), "Não encontrado")), _xlpm.tipotxt, IF(_xlpm.tipoMod<>"", _xlpm.tipoMod, _xlpm.tipotxt_antigo), _xlpm.dimtxt, IF(_xlpm.dimMod<>"", _xlpm.dimMod, _xlpm.dimtxt_antigo), _xlpm.deTxt, IF(L43="CLIENTE", O43, IF(LEFT(L43,4)="http", L43, "MACPONTA AGRO DE "&L43)), _xlpm.paraBase, IF(M43="CLIENTE", P43, M43), _xlpm.paraTxt, IF(LEFT(_xlpm.paraBase,4)="http", _xlpm.paraBase, "MACPONTA AGRO DE "&_xlpm.paraBase), _xlpm.nfParte, IF(LEN(TRIM(I43))=0, "", " -NF "&TRIM(I43)), "- " & _xlpm.tipotxt & ": *" & G43 & "*" & CHAR(13)&CHAR(10) & "- " & _xlpm.dimtxt & CHAR(13)&CHAR(10) & "- *Cliente*: " & J43 & _xlpm.nfParte & CHAR(13)&CHAR(10) & "- *Obs:* " & Q43 & CHAR(13)&CHAR(10) & CHAR(10) & "- *De*: " & _xlpm.deTxt & CHAR(13)&CHAR(10) & "- *Para*: " & _xlpm.paraTxt & CHAR(13)&CHAR(10) & "- *Ida e volta*: +/- " & TEXT(((D43*1.5)/1440),"h:mm") & "h | " & D43 & "km" )} -> - COLHEITADEIRA: *1CQS440ACS0155147*_x000D_ - A:4,10 x C:7,70 x L:3,40-4,10 x P:11.800kg_x000D_ - *Cliente*: SILO DO MALOCA -NF61894 -NF 45975_x000D_ - *Obs:* Conexão JD Estática + Jantar - São José da Boa Vista_x000D_ - *De*: MACPONTA AGRO DE IRATI_x000D_ - *Para*: https://maps.app.goo.gl/TYsDXWU4kqkeGb8D6_x000D_ - *Ida e volta*: +/- 11:57h | 478km
A44: CONCLUIDO (D) | B44: PROPRIO VW | C44: =IFERROR((D44*1.5)/1440, "?") -> 0.31875 | D44: 306 | E44: =IFERROR((D44*6),"?") -> 1836 | G44: 1BM5080ETS6204305 | H44: 45978 | I44: 45978 | J44: SILO DO MALOCA -NF61894 VOLTA | K44: josiane.oliveira | L44: ARAPOTI | M44: CLIENTE | N44: DE LOJA PARA DEMONSTRAÇÃO | O44: MPA | P44: https://maps.app.goo.gl/TYsDXWU4kqkeGb8D6 | Q44: Conexão JD Estática + Jantar - São José da Boa Vista | R44: ARAPOTI | S44: TRATOR | T44: =IF( OR( IFERROR(FIND("BM",G44),0)>0, IFERROR(FIND("PY",G44),0)>0 ), MID(TRIM(SUBSTITUTE(SUBSTITUTE(G44,CHAR(160),""),CHAR(9),"")),4,5), MID(TRIM(SUBSTITUTE(SUBSTITUTE(G44,CHAR(160),""),CHAR(9),"")),4,4) ) -> 5080E | U44: {=_xlfn.LET( _xlpm.ch, TRIM(SUBSTITUTE(G44,CHAR(160),"")), _xlpm.ehTrator, OR(IFERROR(FIND("BM",_xlpm.ch),0)>0, IFERROR(FIND("PY",_xlpm.ch),0)>0), _xlpm.chave, IF(_xlpm.ehTrator, MID(_xlpm.ch,4,5), MID(_xlpm.ch,4,4)), _xlpm.fonte, IF(LEN(_xlpm.chave)=5, UTIL!BS:BS, UTIL!BR:BR), _xlpm.modelo, TRIM(SUBSTITUTE(T44,CHAR(160),"")), _xlpm.nomeMod, IFERROR(_xlfn.XLOOKUP("*"&_xlpm.modelo&"*", UTIL!D:D, UTIL!B:B, "", 2), IFERROR(_xlfn.XLOOKUP("*"&_xlpm.modelo&"*", UTIL!E:E, UTIL!B:B, "", 2), "")), _xlpm.tipoMod, IF(_xlpm.nomeMod="", "", IFERROR(LEFT(_xlpm.nomeMod, FIND(" ", _xlpm.nomeMod)-1), _xlpm.nomeMod)), _xlpm.dimMod, IFERROR(_xlfn.XLOOKUP("*"&_xlpm.modelo&"*", UTIL!D:D, UTIL!K:K, "", 2), IFERROR(_xlfn.XLOOKUP("*"&_xlpm.modelo&"*", UTIL!E:E, UTIL!K:K, "", 2), "")), _xlpm.tipotxt_antigo, IF(_xlpm.ehTrator, "TRATOR", IFERROR(_xlfn.XLOOKUP(_xlpm.chave, _xlpm.fonte, UTIL!BP:BP, "", 0), IFERROR(_xlfn.XLOOKUP("*"&_xlpm.chave&"*", _xlpm.fonte, UTIL!BP:BP, "", 2), "Não encontrado"))), _xlpm.dimtxt_antigo, IFERROR(_xlfn.XLOOKUP(_xlpm.chave, _xlpm.fonte, UTIL!BY:BY, "", 0), IFERROR(_xlfn.XLOOKUP("*"&_xlpm.chave&"*", _xlpm.fonte, UTIL!BY:BY, "", 2), "Não encontrado")), _xlpm.tipotxt, IF(_xlpm.tipoMod<>"", _xlpm.tipoMod, _xlpm.tipotxt_antigo), _xlpm.dimtxt, IF(_xlpm.dimMod<>"", _xlpm.dimMod, _xlpm.dimtxt_antigo), _xlpm.deTxt, IF(L44="CLIENTE", O44, IF(LEFT(L44,4)="http", L44, "MACPONTA AGRO DE "&L44)), _xlpm.paraBase, IF(M44="CLIENTE", P44, M44), _xlpm.paraTxt, IF(LEFT(_xlpm.paraBase,4)="http", _xlpm.paraBase, "MACPONTA AGRO DE "&_xlpm.paraBase), _xlpm.nfParte, IF(LEN(TRIM(I44))=0, "", " -NF "&TRIM(I44)), "- " & _xlpm.tipotxt & ": *" & G44 & "*" & CHAR(13)&CHAR(10) & "- " & _xlpm.dimtxt & CHAR(13)&CHAR(10) & "- *Cliente*: " & J44 & _xlpm.nfParte & CHAR(13)&CHAR(10) & "- *Obs:* " & Q44 & CHAR(13)&CHAR(10) & CHAR(10) & "- *De*: " & _xlpm.deTxt & CHAR(13)&CHAR(10) & "- *Para*: " & _xlpm.paraTxt & CHAR(13)&CHAR(10) & "- *Ida e volta*: +/- " & TEXT(((D44*1.5)/1440),"h:mm") & "h | " & D44 & "km" )} -> - TRATOR: *1BM5080ETS6204305*_x000D_ - _x000D_ - *Cliente*: SILO DO MALOCA -NF61894 VOLTA -NF 45978_x000D_ - *Obs:* Conexão JD Estática + Jantar - São José da Boa Vista_x000D_ - *De*: MACPONTA AGRO DE ARAPOTI_x000D_ - *Para*: https://maps.app.goo.gl/TYsDXWU4kqkeGb8D6_x000D_ - *Ida e volta*: +/- 7:39h | 306km
A45: CONCLUIDO (D) | B45: PROPRIO VW | C45: =IFERROR((D45*1.5)/1440, "?") -> 0.31875 | D45: 306 | E45: =IFERROR((D45*6),"?") -> 1836 | G45: 1BM5080EVS4204226 | H45: 45978 | I45: 45978 | J45: SILO DO MALOCA -NF61894 VOLTA | K45: josiane.oliveira | L45: ARAPOTI | M45: CLIENTE | N45: DE LOJA PARA DEMONSTRAÇÃO | O45: MPA | P45: https://maps.app.goo.gl/TYsDXWU4kqkeGb8D6 | Q45: Conexão JD Estática + Jantar - São José da Boa Vista | R45: ARAPOTI | S45: TRATOR | T45: =IF( OR( IFERROR(FIND("BM",G45),0)>0, IFERROR(FIND("PY",G45),0)>0 ), MID(TRIM(SUBSTITUTE(SUBSTITUTE(G45,CHAR(160),""),CHAR(9),"")),4,5), MID(TRIM(SUBSTITUTE(SUBSTITUTE(G45,CHAR(160),""),CHAR(9),"")),4,4) ) -> 5080E | U45: {=_xlfn.LET( _xlpm.ch, TRIM(SUBSTITUTE(G45,CHAR(160),"")), _xlpm.ehTrator, OR(IFERROR(FIND("BM",_xlpm.ch),0)>0, IFERROR(FIND("PY",_xlpm.ch),0)>0), _xlpm.chave, IF(_xlpm.ehTrator, MID(_xlpm.ch,4,5), MID(_xlpm.ch,4,4)), _xlpm.fonte, IF(LEN(_xlpm.chave)=5, UTIL!BS:BS, UTIL!BR:BR), _xlpm.modelo, TRIM(SUBSTITUTE(T45,CHAR(160),"")), _xlpm.nomeMod, IFERROR(_xlfn.XLOOKUP("*"&_xlpm.modelo&"*", UTIL!D:D, UTIL!B:B, "", 2), IFERROR(_xlfn.XLOOKUP("*"&_xlpm.modelo&"*", UTIL!E:E, UTIL!B:B, "", 2), "")), _xlpm.tipoMod, IF(_xlpm.nomeMod="", "", IFERROR(LEFT(_xlpm.nomeMod, FIND(" ", _xlpm.nomeMod)-1), _xlpm.nomeMod)), _xlpm.dimMod, IFERROR(_xlfn.XLOOKUP("*"&_xlpm.modelo&"*", UTIL!D:D, UTIL!K:K, "", 2), IFERROR(_xlfn.XLOOKUP("*"&_xlpm.modelo&"*", UTIL!E:E, UTIL!K:K, "", 2), "")), _xlpm.tipotxt_antigo, IF(_xlpm.ehTrator, "TRATOR", IFERROR(_xlfn.XLOOKUP(_xlpm.chave, _xlpm.fonte, UTIL!BP:BP, "", 0), IFERROR(_xlfn.XLOOKUP("*"&_xlpm.chave&"*", _xlpm.fonte, UTIL!BP:BP, "", 2), "Não encontrado"))), _xlpm.dimtxt_antigo, IFERROR(_xlfn.XLOOKUP(_xlpm.chave, _xlpm.fonte, UTIL!BY:BY, "", 0), IFERROR(_xlfn.XLOOKUP("*"&_xlpm.chave&"*", _xlpm.fonte, UTIL!BY:BY, "", 2), "Não encontrado")), _xlpm.tipotxt, IF(_xlpm.tipoMod<>"", _xlpm.tipoMod, _xlpm.tipotxt_antigo), _xlpm.dimtxt, IF(_xlpm.dimMod<>"", _xlpm.dimMod, _xlpm.dimtxt_antigo), _xlpm.deTxt, IF(L45="CLIENTE", O45, IF(LEFT(L45,4)="http", L45, "MACPONTA AGRO DE "&L45)), _xlpm.paraBase, IF(M45="CLIENTE", P45, M45), _xlpm.paraTxt, IF(LEFT(_xlpm.paraBase,4)="http", _xlpm.paraBase, "MACPONTA AGRO DE "&_xlpm.paraBase), _xlpm.nfParte, IF(LEN(TRIM(I45))=0, "", " -NF "&TRIM(I45)), "- " & _xlpm.tipotxt & ": *" & G45 & "*" & CHAR(13)&CHAR(10) & "- " & _xlpm.dimtxt & CHAR(13)&CHAR(10) & "- *Cliente*: " & J45 & _xlpm.nfParte & CHAR(13)&CHAR(10) & "- *Obs:* " & Q45 & CHAR(13)&CHAR(10) & CHAR(10) & "- *De*: " & _xlpm.deTxt & CHAR(13)&CHAR(10) & "- *Para*: " & _xlpm.paraTxt & CHAR(13)&CHAR(10) & "- *Ida e volta*: +/- " & TEXT(((D45*1.5)/1440),"h:mm") & "h | " & D45 & "km" )} -> - TRATOR: *1BM5080EVS4204226*_x000D_ - _x000D_ - *Cliente*: SILO DO MALOCA -NF61894 VOLTA -NF 45978_x000D_ - *Obs:* Conexão JD Estática + Jantar - São José da Boa Vista_x000D_ - *De*: MACPONTA AGRO DE ARAPOTI_x000D_ - *Para*: https://maps.app.goo.gl/TYsDXWU4kqkeGb8D6_x000D_ - *Ida e volta*: +/- 7:39h | 306km
A46: CONCLUIDO (D) | B46: PROPRIO VW | C46: =IFERROR((D46*1.5)/1440, "?") -> 0.20833333 | D46: 200 | E46: =IFERROR((D46*6),"?") -> 1200 | G46: 1BM7230CVS3001962 | H46: 45979 | I46: 45979 | J46: FAZENDINHA -NF61895 | K46: josiane.oliveira | L46: CLIENTE | M46: CLIENTE | N46: DE CLIENTE PARA CLIENTE | P46: https://maps.app.goo.gl/HAQzMitpSPVxhKFi9 | R46: ARAPOTI | S46: TRATOR | T46: =IF( OR( IFERROR(FIND("BM",G46),0)>0, IFERROR(FIND("PY",G46),0)>0 ), MID(TRIM(SUBSTITUTE(SUBSTITUTE(G46,CHAR(160),""),CHAR(9),"")),4,5), MID(TRIM(SUBSTITUTE(SUBSTITUTE(G46,CHAR(160),""),CHAR(9),"")),4,4) ) -> 7230C | U46: {=_xlfn.LET( _xlpm.ch, TRIM(SUBSTITUTE(G46,CHAR(160),"")), _xlpm.ehTrator, OR(IFERROR(FIND("BM",_xlpm.ch),0)>0, IFERROR(FIND("PY",_xlpm.ch),0)>0), _xlpm.chave, IF(_xlpm.ehTrator, MID(_xlpm.ch,4,5), MID(_xlpm.ch,4,4)), _xlpm.fonte, IF(LEN(_xlpm.chave)=5, UTIL!BS:BS, UTIL!BR:BR), _xlpm.modelo, TRIM(SUBSTITUTE(T46,CHAR(160),"")), _xlpm.nomeMod, IFERROR(_xlfn.XLOOKUP("*"&_xlpm.modelo&"*", UTIL!D:D, UTIL!B:B, "", 2), IFERROR(_xlfn.XLOOKUP("*"&_xlpm.modelo&"*", UTIL!E:E, UTIL!B:B, "", 2), "")), _xlpm.tipoMod, IF(_xlpm.nomeMod="", "", IFERROR(LEFT(_xlpm.nomeMod, FIND(" ", _xlpm.nomeMod)-1), _xlpm.nomeMod)), _xlpm.dimMod, IFERROR(_xlfn.XLOOKUP("*"&_xlpm.modelo&"*", UTIL!D:D, UTIL!K:K, "", 2), IFERROR(_xlfn.XLOOKUP("*"&_xlpm.modelo&"*", UTIL!E:E, UTIL!K:K, "", 2), "")), _xlpm.tipotxt_antigo, IF(_xlpm.ehTrator, "TRATOR", IFERROR(_xlfn.XLOOKUP(_xlpm.chave, _xlpm.fonte, UTIL!BP:BP, "", 0), IFERROR(_xlfn.XLOOKUP("*"&_xlpm.chave&"*", _xlpm.fonte, UTIL!BP:BP, "", 2), "Não encontrado"))), _xlpm.dimtxt_antigo, IFERROR(_xlfn.XLOOKUP(_xlpm.chave, _xlpm.fonte, UTIL!BY:BY, "", 0), IFERROR(_xlfn.XLOOKUP("*"&_xlpm.chave&"*", _xlpm.fonte, UTIL!BY:BY, "", 2), "Não encontrado")), _xlpm.tipotxt, IF(_xlpm.tipoMod<>"", _xlpm.tipoMod, _xlpm.tipotxt_antigo), _xlpm.dimtxt, IF(_xlpm.dimMod<>"", _xlpm.dimMod, _xlpm.dimtxt_antigo), _xlpm.deTxt, IF(L46="CLIENTE", O46, IF(LEFT(L46,4)="http", L46, "MACPONTA AGRO DE "&L46)), _xlpm.paraBase, IF(M46="CLIENTE", P46, M46), _xlpm.paraTxt, IF(LEFT(_xlpm.paraBase,4)="http", _xlpm.paraBase, "MACPONTA AGRO DE "&_xlpm.paraBase), _xlpm.nfParte, IF(LEN(TRIM(I46))=0, "", " -NF "&TRIM(I46)), "- " & _xlpm.tipotxt & ": *" & G46 & "*" & CHAR(13)&CHAR(10) & "- " & _xlpm.dimtxt & CHAR(13)&CHAR(10) & "- *Cliente*: " & J46 & _xlpm.nfParte & CHAR(13)&CHAR(10) & "- *Obs:* " & Q46 & CHAR(13)&CHAR(10) & CHAR(10) & "- *De*: " & _xlpm.deTxt & CHAR(13)&CHAR(10) & "- *Para*: " & _xlpm.paraTxt & CHAR(13)&CHAR(10) & "- *Ida e volta*: +/- " & TEXT(((D46*1.5)/1440),"h:mm") & "h | " & D46 & "km" )} -> - TRATOR: *1BM7230CVS3001962*_x000D_ - _x000D_ - *Cliente*: FAZENDINHA -NF61895 -NF 45979_x000D_ - *Obs:* _x000D_ - *De*: _x000D_ - *Para*: https://maps.app.goo.gl/HAQzMitpSPVxhKFi9_x000D_ - *Ida e volta*: +/- 5:00h | 200km
A47: CONCLUIDO | B47: TERCEIRO COLOMBO | C47: =IFERROR((D47*1.5)/1440, "?") -> 0.76354167 | D47: 733 | F47: 9600 | G47: 1NW4030MES0250870 | H47: 45979 | I47: 45979 | J47: VIKTOR LEH -NF107863 - AET ESP+ESCOLTA | K47: euclides.junior | L47: GUARAPUAVA | M47: CLIENTE | N47: DE LOJA PARA CLIENTE | O47: MPA | P47: https://maps.app.goo.gl/CR8ypB1Pd9ZCuWzE6 | Q47: Viktor | R47: GUARAPUAVA | S47: PULVERIZADOR | T47: =IF( OR( IFERROR(FIND("BM",G47),0)>0, IFERROR(FIND("PY",G47),0)>0 ), MID(TRIM(SUBSTITUTE(SUBSTITUTE(G47,CHAR(160),""),CHAR(9),"")),4,5), MID(TRIM(SUBSTITUTE(SUBSTITUTE(G47,CHAR(160),""),CHAR(9),"")),4,4) ) -> 4030 | U47: {=_xlfn.LET( _xlpm.ch, TRIM(SUBSTITUTE(G47,CHAR(160),"")), _xlpm.ehTrator, OR(IFERROR(FIND("BM",_xlpm.ch),0)>0, IFERROR(FIND("PY",_xlpm.ch),0)>0), _xlpm.chave, IF(_xlpm.ehTrator, MID(_xlpm.ch,4,5), MID(_xlpm.ch,4,4)), _xlpm.fonte, IF(LEN(_xlpm.chave)=5, UTIL!BS:BS, UTIL!BR:BR), _xlpm.modelo, TRIM(SUBSTITUTE(T47,CHAR(160),"")), _xlpm.nomeMod, IFERROR(_xlfn.XLOOKUP("*"&_xlpm.modelo&"*", UTIL!D:D, UTIL!B:B, "", 2), IFERROR(_xlfn.XLOOKUP("*"&_xlpm.modelo&"*", UTIL!E:E, UTIL!B:B, "", 2), "")), _xlpm.tipoMod, IF(_xlpm.nomeMod="", "", IFERROR(LEFT(_xlpm.nomeMod, FIND(" ", _xlpm.nomeMod)-1), _xlpm.nomeMod)), _xlpm.dimMod, IFERROR(_xlfn.XLOOKUP("*"&_xlpm.modelo&"*", UTIL!D:D, UTIL!K:K, "", 2), IFERROR(_xlfn.XLOOKUP("*"&_xlpm.modelo&"*", UTIL!E:E, UTIL!K:K, "", 2), "")), _xlpm.tipotxt_antigo, IF(_xlpm.ehTrator, "TRATOR", IFERROR(_xlfn.XLOOKUP(_xlpm.chave, _xlpm.fonte, UTIL!BP:BP, "", 0), IFERROR(_xlfn.XLOOKUP("*"&_xlpm.chave&"*", _xlpm.fonte, UTIL!BP:BP, "", 2), "Não encontrado"))), _xlpm.dimtxt_antigo, IFERROR(_xlfn.XLOOKUP(_xlpm.chave, _xlpm.fonte, UTIL!BY:BY, "", 0), IFERROR(_xlfn.XLOOKUP("*"&_xlpm.chave&"*", _xlpm.fonte, UTIL!BY:BY, "", 2), "Não encontrado")), _xlpm.tipotxt, IF(_xlpm.tipoMod<>"", _xlpm.tipoMod, _xlpm.tipotxt_antigo), _xlpm.dimtxt, IF(_xlpm.dimMod<>"", _xlpm.dimMod, _xlpm.dimtxt_antigo), _xlpm.deTxt, IF(L47="CLIENTE", O47, IF(LEFT(L47,4)="http", L47, "MACPONTA AGRO DE "&L47)), _xlpm.paraBase, IF(M47="CLIENTE", P47, M47), _xlpm.paraTxt, IF(LEFT(_xlpm.paraBase,4)="http", _xlpm.paraBase, "MACPONTA AGRO DE "&_xlpm.paraBase), _xlpm.nfParte, IF(LEN(TRIM(I47))=0, "", " -NF "&TRIM(I47)), "- " & _xlpm.tipotxt & ": *" & G47 & "*" & CHAR(13)&CHAR(10) & "- " & _xlpm.dimtxt & CHAR(13)&CHAR(10) & "- *Cliente*: " & J47 & _xlpm.nfParte & CHAR(13)&CHAR(10) & "- *Obs:* " & Q47 & CHAR(13)&CHAR(10) & CHAR(10) & "- *De*: " & _xlpm.deTxt & CHAR(13)&CHAR(10) & "- *Para*: " & _xlpm.paraTxt & CHAR(13)&CHAR(10) & "- *Ida e volta*: +/- " & TEXT(((D47*1.5)/1440),"h:mm") & "h | " & D47 & "km" )} -> - PULVERIZADOR: *1NW4030MES0250870*_x000D_ - A:3,35 x C:7,50 x L:3,12-3,94 x P:10.000kg_x000D_ - *Cliente*: VIKTOR LEH -NF107863 - AET ESP+ESCOLTA -NF 45979_x000D_ - *Obs:* Viktor _x000D_ - *De*: MACPONTA AGRO DE GUARAPUAVA_x000D_ - *Para*: https://maps.app.goo.gl/CR8ypB1Pd9ZCuWzE6_x000D_ - *Ida e volta*: +/- 18:19h | 733km
A48: CONCLUIDO (D) | B48: TERCEIRO AGROMAQ | C48: =IFERROR((D48*1.5)/1440, "?") -> 0.19479167 | D48: 187 | F48: 2000 | G48: 1CQ1213AHS0155196 | H48: 45979 | I48: 45979 | J48: FAZENDINHA -NF61895 | K48: josiane.oliveira | L48: ARAPOTI | M48: CLIENTE | N48: DE CLIENTE PARA LOJA | O48: MPA | P48: https://maps.app.goo.gl/HAQzMitpSPVxhKFi9 | R48: ARAPOTI | S48: PLANTADEIRA | T48: =IF( OR( IFERROR(FIND("BM",G48),0)>0, IFERROR(FIND("PY",G48),0)>0 ), MID(TRIM(SUBSTITUTE(SUBSTITUTE(G48,CHAR(160),""),CHAR(9),"")),4,5), MID(TRIM(SUBSTITUTE(SUBSTITUTE(G48,CHAR(160),""),CHAR(9),"")),4,4) ) -> 1213 | U48: {=_xlfn.LET( _xlpm.ch, TRIM(SUBSTITUTE(G48,CHAR(160),"")), _xlpm.ehTrator, OR(IFERROR(FIND("BM",_xlpm.ch),0)>0, IFERROR(FIND("PY",_xlpm.ch),0)>0), _xlpm.chave, IF(_xlpm.ehTrator, MID(_xlpm.ch,4,5), MID(_xlpm.ch,4,4)), _xlpm.fonte, IF(LEN(_xlpm.chave)=5, UTIL!BS:BS, UTIL!BR:BR), _xlpm.modelo, TRIM(SUBSTITUTE(T48,CHAR(160),"")), _xlpm.nomeMod, IFERROR(_xlfn.XLOOKUP("*"&_xlpm.modelo&"*", UTIL!D:D, UTIL!B:B, "", 2), IFERROR(_xlfn.XLOOKUP("*"&_xlpm.modelo&"*", UTIL!E:E, UTIL!B:B, "", 2), "")), _xlpm.tipoMod, IF(_xlpm.nomeMod="", "", IFERROR(LEFT(_xlpm.nomeMod, FIND(" ", _xlpm.nomeMod)-1), _xlpm.nomeMod)), _xlpm.dimMod, IFERROR(_xlfn.XLOOKUP("*"&_xlpm.modelo&"*", UTIL!D:D, UTIL!K:K, "", 2), IFERROR(_xlfn.XLOOKUP("*"&_xlpm.modelo&"*", UTIL!E:E, UTIL!K:K, "", 2), "")), _xlpm.tipotxt_antigo, IF(_xlpm.ehTrator, "TRATOR", IFERROR(_xlfn.XLOOKUP(_xlpm.chave, _xlpm.fonte, UTIL!BP:BP, "", 0), IFERROR(_xlfn.XLOOKUP("*"&_xlpm.chave&"*", _xlpm.fonte, UTIL!BP:BP, "", 2), "Não encontrado"))), _xlpm.dimtxt_antigo, IFERROR(_xlfn.XLOOKUP(_xlpm.chave, _xlpm.fonte, UTIL!BY:BY, "", 0), IFERROR(_xlfn.XLOOKUP("*"&_xlpm.chave&"*", _xlpm.fonte, UTIL!BY:BY, "", 2), "Não encontrado")), _xlpm.tipotxt, IF(_xlpm.tipoMod<>"", _xlpm.tipoMod, _xlpm.tipotxt_antigo), _xlpm.dimtxt, IF(_xlpm.dimMod<>"", _xlpm.dimMod, _xlpm.dimtxt_antigo), _xlpm.deTxt, IF(L48="CLIENTE", O48, IF(LEFT(L48,4)="http", L48, "MACPONTA AGRO DE "&L48)), _xlpm.paraBase, IF(M48="CLIENTE", P48, M48), _xlpm.paraTxt, IF(LEFT(_xlpm.paraBase,4)="http", _xlpm.paraBase, "MACPONTA AGRO DE "&_xlpm.paraBase), _xlpm.nfParte, IF(LEN(TRIM(I48))=0, "", " -NF "&TRIM(I48)), "- " & _xlpm.tipotxt & ": *" & G48 & "*" & CHAR(13)&CHAR(10) & "- " & _xlpm.dimtxt & CHAR(13)&CHAR(10) & "- *Cliente*: " & J48 & _xlpm.nfParte & CHAR(13)&CHAR(10) & "- *Obs:* " & Q48 & CHAR(13)&CHAR(10) & CHAR(10) & "- *De*: " & _xlpm.deTxt & CHAR(13)&CHAR(10) & "- *Para*: " & _xlpm.paraTxt & CHAR(13)&CHAR(10) & "- *Ida e volta*: +/- " & TEXT(((D48*1.5)/1440),"h:mm") & "h | " & D48 & "km" )} -> - PLANTADEIRA: *1CQ1213AHS0155196*_x000D_ - A:2,45 x C:7,00 x L:3,20-3,20 x P:6.025kg_x000D_ - *Cliente*: FAZENDINHA -NF61895 -NF 45979_x000D_ - *Obs:* _x000D_ - *De*: MACPONTA AGRO DE ARAPOTI_x000D_ - *Para*: https://maps.app.goo.gl/HAQzMitpSPVxhKFi9_x000D_ - *Ida e volta*: +/- 4:40h | 187km
A49: PROGRAMADO (D) | B49: TERCEIRO AGROMAQ | C49: =IFERROR((D49*1.5)/1440, "?") -> 0.49791667 | D49: 478 | F49: 300 | G49: 1CQFA25APS0160156 | H49: 45979 | J49: SILO DO MALOCA -NF61894 VOLTA | K49: josiane.oliveira | L49: IRATI | M49: CLIENTE | N49: DE LOJA PARA DEMONSTRAÇÃO | O49: MPA | P49: https://maps.app.goo.gl/TYsDXWU4kqkeGb8D6 | Q49: Conexão JD Estática + Jantar - São José da Boa Vista | R49: ARAPOTI | S49: PLATAFORMA | T49: =IF( OR( IFERROR(FIND("BM",G49),0)>0, IFERROR(FIND("PY",G49),0)>0 ), MID(TRIM(SUBSTITUTE(SUBSTITUTE(G49,CHAR(160),""),CHAR(9),"")),4,5), MID(TRIM(SUBSTITUTE(SUBSTITUTE(G49,CHAR(160),""),CHAR(9),"")),4,4) ) -> FA25 | U49: {=_xlfn.LET( _xlpm.ch, TRIM(SUBSTITUTE(G49,CHAR(160),"")), _xlpm.ehTrator, OR(IFERROR(FIND("BM",_xlpm.ch),0)>0, IFERROR(FIND("PY",_xlpm.ch),0)>0), _xlpm.chave, IF(_xlpm.ehTrator, MID(_xlpm.ch,4,5), MID(_xlpm.ch,4,4)), _xlpm.fonte, IF(LEN(_xlpm.chave)=5, UTIL!BS:BS, UTIL!BR:BR), _xlpm.modelo, TRIM(SUBSTITUTE(T49,CHAR(160),"")), _xlpm.nomeMod, IFERROR(_xlfn.XLOOKUP("*"&_xlpm.modelo&"*", UTIL!D:D, UTIL!B:B, "", 2), IFERROR(_xlfn.XLOOKUP("*"&_xlpm.modelo&"*", UTIL!E:E, UTIL!B:B, "", 2), "")), _xlpm.tipoMod, IF(_xlpm.nomeMod="", "", IFERROR(LEFT(_xlpm.nomeMod, FIND(" ", _xlpm.nomeMod)-1), _xlpm.nomeMod)), _xlpm.dimMod, IFERROR(_xlfn.XLOOKUP("*"&_xlpm.modelo&"*", UTIL!D:D, UTIL!K:K, "", 2), IFERROR(_xlfn.XLOOKUP("*"&_xlpm.modelo&"*", UTIL!E:E, UTIL!K:K, "", 2), "")), _xlpm.tipotxt_antigo, IF(_xlpm.ehTrator, "TRATOR", IFERROR(_xlfn.XLOOKUP(_xlpm.chave, _xlpm.fonte, UTIL!BP:BP, "", 0), IFERROR(_xlfn.XLOOKUP("*"&_xlpm.chave&"*", _xlpm.fonte, UTIL!BP:BP, "", 2), "Não encontrado"))), _xlpm.dimtxt_antigo, IFERROR(_xlfn.XLOOKUP(_xlpm.chave, _xlpm.fonte, UTIL!BY:BY, "", 0), IFERROR(_xlfn.XLOOKUP("*"&_xlpm.chave&"*", _xlpm.fonte, UTIL!BY:BY, "", 2), "Não encontrado")), _xlpm.tipotxt, IF(_xlpm.tipoMod<>"", _xlpm.tipoMod, _xlpm.tipotxt_antigo), _xlpm.dimtxt, IF(_xlpm.dimMod<>"", _xlpm.dimMod, _xlpm.dimtxt_antigo), _xlpm.deTxt, IF(L49="CLIENTE", O49, IF(LEFT(L49,4)="http", L49, "MACPONTA AGRO DE "&L49)), _xlpm.paraBase, IF(M49="CLIENTE", P49, M49), _xlpm.paraTxt, IF(LEFT(_xlpm.paraBase,4)="http", _xlpm.paraBase, "MACPONTA AGRO DE "&_xlpm.paraBase), _xlpm.nfParte, IF(LEN(TRIM(I49))=0, "", " -NF "&TRIM(I49)), "- " & _xlpm.tipotxt & ": *" & G49 & "*" & CHAR(13)&CHAR(10) & "- " & _xlpm.dimtxt & CHAR(13)&CHAR(10) & "- *Cliente*: " & J49 & _xlpm.nfParte & CHAR(13)&CHAR(10) & "- *Obs:* " & Q49 & CHAR(13)&CHAR(10) & CHAR(10) & "- *De*: " & _xlpm.deTxt & CHAR(13)&CHAR(10) & "- *Para*: " & _xlpm.paraTxt & CHAR(13)&CHAR(10) & "- *Ida e volta*: +/- " & TEXT(((D49*1.5)/1440),"h:mm") & "h | " & D49 & "km" )} -> - PLATAFORMA: *1CQFA25APS0160156*_x000D_ - A:1,60 x C:7,60 x L:1,80-1,80 x P:2.100kg_x000D_ - *Cliente*: SILO DO MALOCA -NF61894 VOLTA_x000D_ - *Obs:* Conexão JD Estática + Jantar - São José da Boa Vista_x000D_ - *De*: MACPONTA AGRO DE IRATI_x000D_ - *Para*: https://maps.app.goo.gl/TYsDXWU4kqkeGb8D6_x000D_ - *Ida e volta*: +/- 11:57h | 478km
A50: PROGRAMADO (D) | B50: TERCEIRO AGROMAQ | C50: =IFERROR((D50*1.5)/1440, "?") -> 0.49791667 | D50: 478 | F50: 900 | G50: 1CQS440ACS0155147 | H50: 45979 | J50: SILO DO MALOCA -NF61894 VOLTA | K50: josiane.oliveira | L50: IRATI | M50: CLIENTE | N50: DE LOJA PARA DEMONSTRAÇÃO | O50: MPA | P50: https://maps.app.goo.gl/TYsDXWU4kqkeGb8D6 | Q50: Conexão JD Estática + Jantar - São José da Boa Vista | R50: ARAPOTI | S50: COLHEITADEIRA | T50: =IF( OR( IFERROR(FIND("BM",G50),0)>0, IFERROR(FIND("PY",G50),0)>0 ), MID(TRIM(SUBSTITUTE(SUBSTITUTE(G50,CHAR(160),""),CHAR(9),"")),4,5), MID(TRIM(SUBSTITUTE(SUBSTITUTE(G50,CHAR(160),""),CHAR(9),"")),4,4) ) -> S440 | U50: {=_xlfn.LET( _xlpm.ch, TRIM(SUBSTITUTE(G50,CHAR(160),"")), _xlpm.ehTrator, OR(IFERROR(FIND("BM",_xlpm.ch),0)>0, IFERROR(FIND("PY",_xlpm.ch),0)>0), _xlpm.chave, IF(_xlpm.ehTrator, MID(_xlpm.ch,4,5), MID(_xlpm.ch,4,4)), _xlpm.fonte, IF(LEN(_xlpm.chave)=5, UTIL!BS:BS, UTIL!BR:BR), _xlpm.modelo, TRIM(SUBSTITUTE(T50,CHAR(160),"")), _xlpm.nomeMod, IFERROR(_xlfn.XLOOKUP("*"&_xlpm.modelo&"*", UTIL!D:D, UTIL!B:B, "", 2), IFERROR(_xlfn.XLOOKUP("*"&_xlpm.modelo&"*", UTIL!E:E, UTIL!B:B, "", 2), "")), _xlpm.tipoMod, IF(_xlpm.nomeMod="", "", IFERROR(LEFT(_xlpm.nomeMod, FIND(" ", _xlpm.nomeMod)-1), _xlpm.nomeMod)), _xlpm.dimMod, IFERROR(_xlfn.XLOOKUP("*"&_xlpm.modelo&"*", UTIL!D:D, UTIL!K:K, "", 2), IFERROR(_xlfn.XLOOKUP("*"&_xlpm.modelo&"*", UTIL!E:E, UTIL!K:K, "", 2), "")), _xlpm.tipotxt_antigo, IF(_xlpm.ehTrator, "TRATOR", IFERROR(_xlfn.XLOOKUP(_xlpm.chave, _xlpm.fonte, UTIL!BP:BP, "", 0), IFERROR(_xlfn.XLOOKUP("*"&_xlpm.chave&"*", _xlpm.fonte, UTIL!BP:BP, "", 2), "Não encontrado"))), _xlpm.dimtxt_antigo, IFERROR(_xlfn.XLOOKUP(_xlpm.chave, _xlpm.fonte, UTIL!BY:BY, "", 0), IFERROR(_xlfn.XLOOKUP("*"&_xlpm.chave&"*", _xlpm.fonte, UTIL!BY:BY, "", 2), "Não encontrado")), _xlpm.tipotxt, IF(_xlpm.tipoMod<>"", _xlpm.tipoMod, _xlpm.tipotxt_antigo), _xlpm.dimtxt, IF(_xlpm.dimMod<>"", _xlpm.dimMod, _xlpm.dimtxt_antigo), _xlpm.deTxt, IF(L50="CLIENTE", O50, IF(LEFT(L50,4)="http", L50, "MACPONTA AGRO DE "&L50)), _xlpm.paraBase, IF(M50="CLIENTE", P50, M50), _xlpm.paraTxt, IF(LEFT(_xlpm.paraBase,4)="http", _xlpm.paraBase, "MACPONTA AGRO DE "&_xlpm.paraBase), _xlpm.nfParte, IF(LEN(TRIM(I50))=0, "", " -NF "&TRIM(I50)), "- " & _xlpm.tipotxt & ": *" & G50 & "*" & CHAR(13)&CHAR(10) & "- " & _xlpm.dimtxt & CHAR(13)&CHAR(10) & "- *Cliente*: " & J50 & _xlpm.nfParte & CHAR(13)&CHAR(10) & "- *Obs:* " & Q50 & CHAR(13)&CHAR(10) & CHAR(10) & "- *De*: " & _xlpm.deTxt & CHAR(13)&CHAR(10) & "- *Para*: " & _xlpm.paraTxt & CHAR(13)&CHAR(10) & "- *Ida e volta*: +/- " & TEXT(((D50*1.5)/1440),"h:mm") & "h | " & D50 & "km" )} -> - COLHEITADEIRA: *1CQS440ACS0155147*_x000D_ - A:4,10 x C:7,70 x L:3,40-4,10 x P:11.800kg_x000D_ - *Cliente*: SILO DO MALOCA -NF61894 VOLTA_x000D_ - *Obs:* Conexão JD Estática + Jantar - São José da Boa Vista_x000D_ - *De*: MACPONTA AGRO DE IRATI_x000D_ - *Para*: https://maps.app.goo.gl/TYsDXWU4kqkeGb8D6_x000D_ - *Ida e volta*: +/- 11:57h | 478km
A51: PROGRAMADO | B51: TERCEIRO AGROMAQ | C51: =IFERROR((D51*1.5)/1440, "?") -> 0.022916667 | D51: 22 | F51: 400 | G51: 1CQRD30AVS0160116 | H51: 45980 | J51: JAN NOORDEGRAAF NETO -NF61591 | K51: josiane.oliveira | L51: ARAPOTI | M51: CLIENTE | N51: DE LOJA PARA CLIENTE | O51: MPA | P51: https://maps.app.goo.gl/w2FYcAi8ZYYfJ88Y8 | Q51: JAN NOORDEGRAAF NETO 042999791942 - CEN PAULO HOPATA | R51: ARAPOTI | S51: PLATAFORMA | T51: =IF( OR( IFERROR(FIND("BM",G51),0)>0, IFERROR(FIND("PY",G51),0)>0 ), MID(TRIM(SUBSTITUTE(SUBSTITUTE(G51,CHAR(160),""),CHAR(9),"")),4,5), MID(TRIM(SUBSTITUTE(SUBSTITUTE(G51,CHAR(160),""),CHAR(9),"")),4,4) ) -> RD30 | U51: {=_xlfn.LET( _xlpm.ch, TRIM(SUBSTITUTE(G51,CHAR(160),"")), _xlpm.ehTrator, OR(IFERROR(FIND("BM",_xlpm.ch),0)>0, IFERROR(FIND("PY",_xlpm.ch),0)>0), _xlpm.chave, IF(_xlpm.ehTrator, MID(_xlpm.ch,4,5), MID(_xlpm.ch,4,4)), _xlpm.fonte, IF(LEN(_xlpm.chave)=5, UTIL!BS:BS, UTIL!BR:BR), _xlpm.modelo, TRIM(SUBSTITUTE(T51,CHAR(160),"")), _xlpm.nomeMod, IFERROR(_xlfn.XLOOKUP("*"&_xlpm.modelo&"*", UTIL!D:D, UTIL!B:B, "", 2), IFERROR(_xlfn.XLOOKUP("*"&_xlpm.modelo&"*", UTIL!E:E, UTIL!B:B, "", 2), "")), _xlpm.tipoMod, IF(_xlpm.nomeMod="", "", IFERROR(LEFT(_xlpm.nomeMod, FIND(" ", _xlpm.nomeMod)-1), _xlpm.nomeMod)), _xlpm.dimMod, IFERROR(_xlfn.XLOOKUP("*"&_xlpm.modelo&"*", UTIL!D:D, UTIL!K:K, "", 2), IFERROR(_xlfn.XLOOKUP("*"&_xlpm.modelo&"*", UTIL!E:E, UTIL!K:K, "", 2), "")), _xlpm.tipotxt_antigo, IF(_xlpm.ehTrator, "TRATOR", IFERROR(_xlfn.XLOOKUP(_xlpm.chave, _xlpm.fonte, UTIL!BP:BP, "", 0), IFERROR(_xlfn.XLOOKUP("*"&_xlpm.chave&"*", _xlpm.fonte, UTIL!BP:BP, "", 2), "Não encontrado"))), _xlpm.dimtxt_antigo, IFERROR(_xlfn.XLOOKUP(_xlpm.chave, _xlpm.fonte, UTIL!BY:BY, "", 0), IFERROR(_xlfn.XLOOKUP("*"&_xlpm.chave&"*", _xlpm.fonte, UTIL!BY:BY, "", 2), "Não encontrado")), _xlpm.tipotxt, IF(_xlpm.tipoMod<>"", _xlpm.tipoMod, _xlpm.tipotxt_antigo), _xlpm.dimtxt, IF(_xlpm.dimMod<>"", _xlpm.dimMod, _xlpm.dimtxt_antigo), _xlpm.deTxt, IF(L51="CLIENTE", O51, IF(LEFT(L51,4)="http", L51, "MACPONTA AGRO DE "&L51)), _xlpm.paraBase, IF(M51="CLIENTE", P51, M51), _xlpm.paraTxt, IF(LEFT(_xlpm.paraBase,4)="http", _xlpm.paraBase, "MACPONTA AGRO DE "&_xlpm.paraBase), _xlpm.nfParte, IF(LEN(TRIM(I51))=0, "", " -NF "&TRIM(I51)), "- " & _xlpm.tipotxt & ": *" & G51 & "*" & CHAR(13)&CHAR(10) & "- " & _xlpm.dimtxt & CHAR(13)&CHAR(10) & "- *Cliente*: " & J51 & _xlpm.nfParte & CHAR(13)&CHAR(10) & "- *Obs:* " & Q51 & CHAR(13)&CHAR(10) & CHAR(10) & "- *De*: " & _xlpm.deTxt & CHAR(13)&CHAR(10) & "- *Para*: " & _xlpm.paraTxt & CHAR(13)&CHAR(10) & "- *Ida e volta*: +/- " & TEXT(((D51*1.5)/1440),"h:mm") & "h | " & D51 & "km" )} -> - PLATAFORMA: *1CQRD30AVS0160116*_x000D_ - A:1,60 x C:9,14 x L:2,20-2,20 x P:4.200kg_x000D_ - *Cliente*: JAN NOORDEGRAAF NETO -NF61591_x000D_ - *Obs:* JAN NOORDEGRAAF NETO 042999791942 - CEN PAULO HOPATA_x000D_ - *De*: MACPONTA AGRO DE ARAPOTI_x000D_ - *Para*: https://maps.app.goo.gl/w2FYcAi8ZYYfJ88Y8_x000D_ - *Ida e volta*: +/- 0:33h | 22km
A52: PROGRAMADO | B52: TERCEIRO AGROMAQ | C52: =IFERROR((D52*1.5)/1440, "?") -> 0.022916667 | D52: 22 | F52: 800 | G52: 1CQS550AAS0160130 | H52: 45980 | J52: JAN NOORDEGRAAF NETO -NF61591 | K52: josiane.oliveira | L52: ARAPOTI | M52: CLIENTE | N52: DE LOJA PARA CLIENTE | O52: MPA | P52: https://maps.app.goo.gl/w2FYcAi8ZYYfJ88Y8 | Q52: JAN NOORDEGRAAF NETO 042999791942 - CEN PAULO HOPATA | R52: ARAPOTI | S52: COLHEITADEIRA | T52: =IF( OR( IFERROR(FIND("BM",G52),0)>0, IFERROR(FIND("PY",G52),0)>0 ), MID(TRIM(SUBSTITUTE(SUBSTITUTE(G52,CHAR(160),""),CHAR(9),"")),4,5), MID(TRIM(SUBSTITUTE(SUBSTITUTE(G52,CHAR(160),""),CHAR(9),"")),4,4) ) -> S550 | U52: {=_xlfn.LET( _xlpm.ch, TRIM(SUBSTITUTE(G52,CHAR(160),"")), _xlpm.ehTrator, OR(IFERROR(FIND("BM",_xlpm.ch),0)>0, IFERROR(FIND("PY",_xlpm.ch),0)>0), _xlpm.chave, IF(_xlpm.ehTrator, MID(_xlpm.ch,4,5), MID(_xlpm.ch,4,4)), _xlpm.fonte, IF(LEN(_xlpm.chave)=5, UTIL!BS:BS, UTIL!BR:BR), _xlpm.modelo, TRIM(SUBSTITUTE(T52,CHAR(160),"")), _xlpm.nomeMod, IFERROR(_xlfn.XLOOKUP("*"&_xlpm.modelo&"*", UTIL!D:D, UTIL!B:B, "", 2), IFERROR(_xlfn.XLOOKUP("*"&_xlpm.modelo&"*", UTIL!E:E, UTIL!B:B, "", 2), "")), _xlpm.tipoMod, IF(_xlpm.nomeMod="", "", IFERROR(LEFT(_xlpm.nomeMod, FIND(" ", _xlpm.nomeMod)-1), _xlpm.nomeMod)), _xlpm.dimMod, IFERROR(_xlfn.XLOOKUP("*"&_xlpm.modelo&"*", UTIL!D:D, UTIL!K:K, "", 2), IFERROR(_xlfn.XLOOKUP("*"&_xlpm.modelo&"*", UTIL!E:E, UTIL!K:K, "", 2), "")), _xlpm.tipotxt_antigo, IF(_xlpm.ehTrator, "TRATOR", IFERROR(_xlfn.XLOOKUP(_xlpm.chave, _xlpm.fonte, UTIL!BP:BP, "", 0), IFERROR(_xlfn.XLOOKUP("*"&_xlpm.chave&"*", _xlpm.fonte, UTIL!BP:BP, "", 2), "Não encontrado"))), _xlpm.dimtxt_antigo, IFERROR(_xlfn.XLOOKUP(_xlpm.chave, _xlpm.fonte, UTIL!BY:BY, "", 0), IFERROR(_xlfn.XLOOKUP("*"&_xlpm.chave&"*", _xlpm.fonte, UTIL!BY:BY, "", 2), "Não encontrado")), _xlpm.tipotxt, IF(_xlpm.tipoMod<>"", _xlpm.tipoMod, _xlpm.tipotxt_antigo), _xlpm.dimtxt, IF(_xlpm.dimMod<>"", _xlpm.dimMod, _xlpm.dimtxt_antigo), _xlpm.deTxt, IF(L52="CLIENTE", O52, IF(LEFT(L52,4)="http", L52, "MACPONTA AGRO DE "&L52)), _xlpm.paraBase, IF(M52="CLIENTE", P52, M52), _xlpm.paraTxt, IF(LEFT(_xlpm.paraBase,4)="http", _xlpm.paraBase, "MACPONTA AGRO DE "&_xlpm.paraBase), _xlpm.nfParte, IF(LEN(TRIM(I52))=0, "", " -NF "&TRIM(I52)), "- " & _xlpm.tipotxt & ": *" & G52 & "*" & CHAR(13)&CHAR(10) & "- " & _xlpm.dimtxt & CHAR(13)&CHAR(10) & "- *Cliente*: " & J52 & _xlpm.nfParte & CHAR(13)&CHAR(10) & "- *Obs:* " & Q52 & CHAR(13)&CHAR(10) & CHAR(10) & "- *De*: " & _xlpm.deTxt & CHAR(13)&CHAR(10) & "- *Para*: " & _xlpm.paraTxt & CHAR(13)&CHAR(10) & "- *Ida e volta*: +/- " & TEXT(((D52*1.5)/1440),"h:mm") & "h | " & D52 & "km" )} -> - COLHEITADEIRA: *1CQS550AAS0160130*_x000D_ - A:3,80 x C:10,00 x L:3,70-4,20 x P:15.938kg_x000D_ - *Cliente*: JAN NOORDEGRAAF NETO -NF61591_x000D_ - *Obs:* JAN NOORDEGRAAF NETO 042999791942 - CEN PAULO HOPATA_x000D_ - *De*: MACPONTA AGRO DE ARAPOTI_x000D_ - *Para*: https://maps.app.goo.gl/w2FYcAi8ZYYfJ88Y8_x000D_ - *Ida e volta*: +/- 0:33h | 22km
A53: PROGRAMADO | B53: TERCEIRO AGROMAQ | C53: =IFERROR((D53*1.5)/1440, "?") -> 0.022916667 | D53: 22 | F53: 300 | G53: CTP28811021 | H53: 45980 | J53: NOTA DO CLIENTE | K53: josiane.oliveira | L53: CLIENTE | M53: ARAPOTI | N53: DE CLIENTE PARA LOJA | O53: https://maps.app.goo.gl/w2FYcAi8ZYYfJ88Y8 | P53: MPA | Q53: JAN NOORDEGRAAF NETO 43999791942 - CEN PAULO HOPATA | R53: ARAPOTI | S53: CARRETA | T53: =IF( OR( IFERROR(FIND("BM",G53),0)>0, IFERROR(FIND("PY",G53),0)>0 ), MID(TRIM(SUBSTITUTE(SUBSTITUTE(G53,CHAR(160),""),CHAR(9),"")),4,5), MID(TRIM(SUBSTITUTE(SUBSTITUTE(G53,CHAR(160),""),CHAR(9),"")),4,4) ) -> 2881 | U53: {=_xlfn.LET( _xlpm.ch, TRIM(SUBSTITUTE(G53,CHAR(160),"")), _xlpm.ehTrator, OR(IFERROR(FIND("BM",_xlpm.ch),0)>0, IFERROR(FIND("PY",_xlpm.ch),0)>0), _xlpm.chave, IF(_xlpm.ehTrator, MID(_xlpm.ch,4,5), MID(_xlpm.ch,4,4)), _xlpm.fonte, IF(LEN(_xlpm.chave)=5, UTIL!BS:BS, UTIL!BR:BR), _xlpm.modelo, TRIM(SUBSTITUTE(T53,CHAR(160),"")), _xlpm.nomeMod, IFERROR(_xlfn.XLOOKUP("*"&_xlpm.modelo&"*", UTIL!D:D, UTIL!B:B, "", 2), IFERROR(_xlfn.XLOOKUP("*"&_xlpm.modelo&"*", UTIL!E:E, UTIL!B:B, "", 2), "")), _xlpm.tipoMod, IF(_xlpm.nomeMod="", "", IFERROR(LEFT(_xlpm.nomeMod, FIND(" ", _xlpm.nomeMod)-1), _xlpm.nomeMod)), _xlpm.dimMod, IFERROR(_xlfn.XLOOKUP("*"&_xlpm.modelo&"*", UTIL!D:D, UTIL!K:K, "", 2), IFERROR(_xlfn.XLOOKUP("*"&_xlpm.modelo&"*", UTIL!E:E, UTIL!K:K, "", 2), "")), _xlpm.tipotxt_antigo, IF(_xlpm.ehTrator, "TRATOR", IFERROR(_xlfn.XLOOKUP(_xlpm.chave, _xlpm.fonte, UTIL!BP:BP, "", 0), IFERROR(_xlfn.XLOOKUP("*"&_xlpm.chave&"*", _xlpm.fonte, UTIL!BP:BP, "", 2), "Não encontrado"))), _xlpm.dimtxt_antigo, IFERROR(_xlfn.XLOOKUP(_xlpm.chave, _xlpm.fonte, UTIL!BY:BY, "", 0), IFERROR(_xlfn.XLOOKUP("*"&_xlpm.chave&"*", _xlpm.fonte, UTIL!BY:BY, "", 2), "Não encontrado")), _xlpm.tipotxt, IF(_xlpm.tipoMod<>"", _xlpm.tipoMod, _xlpm.tipotxt_antigo), _xlpm.dimtxt, IF(_xlpm.dimMod<>"", _xlpm.dimMod, _xlpm.dimtxt_antigo), _xlpm.deTxt, IF(L53="CLIENTE", O53, IF(LEFT(L53,4)="http", L53, "MACPONTA AGRO DE "&L53)), _xlpm.paraBase, IF(M53="CLIENTE", P53, M53), _xlpm.paraTxt, IF(LEFT(_xlpm.paraBase,4)="http", _xlpm.paraBase, "MACPONTA AGRO DE "&_xlpm.paraBase), _xlpm.nfParte, IF(LEN(TRIM(I53))=0, "", " -NF "&TRIM(I53)), "- " & _xlpm.tipotxt & ": *" & G53 & "*" & CHAR(13)&CHAR(10) & "- " & _xlpm.dimtxt & CHAR(13)&CHAR(10) & "- *Cliente*: " & J53 & _xlpm.nfParte & CHAR(13)&CHAR(10) & "- *Obs:* " & Q53 & CHAR(13)&CHAR(10) & CHAR(10) & "- *De*: " & _xlpm.deTxt & CHAR(13)&CHAR(10) & "- *Para*: " & _xlpm.paraTxt & CHAR(13)&CHAR(10) & "- *Ida e volta*: +/- " & TEXT(((D53*1.5)/1440),"h:mm") & "h | " & D53 & "km" )} -> - : *CTP28811021*_x000D_ - _x000D_ - *Cliente*: NOTA DO CLIENTE_x000D_ - *Obs:* JAN NOORDEGRAAF NETO 43999791942 - CEN PAULO HOPATA_x000D_ - *De*: https://maps.app.goo.gl/w2FYcAi8ZYYfJ88Y8_x000D_ - *Para*: MACPONTA AGRO DE ARAPOTI_x000D_ - *Ida e volta*: +/- 0:33h | 22km
A54: PROGRAMADO | B54: TERCEIRO AGROMAQ | C54: =IFERROR((D54*1.5)/1440, "?") -> 0.022916667 | D54: 22 | F54: 300 | G54: CTP58701025 | H54: 45980 | J54: JAN NOORDEGRAAF NETO -NF61845 | K54: josiane.oliveira | L54: ARAPOTI | M54: CLIENTE | N54: DE LOJA PARA CLIENTE | O54: MPA | P54: https://maps.app.goo.gl/w2FYcAi8ZYYfJ88Y8 | Q54: JAN NOORDEGRAAF NETO 43999791942 - CEN Paulo Hopata | R54: ARAPOTI | S54: CARRETA | T54: =IF( OR( IFERROR(FIND("BM",G54),0)>0, IFERROR(FIND("PY",G54),0)>0 ), MID(TRIM(SUBSTITUTE(SUBSTITUTE(G54,CHAR(160),""),CHAR(9),"")),4,5), MID(TRIM(SUBSTITUTE(SUBSTITUTE(G54,CHAR(160),""),CHAR(9),"")),4,4) ) -> 5870 | U54: {=_xlfn.LET( _xlpm.ch, TRIM(SUBSTITUTE(G54,CHAR(160),"")), _xlpm.ehTrator, OR(IFERROR(FIND("BM",_xlpm.ch),0)>0, IFERROR(FIND("PY",_xlpm.ch),0)>0), _xlpm.chave, IF(_xlpm.ehTrator, MID(_xlpm.ch,4,5), MID(_xlpm.ch,4,4)), _xlpm.fonte, IF(LEN(_xlpm.chave)=5, UTIL!BS:BS, UTIL!BR:BR), _xlpm.modelo, TRIM(SUBSTITUTE(T54,CHAR(160),"")), _xlpm.nomeMod, IFERROR(_xlfn.XLOOKUP("*"&_xlpm.modelo&"*", UTIL!D:D, UTIL!B:B, "", 2), IFERROR(_xlfn.XLOOKUP("*"&_xlpm.modelo&"*", UTIL!E:E, UTIL!B:B, "", 2), "")), _xlpm.tipoMod, IF(_xlpm.nomeMod="", "", IFERROR(LEFT(_xlpm.nomeMod, FIND(" ", _xlpm.nomeMod)-1), _xlpm.nomeMod)), _xlpm.dimMod, IFERROR(_xlfn.XLOOKUP("*"&_xlpm.modelo&"*", UTIL!D:D, UTIL!K:K, "", 2), IFERROR(_xlfn.XLOOKUP("*"&_xlpm.modelo&"*", UTIL!E:E, UTIL!K:K, "", 2), "")), _xlpm.tipotxt_antigo, IF(_xlpm.ehTrator, "TRATOR", IFERROR(_xlfn.XLOOKUP(_xlpm.chave, _xlpm.fonte, UTIL!BP:BP, "", 0), IFERROR(_xlfn.XLOOKUP("*"&_xlpm.chave&"*", _xlpm.fonte, UTIL!BP:BP, "", 2), "Não encontrado"))), _xlpm.dimtxt_antigo, IFERROR(_xlfn.XLOOKUP(_xlpm.chave, _xlpm.fonte, UTIL!BY:BY, "", 0), IFERROR(_xlfn.XLOOKUP("*"&_xlpm.chave&"*", _xlpm.fonte, UTIL!BY:BY, "", 2), "Não encontrado")), _xlpm.tipotxt, IF(_xlpm.tipoMod<>"", _xlpm.tipoMod, _xlpm.tipotxt_antigo), _xlpm.dimtxt, IF(_xlpm.dimMod<>"", _xlpm.dimMod, _xlpm.dimtxt_antigo), _xlpm.deTxt, IF(L54="CLIENTE", O54, IF(LEFT(L54,4)="http", L54, "MACPONTA AGRO DE "&L54)), _xlpm.paraBase, IF(M54="CLIENTE", P54, M54), _xlpm.paraTxt, IF(LEFT(_xlpm.paraBase,4)="http", _xlpm.paraBase, "MACPONTA AGRO DE "&_xlpm.paraBase), _xlpm.nfParte, IF(LEN(TRIM(I54))=0, "", " -NF "&TRIM(I54)), "- " & _xlpm.tipotxt & ": *" & G54 & "*" & CHAR(13)&CHAR(10) & "- " & _xlpm.dimtxt & CHAR(13)&CHAR(10) & "- *Cliente*: " & J54 & _xlpm.nfParte & CHAR(13)&CHAR(10) & "- *Obs:* " & Q54 & CHAR(13)&CHAR(10) & CHAR(10) & "- *De*: " & _xlpm.deTxt & CHAR(13)&CHAR(10) & "- *Para*: " & _xlpm.paraTxt & CHAR(13)&CHAR(10) & "- *Ida e volta*: +/- " & TEXT(((D54*1.5)/1440),"h:mm") & "h | " & D54 & "km" )} -> - : *CTP58701025*_x000D_ - _x000D_ - *Cliente*: JAN NOORDEGRAAF NETO -NF61845_x000D_ - *Obs:* JAN NOORDEGRAAF NETO 43999791942 - CEN Paulo Hopata_x000D_ - *De*: MACPONTA AGRO DE ARAPOTI_x000D_ - *Para*: https://maps.app.goo.gl/w2FYcAi8ZYYfJ88Y8_x000D_ - *Ida e volta*: +/- 0:33h | 22km
A55: PROGRAMADO | B55: TERCEIRO AGROMAQ | C55: =IFERROR((D55*1.5)/1440, "?") -> 0.022916667 | D55: 22 | F55: 800 | G55: HCCB251KEKC318677 | H55: 45980 | J55: NOTA DO CLIENTE | K55: josiane.oliveira | L55: CLIENTE | M55: ARAPOTI | N55: DE CLIENTE PARA LOJA | O55: https://maps.app.goo.gl/w2FYcAi8ZYYfJ88Y8 | P55: MPA | Q55: JAN NOORDEGRAAF NETO 43999791942 - CEN PAULO HOPATA | R55: ARAPOTI | S55: COLHEITADEIRA | T55: =IF( OR( IFERROR(FIND("BM",G55),0)>0, IFERROR(FIND("PY",G55),0)>0 ), MID(TRIM(SUBSTITUTE(SUBSTITUTE(G55,CHAR(160),""),CHAR(9),"")),4,5), MID(TRIM(SUBSTITUTE(SUBSTITUTE(G55,CHAR(160),""),CHAR(9),"")),4,4) ) -> B251 | U55: {=_xlfn.LET( _xlpm.ch, TRIM(SUBSTITUTE(G55,CHAR(160),"")), _xlpm.ehTrator, OR(IFERROR(FIND("BM",_xlpm.ch),0)>0, IFERROR(FIND("PY",_xlpm.ch),0)>0), _xlpm.chave, IF(_xlpm.ehTrator, MID(_xlpm.ch,4,5), MID(_xlpm.ch,4,4)), _xlpm.fonte, IF(LEN(_xlpm.chave)=5, UTIL!BS:BS, UTIL!BR:BR), _xlpm.modelo, TRIM(SUBSTITUTE(T55,CHAR(160),"")), _xlpm.nomeMod, IFERROR(_xlfn.XLOOKUP("*"&_xlpm.modelo&"*", UTIL!D:D, UTIL!B:B, "", 2), IFERROR(_xlfn.XLOOKUP("*"&_xlpm.modelo&"*", UTIL!E:E, UTIL!B:B, "", 2), "")), _xlpm.tipoMod, IF(_xlpm.nomeMod="", "", IFERROR(LEFT(_xlpm.nomeMod, FIND(" ", _xlpm.nomeMod)-1), _xlpm.nomeMod)), _xlpm.dimMod, IFERROR(_xlfn.XLOOKUP("*"&_xlpm.modelo&"*", UTIL!D:D, UTIL!K:K, "", 2), IFERROR(_xlfn.XLOOKUP("*"&_xlpm.modelo&"*", UTIL!E:E, UTIL!K:K, "", 2), "")), _xlpm.tipotxt_antigo, IF(_xlpm.ehTrator, "TRATOR", IFERROR(_xlfn.XLOOKUP(_xlpm.chave, _xlpm.fonte, UTIL!BP:BP, "", 0), IFERROR(_xlfn.XLOOKUP("*"&_xlpm.chave&"*", _xlpm.fonte, UTIL!BP:BP, "", 2), "Não encontrado"))), _xlpm.dimtxt_antigo, IFERROR(_xlfn.XLOOKUP(_xlpm.chave, _xlpm.fonte, UTIL!BY:BY, "", 0), IFERROR(_xlfn.XLOOKUP("*"&_xlpm.chave&"*", _xlpm.fonte, UTIL!BY:BY, "", 2), "Não encontrado")), _xlpm.tipotxt, IF(_xlpm.tipoMod<>"", _xlpm.tipoMod, _xlpm.tipotxt_antigo), _xlpm.dimtxt, IF(_xlpm.dimMod<>"", _xlpm.dimMod, _xlpm.dimtxt_antigo), _xlpm.deTxt, IF(L55="CLIENTE", O55, IF(LEFT(L55,4)="http", L55, "MACPONTA AGRO DE "&L55)), _xlpm.paraBase, IF(M55="CLIENTE", P55, M55), _xlpm.paraTxt, IF(LEFT(_xlpm.paraBase,4)="http", _xlpm.paraBase, "MACPONTA AGRO DE "&_xlpm.paraBase), _xlpm.nfParte, IF(LEN(TRIM(I55))=0, "", " -NF "&TRIM(I55)), "- " & _xlpm.tipotxt & ": *" & G55 & "*" & CHAR(13)&CHAR(10) & "- " & _xlpm.dimtxt & CHAR(13)&CHAR(10) & "- *Cliente*: " & J55 & _xlpm.nfParte & CHAR(13)&CHAR(10) & "- *Obs:* " & Q55 & CHAR(13)&CHAR(10) & CHAR(10) & "- *De*: " & _xlpm.deTxt & CHAR(13)&CHAR(10) & "- *Para*: " & _xlpm.paraTxt & CHAR(13)&CHAR(10) & "- *Ida e volta*: +/- " & TEXT(((D55*1.5)/1440),"h:mm") & "h | " & D55 & "km" )} -> - : *HCCB251KEKC318677*_x000D_ - _x000D_ - *Cliente*: NOTA DO CLIENTE_x000D_ - *Obs:* JAN NOORDEGRAAF NETO 43999791942 - CEN PAULO HOPATA_x000D_ - *De*: https://maps.app.goo.gl/w2FYcAi8ZYYfJ88Y8_x000D_ - *Para*: MACPONTA AGRO DE ARAPOTI_x000D_ - *Ida e volta*: +/- 0:33h | 22km
A56: PROGRAMADO | B56: TERCEIRO AGROMAQ | C56: =IFERROR((D56*1.5)/1440, "?") -> 0.022916667 | D56: 22 | F56: 400 | G56: JHFY3585PKJF12965 | H56: 45980 | J56: NOTA DO CLIENTE | K56: josiane.oliveira | L56: CLIENTE | M56: ARAPOTI | N56: DE CLIENTE PARA LOJA | O56: https://maps.app.goo.gl/w2FYcAi8ZYYfJ88Y8 | P56: MPA | Q56: JAN NOORDEGRAAF NETO 43999791942 - CEN PAULO HOPATA | R56: ARAPOTI | S56: PLATAFORMA | T56: =IF( OR( IFERROR(FIND("BM",G56),0)>0, IFERROR(FIND("PY",G56),0)>0 ), MID(TRIM(SUBSTITUTE(SUBSTITUTE(G56,CHAR(160),""),CHAR(9),"")),4,5), MID(TRIM(SUBSTITUTE(SUBSTITUTE(G56,CHAR(160),""),CHAR(9),"")),4,4) ) -> Y358 | U56: {=_xlfn.LET( _xlpm.ch, TRIM(SUBSTITUTE(G56,CHAR(160),"")), _xlpm.ehTrator, OR(IFERROR(FIND("BM",_xlpm.ch),0)>0, IFERROR(FIND("PY",_xlpm.ch),0)>0), _xlpm.chave, IF(_xlpm.ehTrator, MID(_xlpm.ch,4,5), MID(_xlpm.ch,4,4)), _xlpm.fonte, IF(LEN(_xlpm.chave)=5, UTIL!BS:BS, UTIL!BR:BR), _xlpm.modelo, TRIM(SUBSTITUTE(T56,CHAR(160),"")), _xlpm.nomeMod, IFERROR(_xlfn.XLOOKUP("*"&_xlpm.modelo&"*", UTIL!D:D, UTIL!B:B, "", 2), IFERROR(_xlfn.XLOOKUP("*"&_xlpm.modelo&"*", UTIL!E:E, UTIL!B:B, "", 2), "")), _xlpm.tipoMod, IF(_xlpm.nomeMod="", "", IFERROR(LEFT(_xlpm.nomeMod, FIND(" ", _xlpm.nomeMod)-1), _xlpm.nomeMod)), _xlpm.dimMod, IFERROR(_xlfn.XLOOKUP("*"&_xlpm.modelo&"*", UTIL!D:D, UTIL!K:K, "", 2), IFERROR(_xlfn.XLOOKUP("*"&_xlpm.modelo&"*", UTIL!E:E, UTIL!K:K, "", 2), "")), _xlpm.tipotxt_antigo, IF(_xlpm.ehTrator, "TRATOR", IFERROR(_xlfn.XLOOKUP(_xlpm.chave, _xlpm.fonte, UTIL!BP:BP, "", 0), IFERROR(_xlfn.XLOOKUP("*"&_xlpm.chave&"*", _xlpm.fonte, UTIL!BP:BP, "", 2), "Não encontrado"))), _xlpm.dimtxt_antigo, IFERROR(_xlfn.XLOOKUP(_xlpm.chave, _xlpm.fonte, UTIL!BY:BY, "", 0), IFERROR(_xlfn.XLOOKUP("*"&_xlpm.chave&"*", _xlpm.fonte, UTIL!BY:BY, "", 2), "Não encontrado")), _xlpm.tipotxt, IF(_xlpm.tipoMod<>"", _xlpm.tipoMod, _xlpm.tipotxt_antigo), _xlpm.dimtxt, IF(_xlpm.dimMod<>"", _xlpm.dimMod, _xlpm.dimtxt_antigo), _xlpm.deTxt, IF(L56="CLIENTE", O56, IF(LEFT(L56,4)="http", L56, "MACPONTA AGRO DE "&L56)), _xlpm.paraBase, IF(M56="CLIENTE", P56, M56), _xlpm.paraTxt, IF(LEFT(_xlpm.paraBase,4)="http", _xlpm.paraBase, "MACPONTA AGRO DE "&_xlpm.paraBase), _xlpm.nfParte, IF(LEN(TRIM(I56))=0, "", " -NF "&TRIM(I56)), "- " & _xlpm.tipotxt & ": *" & G56 & "*" & CHAR(13)&CHAR(10) & "- " & _xlpm.dimtxt & CHAR(13)&CHAR(10) & "- *Cliente*: " & J56 & _xlpm.nfParte & CHAR(13)&CHAR(10) & "- *Obs:* " & Q56 & CHAR(13)&CHAR(10) & CHAR(10) & "- *De*: " & _xlpm.deTxt & CHAR(13)&CHAR(10) & "- *Para*: " & _xlpm.paraTxt & CHAR(13)&CHAR(10) & "- *Ida e volta*: +/- " & TEXT(((D56*1.5)/1440),"h:mm") & "h | " & D56 & "km" )} -> - : *JHFY3585PKJF12965*_x000D_ - _x000D_ - *Cliente*: NOTA DO CLIENTE_x000D_ - *Obs:* JAN NOORDEGRAAF NETO 43999791942 - CEN PAULO HOPATA_x000D_ - *De*: https://maps.app.goo.gl/w2FYcAi8ZYYfJ88Y8_x000D_ - *Para*: MACPONTA AGRO DE ARAPOTI_x000D_ - *Ida e volta*: +/- 0:33h | 22km
A57: PROGRAMADO | B57: TERCEIRO MAZETTO | C57: =IFERROR((D57*1.5)/1440, "?") -> 0.22916667 | D57: 220 | G57: 1BM6100JTSD602254 | H57: 45980 | J57: PATRICIA H O HASEGAWA -NF106525 | K57: euclides.junior | L57: GUARAPUAVA | M57: CLIENTE | N57: DE LOJA PARA CLIENTE | O57: MPA | P57: https://maps.app.goo.gl/sUh1AADFcu4n8yPE8?g_st=iw | Q57: Patricia | R57: GUARAPUAVA | S57: TRATOR | T57: =IF( OR( IFERROR(FIND("BM",G57),0)>0, IFERROR(FIND("PY",G57),0)>0 ), MID(TRIM(SUBSTITUTE(SUBSTITUTE(G57,CHAR(160),""),CHAR(9),"")),4,5), MID(TRIM(SUBSTITUTE(SUBSTITUTE(G57,CHAR(160),""),CHAR(9),"")),4,4) ) -> 6100J | U57: {=_xlfn.LET( _xlpm.ch, TRIM(SUBSTITUTE(G57,CHAR(160),"")), _xlpm.ehTrator, OR(IFERROR(FIND("BM",_xlpm.ch),0)>0, IFERROR(FIND("PY",_xlpm.ch),0)>0), _xlpm.chave, IF(_xlpm.ehTrator, MID(_xlpm.ch,4,5), MID(_xlpm.ch,4,4)), _xlpm.fonte, IF(LEN(_xlpm.chave)=5, UTIL!BS:BS, UTIL!BR:BR), _xlpm.modelo, TRIM(SUBSTITUTE(T57,CHAR(160),"")), _xlpm.nomeMod, IFERROR(_xlfn.XLOOKUP("*"&_xlpm.modelo&"*", UTIL!D:D, UTIL!B:B, "", 2), IFERROR(_xlfn.XLOOKUP("*"&_xlpm.modelo&"*", UTIL!E:E, UTIL!B:B, "", 2), "")), _xlpm.tipoMod, IF(_xlpm.nomeMod="", "", IFERROR(LEFT(_xlpm.nomeMod, FIND(" ", _xlpm.nomeMod)-1), _xlpm.nomeMod)), _xlpm.dimMod, IFERROR(_xlfn.XLOOKUP("*"&_xlpm.modelo&"*", UTIL!D:D, UTIL!K:K, "", 2), IFERROR(_xlfn.XLOOKUP("*"&_xlpm.modelo&"*", UTIL!E:E, UTIL!K:K, "", 2), "")), _xlpm.tipotxt_antigo, IF(_xlpm.ehTrator, "TRATOR", IFERROR(_xlfn.XLOOKUP(_xlpm.chave, _xlpm.fonte, UTIL!BP:BP, "", 0), IFERROR(_xlfn.XLOOKUP("*"&_xlpm.chave&"*", _xlpm.fonte, UTIL!BP:BP, "", 2), "Não encontrado"))), _xlpm.dimtxt_antigo, IFERROR(_xlfn.XLOOKUP(_xlpm.chave, _xlpm.fonte, UTIL!BY:BY, "", 0), IFERROR(_xlfn.XLOOKUP("*"&_xlpm.chave&"*", _xlpm.fonte, UTIL!BY:BY, "", 2), "Não encontrado")), _xlpm.tipotxt, IF(_xlpm.tipoMod<>"", _xlpm.tipoMod, _xlpm.tipotxt_antigo), _xlpm.dimtxt, IF(_xlpm.dimMod<>"", _xlpm.dimMod, _xlpm.dimtxt_antigo), _xlpm.deTxt, IF(L57="CLIENTE", O57, IF(LEFT(L57,4)="http", L57, "MACPONTA AGRO DE "&L57)), _xlpm.paraBase, IF(M57="CLIENTE", P57, M57), _xlpm.paraTxt, IF(LEFT(_xlpm.paraBase,4)="http", _xlpm.paraBase, "MACPONTA AGRO DE "&_xlpm.paraBase), _xlpm.nfParte, IF(LEN(TRIM(I57))=0, "", " -NF "&TRIM(I57)), "- " & _xlpm.tipotxt & ": *" & G57 & "*" & CHAR(13)&CHAR(10) & "- " & _xlpm.dimtxt & CHAR(13)&CHAR(10) & "- *Cliente*: " & J57 & _xlpm.nfParte & CHAR(13)&CHAR(10) & "- *Obs:* " & Q57 & CHAR(13)&CHAR(10) & CHAR(10) & "- *De*: " & _xlpm.deTxt & CHAR(13)&CHAR(10) & "- *Para*: " & _xlpm.paraTxt & CHAR(13)&CHAR(10) & "- *Ida e volta*: +/- " & TEXT(((D57*1.5)/1440),"h:mm") & "h | " & D57 & "km" )} -> - TRATOR: *1BM6100JTSD602254*_x000D_ - _x000D_ - *Cliente*: PATRICIA H O HASEGAWA -NF106525_x000D_ - *Obs:* Patricia_x000D_ - *De*: MACPONTA AGRO DE GUARAPUAVA_x000D_ - *Para*: https://maps.app.goo.gl/sUh1AADFcu4n8yPE8?g_st=iw_x000D_ - *Ida e volta*: +/- 5:30h | 220km
A58: PROGRAMADO | B58: TERCEIRO MAZETTO | C58: =IFERROR((D58*1.5)/1440, "?") -> 0.09375 | D58: 90 | G58: 1BM6100JCSD602446 | H58: 45980 | J58: BRUNNO F VIOMAR -NF 107324 | K58: euclides.junior | L58: GUARAPUAVA | M58: CLIENTE | N58: DE LOJA PARA CLIENTE | O58: MPA | P58: https://maps.app.goo.gl/dMP2u2euHz5GQfGg7 | Q58: Bruno | R58: GUARAPUAVA | S58: TRATOR | T58: =IF( OR( IFERROR(FIND("BM",G58),0)>0, IFERROR(FIND("PY",G58),0)>0 ), MID(TRIM(SUBSTITUTE(SUBSTITUTE(G58,CHAR(160),""),CHAR(9),"")),4,5), MID(TRIM(SUBSTITUTE(SUBSTITUTE(G58,CHAR(160),""),CHAR(9),"")),4,4) ) -> 6100J | U58: {=_xlfn.LET( _xlpm.ch, TRIM(SUBSTITUTE(G58,CHAR(160),"")), _xlpm.ehTrator, OR(IFERROR(FIND("BM",_xlpm.ch),0)>0, IFERROR(FIND("PY",_xlpm.ch),0)>0), _xlpm.chave, IF(_xlpm.ehTrator, MID(_xlpm.ch,4,5), MID(_xlpm.ch,4,4)), _xlpm.fonte, IF(LEN(_xlpm.chave)=5, UTIL!BS:BS, UTIL!BR:BR), _xlpm.modelo, TRIM(SUBSTITUTE(T58,CHAR(160),"")), _xlpm.nomeMod, IFERROR(_xlfn.XLOOKUP("*"&_xlpm.modelo&"*", UTIL!D:D, UTIL!B:B, "", 2), IFERROR(_xlfn.XLOOKUP("*"&_xlpm.modelo&"*", UTIL!E:E, UTIL!B:B, "", 2), "")), _xlpm.tipoMod, IF(_xlpm.nomeMod="", "", IFERROR(LEFT(_xlpm.nomeMod, FIND(" ", _xlpm.nomeMod)-1), _xlpm.nomeMod)), _xlpm.dimMod, IFERROR(_xlfn.XLOOKUP("*"&_xlpm.modelo&"*", UTIL!D:D, UTIL!K:K, "", 2), IFERROR(_xlfn.XLOOKUP("*"&_xlpm.modelo&"*", UTIL!E:E, UTIL!K:K, "", 2), "")), _xlpm.tipotxt_antigo, IF(_xlpm.ehTrator, "TRATOR", IFERROR(_xlfn.XLOOKUP(_xlpm.chave, _xlpm.fonte, UTIL!BP:BP, "", 0), IFERROR(_xlfn.XLOOKUP("*"&_xlpm.chave&"*", _xlpm.fonte, UTIL!BP:BP, "", 2), "Não encontrado"))), _xlpm.dimtxt_antigo, IFERROR(_xlfn.XLOOKUP(_xlpm.chave, _xlpm.fonte, UTIL!BY:BY, "", 0), IFERROR(_xlfn.XLOOKUP("*"&_xlpm.chave&"*", _xlpm.fonte, UTIL!BY:BY, "", 2), "Não encontrado")), _xlpm.tipotxt, IF(_xlpm.tipoMod<>"", _xlpm.tipoMod, _xlpm.tipotxt_antigo), _xlpm.dimtxt, IF(_xlpm.dimMod<>"", _xlpm.dimMod, _xlpm.dimtxt_antigo), _xlpm.deTxt, IF(L58="CLIENTE", O58, IF(LEFT(L58,4)="http", L58, "MACPONTA AGRO DE "&L58)), _xlpm.paraBase, IF(M58="CLIENTE", P58, M58), _xlpm.paraTxt, IF(LEFT(_xlpm.paraBase,4)="http", _xlpm.paraBase, "MACPONTA AGRO DE "&_xlpm.paraBase), _xlpm.nfParte, IF(LEN(TRIM(I58))=0, "", " -NF "&TRIM(I58)), "- " & _xlpm.tipotxt & ": *" & G58 & "*" & CHAR(13)&CHAR(10) & "- " & _xlpm.dimtxt & CHAR(13)&CHAR(10) & "- *Cliente*: " & J58 & _xlpm.nfParte & CHAR(13)&CHAR(10) & "- *Obs:* " & Q58 & CHAR(13)&CHAR(10) & CHAR(10) & "- *De*: " & _xlpm.deTxt & CHAR(13)&CHAR(10) & "- *Para*: " & _xlpm.paraTxt & CHAR(13)&CHAR(10) & "- *Ida e volta*: +/- " & TEXT(((D58*1.5)/1440),"h:mm") & "h | " & D58 & "km" )} -> - TRATOR: *1BM6100JCSD602446*_x000D_ - _x000D_ - *Cliente*: BRUNNO F VIOMAR -NF 107324_x000D_ - *Obs:* Bruno_x000D_ - *De*: MACPONTA AGRO DE GUARAPUAVA_x000D_ - *Para*: https://maps.app.goo.gl/dMP2u2euHz5GQfGg7_x000D_ - *Ida e volta*: +/- 2:15h | 90km
A59: PROGRAMADO | B59: TERCEIRO MAZETTO | C59: =IFERROR((D59*1.5)/1440, "?") -> 0.12708333 | D59: 122 | G59: Y8C525126 | H59: 45980 | J59: ANDRE MUZZOLON TURCO -NF10833 | K59: euclides.junior | L59: GUARAPUAVA | M59: CLIENTE | N59: DE LOJA PARA CLIENTE | O59: MPA | P59: https://maps.app.goo.gl/k8sSRQfK1xFP8eN89 | Q59: Andre | R59: GUARAPUAVA | S59: COLHEITADEIRA | T59: =IF( OR( IFERROR(FIND("BM",G59),0)>0, IFERROR(FIND("PY",G59),0)>0 ), MID(TRIM(SUBSTITUTE(SUBSTITUTE(G59,CHAR(160),""),CHAR(9),"")),4,5), MID(TRIM(SUBSTITUTE(SUBSTITUTE(G59,CHAR(160),""),CHAR(9),"")),4,4) ) -> 5251 | U59: {=_xlfn.LET( _xlpm.ch, TRIM(SUBSTITUTE(G59,CHAR(160),"")), _xlpm.ehTrator, OR(IFERROR(FIND("BM",_xlpm.ch),0)>0, IFERROR(FIND("PY",_xlpm.ch),0)>0), _xlpm.chave, IF(_xlpm.ehTrator, MID(_xlpm.ch,4,5), MID(_xlpm.ch,4,4)), _xlpm.fonte, IF(LEN(_xlpm.chave)=5, UTIL!BS:BS, UTIL!BR:BR), _xlpm.modelo, TRIM(SUBSTITUTE(T59,CHAR(160),"")), _xlpm.nomeMod, IFERROR(_xlfn.XLOOKUP("*"&_xlpm.modelo&"*", UTIL!D:D, UTIL!B:B, "", 2), IFERROR(_xlfn.XLOOKUP("*"&_xlpm.modelo&"*", UTIL!E:E, UTIL!B:B, "", 2), "")), _xlpm.tipoMod, IF(_xlpm.nomeMod="", "", IFERROR(LEFT(_xlpm.nomeMod, FIND(" ", _xlpm.nomeMod)-1), _xlpm.nomeMod)), _xlpm.dimMod, IFERROR(_xlfn.XLOOKUP("*"&_xlpm.modelo&"*", UTIL!D:D, UTIL!K:K, "", 2), IFERROR(_xlfn.XLOOKUP("*"&_xlpm.modelo&"*", UTIL!E:E, UTIL!K:K, "", 2), "")), _xlpm.tipotxt_antigo, IF(_xlpm.ehTrator, "TRATOR", IFERROR(_xlfn.XLOOKUP(_xlpm.chave, _xlpm.fonte, UTIL!BP:BP, "", 0), IFERROR(_xlfn.XLOOKUP("*"&_xlpm.chave&"*", _xlpm.fonte, UTIL!BP:BP, "", 2), "Não encontrado"))), _xlpm.dimtxt_antigo, IFERROR(_xlfn.XLOOKUP(_xlpm.chave, _xlpm.fonte, UTIL!BY:BY, "", 0), IFERROR(_xlfn.XLOOKUP("*"&_xlpm.chave&"*", _xlpm.fonte, UTIL!BY:BY, "", 2), "Não encontrado")), _xlpm.tipotxt, IF(_xlpm.tipoMod<>"", _xlpm.tipoMod, _xlpm.tipotxt_antigo), _xlpm.dimtxt, IF(_xlpm.dimMod<>"", _xlpm.dimMod, _xlpm.dimtxt_antigo), _xlpm.deTxt, IF(L59="CLIENTE", O59, IF(LEFT(L59,4)="http", L59, "MACPONTA AGRO DE "&L59)), _xlpm.paraBase, IF(M59="CLIENTE", P59, M59), _xlpm.paraTxt, IF(LEFT(_xlpm.paraBase,4)="http", _xlpm.paraBase, "MACPONTA AGRO DE "&_xlpm.paraBase), _xlpm.nfParte, IF(LEN(TRIM(I59))=0, "", " -NF "&TRIM(I59)), "- " & _xlpm.tipotxt & ": *" & G59 & "*" & CHAR(13)&CHAR(10) & "- " & _xlpm.dimtxt & CHAR(13)&CHAR(10) & "- *Cliente*: " & J59 & _xlpm.nfParte & CHAR(13)&CHAR(10) & "- *Obs:* " & Q59 & CHAR(13)&CHAR(10) & CHAR(10) & "- *De*: " & _xlpm.deTxt & CHAR(13)&CHAR(10) & "- *Para*: " & _xlpm.paraTxt & CHAR(13)&CHAR(10) & "- *Ida e volta*: +/- " & TEXT(((D59*1.5)/1440),"h:mm") & "h | " & D59 & "km" )} -> - : *Y8C525126*_x000D_ - _x000D_ - *Cliente*: ANDRE MUZZOLON TURCO -NF10833_x000D_ - *Obs:* Andre_x000D_ - *De*: MACPONTA AGRO DE GUARAPUAVA_x000D_ - *Para*: https://maps.app.goo.gl/k8sSRQfK1xFP8eN89_x000D_ - *Ida e volta*: +/- 3:03h | 122km
A60: PROGRAMADO | B60: TERCEIRO DEMETRIO | C60: =IFERROR((D60*1.5)/1440, "?") -> 0.14583333 | D60: 140 | F60: 550 | G60: 1BM5060EVS4201539 | H60: 45980 | J60: OSMAR DIATCZUK -NF 30883 | K60: fernando.wiesinies | L60: IRATI | M60: CLIENTE | N60: DE LOJA PARA CLIENTE | O60: MPA | P60: https://maps.google.com/maps?q=-25.1189094%2C-51.0372015&z=17&hl=pt-BR | Q60: Osmar (42) 99908-3514 | R60: PRUDENTOPOLIS | S60: TRATOR | T60: =IF( OR( IFERROR(FIND("BM",G60),0)>0, IFERROR(FIND("PY",G60),0)>0 ), MID(TRIM(SUBSTITUTE(SUBSTITUTE(G60,CHAR(160),""),CHAR(9),"")),4,5), MID(TRIM(SUBSTITUTE(SUBSTITUTE(G60,CHAR(160),""),CHAR(9),"")),4,4) ) -> 5060E | U60: {=_xlfn.LET( _xlpm.ch, TRIM(SUBSTITUTE(G60,CHAR(160),"")), _xlpm.ehTrator, OR(IFERROR(FIND("BM",_xlpm.ch),0)>0, IFERROR(FIND("PY",_xlpm.ch),0)>0), _xlpm.chave, IF(_xlpm.ehTrator, MID(_xlpm.ch,4,5), MID(_xlpm.ch,4,4)), _xlpm.fonte, IF(LEN(_xlpm.chave)=5, UTIL!BS:BS, UTIL!BR:BR), _xlpm.modelo, TRIM(SUBSTITUTE(T60,CHAR(160),"")), _xlpm.nomeMod, IFERROR(_xlfn.XLOOKUP("*"&_xlpm.modelo&"*", UTIL!D:D, UTIL!B:B, "", 2), IFERROR(_xlfn.XLOOKUP("*"&_xlpm.modelo&"*", UTIL!E:E, UTIL!B:B, "", 2), "")), _xlpm.tipoMod, IF(_xlpm.nomeMod="", "", IFERROR(LEFT(_xlpm.nomeMod, FIND(" ", _xlpm.nomeMod)-1), _xlpm.nomeMod)), _xlpm.dimMod, IFERROR(_xlfn.XLOOKUP("*"&_xlpm.modelo&"*", UTIL!D:D, UTIL!K:K, "", 2), IFERROR(_xlfn.XLOOKUP("*"&_xlpm.modelo&"*", UTIL!E:E, UTIL!K:K, "", 2), "")), _xlpm.tipotxt_antigo, IF(_xlpm.ehTrator, "TRATOR", IFERROR(_xlfn.XLOOKUP(_xlpm.chave, _xlpm.fonte, UTIL!BP:BP, "", 0), IFERROR(_xlfn.XLOOKUP("*"&_xlpm.chave&"*", _xlpm.fonte, UTIL!BP:BP, "", 2), "Não encontrado"))), _xlpm.dimtxt_antigo, IFERROR(_xlfn.XLOOKUP(_xlpm.chave, _xlpm.fonte, UTIL!BY:BY, "", 0), IFERROR(_xlfn.XLOOKUP("*"&_xlpm.chave&"*", _xlpm.fonte, UTIL!BY:BY, "", 2), "Não encontrado")), _xlpm.tipotxt, IF(_xlpm.tipoMod<>"", _xlpm.tipoMod, _xlpm.tipotxt_antigo), _xlpm.dimtxt, IF(_xlpm.dimMod<>"", _xlpm.dimMod, _xlpm.dimtxt_antigo), _xlpm.deTxt, IF(L60="CLIENTE", O60, IF(LEFT(L60,4)="http", L60, "MACPONTA AGRO DE "&L60)), _xlpm.paraBase, IF(M60="CLIENTE", P60, M60), _xlpm.paraTxt, IF(LEFT(_xlpm.paraBase,4)="http", _xlpm.paraBase, "MACPONTA AGRO DE "&_xlpm.paraBase), _xlpm.nfParte, IF(LEN(TRIM(I60))=0, "", " -NF "&TRIM(I60)), "- " & _xlpm.tipotxt & ": *" & G60 & "*" & CHAR(13)&CHAR(10) & "- " & _xlpm.dimtxt & CHAR(13)&CHAR(10) & "- *Cliente*: " & J60 & _xlpm.nfParte & CHAR(13)&CHAR(10) & "- *Obs:* " & Q60 & CHAR(13)&CHAR(10) & CHAR(10) & "- *De*: " & _xlpm.deTxt & CHAR(13)&CHAR(10) & "- *Para*: " & _xlpm.paraTxt & CHAR(13)&CHAR(10) & "- *Ida e volta*: +/- " & TEXT(((D60*1.5)/1440),"h:mm") & "h | " & D60 & "km" )} -> - TRATOR: *1BM5060EVS4201539*_x000D_ - _x000D_ - *Cliente*: OSMAR DIATCZUK -NF 30883_x000D_ - *Obs:* Osmar (42) 99908-3514_x000D_ - *De*: MACPONTA AGRO DE IRATI_x000D_ - *Para*: https://maps.google.com/maps?q=-25.1189094%2C-51.0372015&z=17&hl=pt-BR_x000D_ - *Ida e volta*: +/- 3:30h | 140km
A61: PROGRAMADO (D) | B61: PROPRIO VW | C61: =IFERROR((D61*1.5)/1440, "?") -> 0.058333333 | D61: 56 | E61: =IFERROR((D61*6),"?") -> 336 | G61: 1BM7215CJSH000128 | H61: 45980 | J61: GOLFE CLUB -NF79151 | K61: carolina.quadros | L61: PONTA GROSSA | M61: CLIENTE | N61: DE LOJA PARA DEMONSTRAÇÃO | O61: MPA | P61: https://maps.app.goo.gl/nPrR72QZAjPCStGf7 | Q61: Silvana +55 42 9955-7892 (Golf Clube) | R61: PONTA GROSSA | S61: TRATOR | T61: =IF( OR( IFERROR(FIND("BM",G61),0)>0, IFERROR(FIND("PY",G61),0)>0 ), MID(TRIM(SUBSTITUTE(SUBSTITUTE(G61,CHAR(160),""),CHAR(9),"")),4,5), MID(TRIM(SUBSTITUTE(SUBSTITUTE(G61,CHAR(160),""),CHAR(9),"")),4,4) ) -> 7215C | U61: {=_xlfn.LET( _xlpm.ch, TRIM(SUBSTITUTE(G61,CHAR(160),"")), _xlpm.ehTrator, OR(IFERROR(FIND("BM",_xlpm.ch),0)>0, IFERROR(FIND("PY",_xlpm.ch),0)>0), _xlpm.chave, IF(_xlpm.ehTrator, MID(_xlpm.ch,4,5), MID(_xlpm.ch,4,4)), _xlpm.fonte, IF(LEN(_xlpm.chave)=5, UTIL!BS:BS, UTIL!BR:BR), _xlpm.modelo, TRIM(SUBSTITUTE(T61,CHAR(160),"")), _xlpm.nomeMod, IFERROR(_xlfn.XLOOKUP("*"&_xlpm.modelo&"*", UTIL!D:D, UTIL!B:B, "", 2), IFERROR(_xlfn.XLOOKUP("*"&_xlpm.modelo&"*", UTIL!E:E, UTIL!B:B, "", 2), "")), _xlpm.tipoMod, IF(_xlpm.nomeMod="", "", IFERROR(LEFT(_xlpm.nomeMod, FIND(" ", _xlpm.nomeMod)-1), _xlpm.nomeMod)), _xlpm.dimMod, IFERROR(_xlfn.XLOOKUP("*"&_xlpm.modelo&"*", UTIL!D:D, UTIL!K:K, "", 2), IFERROR(_xlfn.XLOOKUP("*"&_xlpm.modelo&"*", UTIL!E:E, UTIL!K:K, "", 2), "")), _xlpm.tipotxt_antigo, IF(_xlpm.ehTrator, "TRATOR", IFERROR(_xlfn.XLOOKUP(_xlpm.chave, _xlpm.fonte, UTIL!BP:BP, "", 0), IFERROR(_xlfn.XLOOKUP("*"&_xlpm.chave&"*", _xlpm.fonte, UTIL!BP:BP, "", 2), "Não encontrado"))), _xlpm.dimtxt_antigo, IFERROR(_xlfn.XLOOKUP(_xlpm.chave, _xlpm.fonte, UTIL!BY:BY, "", 0), IFERROR(_xlfn.XLOOKUP("*"&_xlpm.chave&"*", _xlpm.fonte, UTIL!BY:BY, "", 2), "Não encontrado")), _xlpm.tipotxt, IF(_xlpm.tipoMod<>"", _xlpm.tipoMod, _xlpm.tipotxt_antigo), _xlpm.dimtxt, IF(_xlpm.dimMod<>"", _xlpm.dimMod, _xlpm.dimtxt_antigo), _xlpm.deTxt, IF(L61="CLIENTE", O61, IF(LEFT(L61,4)="http", L61, "MACPONTA AGRO DE "&L61)), _xlpm.paraBase, IF(M61="CLIENTE", P61, M61), _xlpm.paraTxt, IF(LEFT(_xlpm.paraBase,4)="http", _xlpm.paraBase, "MACPONTA AGRO DE "&_xlpm.paraBase), _xlpm.nfParte, IF(LEN(TRIM(I61))=0, "", " -NF "&TRIM(I61)), "- " & _xlpm.tipotxt & ": *" & G61 & "*" & CHAR(13)&CHAR(10) & "- " & _xlpm.dimtxt & CHAR(13)&CHAR(10) & "- *Cliente*: " & J61 & _xlpm.nfParte & CHAR(13)&CHAR(10) & "- *Obs:* " & Q61 & CHAR(13)&CHAR(10) & CHAR(10) & "- *De*: " & _xlpm.deTxt & CHAR(13)&CHAR(10) & "- *Para*: " & _xlpm.paraTxt & CHAR(13)&CHAR(10) & "- *Ida e volta*: +/- " & TEXT(((D61*1.5)/1440),"h:mm") & "h | " & D61 & "km" )} -> - TRATOR: *1BM7215CJSH000128*_x000D_ - _x000D_ - *Cliente*: GOLFE CLUB -NF79151_x000D_ - *Obs:* Silvana +55 42 9955-7892 (Golf Clube)_x000D_ - *De*: MACPONTA AGRO DE PONTA GROSSA_x000D_ - *Para*: https://maps.app.goo.gl/nPrR72QZAjPCStGf7_x000D_ - *Ida e volta*: +/- 1:24h | 56km
A62: PROGRAMADO (D) | B62: PROPRIO VW | C62: =IFERROR((D62*1.5)/1440, "?") -> 0.058333333 | D62: 56 | E62: =IFERROR((D62*6),"?") -> 336 | G62: 1BM6210MPS3001463 | H62: 45980 | J62: GOLFE CLUB -NF79151 | K62: carolina.quadros | L62: PONTA GROSSA | M62: CLIENTE | N62: DE LOJA PARA DEMONSTRAÇÃO | O62: MPA | P62: https://maps.app.goo.gl/nPrR72QZAjPCStGf7 | Q62: Silvana +55 42 9955-7892 (Golf Clube) | R62: PONTA GROSSA | S62: TRATOR | T62: =IF( OR( IFERROR(FIND("BM",G62),0)>0, IFERROR(FIND("PY",G62),0)>0 ), MID(TRIM(SUBSTITUTE(SUBSTITUTE(G62,CHAR(160),""),CHAR(9),"")),4,5), MID(TRIM(SUBSTITUTE(SUBSTITUTE(G62,CHAR(160),""),CHAR(9),"")),4,4) ) -> 6210M | U62: {=_xlfn.LET( _xlpm.ch, TRIM(SUBSTITUTE(G62,CHAR(160),"")), _xlpm.ehTrator, OR(IFERROR(FIND("BM",_xlpm.ch),0)>0, IFERROR(FIND("PY",_xlpm.ch),0)>0), _xlpm.chave, IF(_xlpm.ehTrator, MID(_xlpm.ch,4,5), MID(_xlpm.ch,4,4)), _xlpm.fonte, IF(LEN(_xlpm.chave)=5, UTIL!BS:BS, UTIL!BR:BR), _xlpm.modelo, TRIM(SUBSTITUTE(T62,CHAR(160),"")), _xlpm.nomeMod, IFERROR(_xlfn.XLOOKUP("*"&_xlpm.modelo&"*", UTIL!D:D, UTIL!B:B, "", 2), IFERROR(_xlfn.XLOOKUP("*"&_xlpm.modelo&"*", UTIL!E:E, UTIL!B:B, "", 2), "")), _xlpm.tipoMod, IF(_xlpm.nomeMod="", "", IFERROR(LEFT(_xlpm.nomeMod, FIND(" ", _xlpm.nomeMod)-1), _xlpm.nomeMod)), _xlpm.dimMod, IFERROR(_xlfn.XLOOKUP("*"&_xlpm.modelo&"*", UTIL!D:D, UTIL!K:K, "", 2), IFERROR(_xlfn.XLOOKUP("*"&_xlpm.modelo&"*", UTIL!E:E, UTIL!K:K, "", 2), "")), _xlpm.tipotxt_antigo, IF(_xlpm.ehTrator, "TRATOR", IFERROR(_xlfn.XLOOKUP(_xlpm.chave, _xlpm.fonte, UTIL!BP:BP, "", 0), IFERROR(_xlfn.XLOOKUP("*"&_xlpm.chave&"*", _xlpm.fonte, UTIL!BP:BP, "", 2), "Não encontrado"))), _xlpm.dimtxt_antigo, IFERROR(_xlfn.XLOOKUP(_xlpm.chave, _xlpm.fonte, UTIL!BY:BY, "", 0), IFERROR(_xlfn.XLOOKUP("*"&_xlpm.chave&"*", _xlpm.fonte, UTIL!BY:BY, "", 2), "Não encontrado")), _xlpm.tipotxt, IF(_xlpm.tipoMod<>"", _xlpm.tipoMod, _xlpm.tipotxt_antigo), _xlpm.dimtxt, IF(_xlpm.dimMod<>"", _xlpm.dimMod, _xlpm.dimtxt_antigo), _xlpm.deTxt, IF(L62="CLIENTE", O62, IF(LEFT(L62,4)="http", L62, "MACPONTA AGRO DE "&L62)), _xlpm.paraBase, IF(M62="CLIENTE", P62, M62), _xlpm.paraTxt, IF(LEFT(_xlpm.paraBase,4)="http", _xlpm.paraBase, "MACPONTA AGRO DE "&_xlpm.paraBase), _xlpm.nfParte, IF(LEN(TRIM(I62))=0, "", " -NF "&TRIM(I62)), "- " & _xlpm.tipotxt & ": *" & G62 & "*" & CHAR(13)&CHAR(10) & "- " & _xlpm.dimtxt & CHAR(13)&CHAR(10) & "- *Cliente*: " & J62 & _xlpm.nfParte & CHAR(13)&CHAR(10) & "- *Obs:* " & Q62 & CHAR(13)&CHAR(10) & CHAR(10) & "- *De*: " & _xlpm.deTxt & CHAR(13)&CHAR(10) & "- *Para*: " & _xlpm.paraTxt & CHAR(13)&CHAR(10) & "- *Ida e volta*: +/- " & TEXT(((D62*1.5)/1440),"h:mm") & "h | " & D62 & "km" )} -> - TRATOR: *1BM6210MPS3001463*_x000D_ - _x000D_ - *Cliente*: GOLFE CLUB -NF79151_x000D_ - *Obs:* Silvana +55 42 9955-7892 (Golf Clube)_x000D_ - *De*: MACPONTA AGRO DE PONTA GROSSA_x000D_ - *Para*: https://maps.app.goo.gl/nPrR72QZAjPCStGf7_x000D_ - *Ida e volta*: +/- 1:24h | 56km
A63: RECEBIDO (D) | B63: NÃO DEFINIDO | C63: =IFERROR((D63*1.5)/1440, "?") -> 0.15625 | D63: 150 | E63: 200 | G63: 1CQ0630AHR0155127 | H63: 45981 | J63: MARCELO RIBEIRO NARDI -NF278794 VOLTA | K63: marcos.ribas | L63: CLIENTE | M63: PONTA GROSSA | N63: DE CLIENTE PARA LOJA | O63: https://maps.app.goo.gl/2DJawZBMR4yqycss9 | P63: MPA | Q63: DANILO - MARCELO | R63: PONTA GROSSA | S63: PLATAFORMA | T63: =IF( OR( IFERROR(FIND("BM",G63),0)>0, IFERROR(FIND("PY",G63),0)>0 ), MID(TRIM(SUBSTITUTE(SUBSTITUTE(G63,CHAR(160),""),CHAR(9),"")),4,5), MID(TRIM(SUBSTITUTE(SUBSTITUTE(G63,CHAR(160),""),CHAR(9),"")),4,4) ) -> 0630 | U63: {=_xlfn.LET( _xlpm.ch, TRIM(SUBSTITUTE(G63,CHAR(160),"")), _xlpm.ehTrator, OR(IFERROR(FIND("BM",_xlpm.ch),0)>0, IFERROR(FIND("PY",_xlpm.ch),0)>0), _xlpm.chave, IF(_xlpm.ehTrator, MID(_xlpm.ch,4,5), MID(_xlpm.ch,4,4)), _xlpm.fonte, IF(LEN(_xlpm.chave)=5, UTIL!BS:BS, UTIL!BR:BR), _xlpm.modelo, TRIM(SUBSTITUTE(T63,CHAR(160),"")), _xlpm.nomeMod, IFERROR(_xlfn.XLOOKUP("*"&_xlpm.modelo&"*", UTIL!D:D, UTIL!B:B, "", 2), IFERROR(_xlfn.XLOOKUP("*"&_xlpm.modelo&"*", UTIL!E:E, UTIL!B:B, "", 2), "")), _xlpm.tipoMod, IF(_xlpm.nomeMod="", "", IFERROR(LEFT(_xlpm.nomeMod, FIND(" ", _xlpm.nomeMod)-1), _xlpm.nomeMod)), _xlpm.dimMod, IFERROR(_xlfn.XLOOKUP("*"&_xlpm.modelo&"*", UTIL!D:D, UTIL!K:K, "", 2), IFERROR(_xlfn.XLOOKUP("*"&_xlpm.modelo&"*", UTIL!E:E, UTIL!K:K, "", 2), "")), _xlpm.tipotxt_antigo, IF(_xlpm.ehTrator, "TRATOR", IFERROR(_xlfn.XLOOKUP(_xlpm.chave, _xlpm.fonte, UTIL!BP:BP, "", 0), IFERROR(_xlfn.XLOOKUP("*"&_xlpm.chave&"*", _xlpm.fonte, UTIL!BP:BP, "", 2), "Não encontrado"))), _xlpm.dimtxt_antigo, IFERROR(_xlfn.XLOOKUP(_xlpm.chave, _xlpm.fonte, UTIL!BY:BY, "", 0), IFERROR(_xlfn.XLOOKUP("*"&_xlpm.chave&"*", _xlpm.fonte, UTIL!BY:BY, "", 2), "Não encontrado")), _xlpm.tipotxt, IF(_xlpm.tipoMod<>"", _xlpm.tipoMod, _xlpm.tipotxt_antigo), _xlpm.dimtxt, IF(_xlpm.dimMod<>"", _xlpm.dimMod, _xlpm.dimtxt_antigo), _xlpm.deTxt, IF(L63="CLIENTE", O63, IF(LEFT(L63,4)="http", L63, "MACPONTA AGRO DE "&L63)), _xlpm.paraBase, IF(M63="CLIENTE", P63, M63), _xlpm.paraTxt, IF(LEFT(_xlpm.paraBase,4)="http", _xlpm.paraBase, "MACPONTA AGRO DE "&_xlpm.paraBase), _xlpm.nfParte, IF(LEN(TRIM(I63))=0, "", " -NF "&TRIM(I63)), "- " & _xlpm.tipotxt & ": *" & G63 & "*" & CHAR(13)&CHAR(10) & "- " & _xlpm.dimtxt & CHAR(13)&CHAR(10) & "- *Cliente*: " & J63 & _xlpm.nfParte & CHAR(13)&CHAR(10) & "- *Obs:* " & Q63 & CHAR(13)&CHAR(10) & CHAR(10) & "- *De*: " & _xlpm.deTxt & CHAR(13)&CHAR(10) & "- *Para*: " & _xlpm.paraTxt & CHAR(13)&CHAR(10) & "- *Ida e volta*: +/- " & TEXT(((D63*1.5)/1440),"h:mm") & "h | " & D63 & "km" )} -> - PLATAFORMA: *1CQ0630AHR0155127*_x000D_ - A:1,60 x C:9,14 x L:1,80-1,80 x P:2.871kg_x000D_ - *Cliente*: MARCELO RIBEIRO NARDI -NF278794 VOLTA_x000D_ - *Obs:* DANILO - MARCELO _x000D_ - *De*: https://maps.app.goo.gl/2DJawZBMR4yqycss9_x000D_ - *Para*: MACPONTA AGRO DE PONTA GROSSA_x000D_ - *Ida e volta*: +/- 3:45h | 150km
A64: RECEBIDO (D) | B64: NÃO DEFINIDO | C64: =IFERROR((D64*1.5)/1440, "?") -> 0.15625 | D64: 150 | E64: 800 | G64: 1CQS550AER0155105 | H64: 45981 | J64: MARCELO RIBEIRO NARDI -NF278794 VOLTA | K64: marcos.ribas | L64: CLIENTE | M64: PONTA GROSSA | N64: DE CLIENTE PARA LOJA | O64: https://maps.app.goo.gl/2DJawZBMR4yqycss9 | P64: MPA | Q64: DANILO - MARCELO | R64: PONTA GROSSA | S64: COLHEITADEIRA | T64: =IF( OR( IFERROR(FIND("BM",G64),0)>0, IFERROR(FIND("PY",G64),0)>0 ), MID(TRIM(SUBSTITUTE(SUBSTITUTE(G64,CHAR(160),""),CHAR(9),"")),4,5), MID(TRIM(SUBSTITUTE(SUBSTITUTE(G64,CHAR(160),""),CHAR(9),"")),4,4) ) -> S550 | U64: {=_xlfn.LET( _xlpm.ch, TRIM(SUBSTITUTE(G64,CHAR(160),"")), _xlpm.ehTrator, OR(IFERROR(FIND("BM",_xlpm.ch),0)>0, IFERROR(FIND("PY",_xlpm.ch),0)>0), _xlpm.chave, IF(_xlpm.ehTrator, MID(_xlpm.ch,4,5), MID(_xlpm.ch,4,4)), _xlpm.fonte, IF(LEN(_xlpm.chave)=5, UTIL!BS:BS, UTIL!BR:BR), _xlpm.modelo, TRIM(SUBSTITUTE(T64,CHAR(160),"")), _xlpm.nomeMod, IFERROR(_xlfn.XLOOKUP("*"&_xlpm.modelo&"*", UTIL!D:D, UTIL!B:B, "", 2), IFERROR(_xlfn.XLOOKUP("*"&_xlpm.modelo&"*", UTIL!E:E, UTIL!B:B, "", 2), "")), _xlpm.tipoMod, IF(_xlpm.nomeMod="", "", IFERROR(LEFT(_xlpm.nomeMod, FIND(" ", _xlpm.nomeMod)-1), _xlpm.nomeMod)), _xlpm.dimMod, IFERROR(_xlfn.XLOOKUP("*"&_xlpm.modelo&"*", UTIL!D:D, UTIL!K:K, "", 2), IFERROR(_xlfn.XLOOKUP("*"&_xlpm.modelo&"*", UTIL!E:E, UTIL!K:K, "", 2), "")), _xlpm.tipotxt_antigo, IF(_xlpm.ehTrator, "TRATOR", IFERROR(_xlfn.XLOOKUP(_xlpm.chave, _xlpm.fonte, UTIL!BP:BP, "", 0), IFERROR(_xlfn.XLOOKUP("*"&_xlpm.chave&"*", _xlpm.fonte, UTIL!BP:BP, "", 2), "Não encontrado"))), _xlpm.dimtxt_antigo, IFERROR(_xlfn.XLOOKUP(_xlpm.chave, _xlpm.fonte, UTIL!BY:BY, "", 0), IFERROR(_xlfn.XLOOKUP("*"&_xlpm.chave&"*", _xlpm.fonte, UTIL!BY:BY, "", 2), "Não encontrado")), _xlpm.tipotxt, IF(_xlpm.tipoMod<>"", _xlpm.tipoMod, _xlpm.tipotxt_antigo), _xlpm.dimtxt, IF(_xlpm.dimMod<>"", _xlpm.dimMod, _xlpm.dimtxt_antigo), _xlpm.deTxt, IF(L64="CLIENTE", O64, IF(LEFT(L64,4)="http", L64, "MACPONTA AGRO DE "&L64)), _xlpm.paraBase, IF(M64="CLIENTE", P64, M64), _xlpm.paraTxt, IF(LEFT(_xlpm.paraBase,4)="http", _xlpm.paraBase, "MACPONTA AGRO DE "&_xlpm.paraBase), _xlpm.nfParte, IF(LEN(TRIM(I64))=0, "", " -NF "&TRIM(I64)), "- " & _xlpm.tipotxt & ": *" & G64 & "*" & CHAR(13)&CHAR(10) & "- " & _xlpm.dimtxt & CHAR(13)&CHAR(10) & "- *Cliente*: " & J64 & _xlpm.nfParte & CHAR(13)&CHAR(10) & "- *Obs:* " & Q64 & CHAR(13)&CHAR(10) & CHAR(10) & "- *De*: " & _xlpm.deTxt & CHAR(13)&CHAR(10) & "- *Para*: " & _xlpm.paraTxt & CHAR(13)&CHAR(10) & "- *Ida e volta*: +/- " & TEXT(((D64*1.5)/1440),"h:mm") & "h | " & D64 & "km" )} -> - COLHEITADEIRA: *1CQS550AER0155105*_x000D_ - A:3,80 x C:10,00 x L:3,70-4,20 x P:15.938kg_x000D_ - *Cliente*: MARCELO RIBEIRO NARDI -NF278794 VOLTA_x000D_ - *Obs:* DANILO - MARCELO _x000D_ - *De*: https://maps.app.goo.gl/2DJawZBMR4yqycss9_x000D_ - *Para*: MACPONTA AGRO DE PONTA GROSSA_x000D_ - *Ida e volta*: +/- 3:45h | 150km
A65: RECEBIDO | B65: NÃO DEFINIDO | C65: =IFERROR((D65*1.5)/1440, "?") -> 0.49479167 | D65: 475 | E65: =IFERROR((D65*6),"?") -> 2850 | G65: 1BM6100JTSD602559 | H65: 45982 | J65: HAROLDO L R FILHO -NF109957 | K65: fernando.wiesinies | L65: GUARAPUAVA | M65: CLIENTE | N65: DE LOJA PARA CLIENTE | O65: MPA | P65: https://maps.app.goo.gl/SAQGugLBfo1Uqy2XA?g_st=awb | Q65: Haroldo (51)99902-8053 | R65: CASTRO | S65: TRATOR | T65: =IF( OR( IFERROR(FIND("BM",G65),0)>0, IFERROR(FIND("PY",G65),0)>0 ), MID(TRIM(SUBSTITUTE(SUBSTITUTE(G65,CHAR(160),""),CHAR(9),"")),4,5), MID(TRIM(SUBSTITUTE(SUBSTITUTE(G65,CHAR(160),""),CHAR(9),"")),4,4) ) -> 6100J | U65: {=_xlfn.LET( _xlpm.ch, TRIM(SUBSTITUTE(G65,CHAR(160),"")), _xlpm.ehTrator, OR(IFERROR(FIND("BM",_xlpm.ch),0)>0, IFERROR(FIND("PY",_xlpm.ch),0)>0), _xlpm.chave, IF(_xlpm.ehTrator, MID(_xlpm.ch,4,5), MID(_xlpm.ch,4,4)), _xlpm.fonte, IF(LEN(_xlpm.chave)=5, UTIL!BS:BS, UTIL!BR:BR), _xlpm.modelo, TRIM(SUBSTITUTE(T65,CHAR(160),"")), _xlpm.nomeMod, IFERROR(_xlfn.XLOOKUP("*"&_xlpm.modelo&"*", UTIL!D:D, UTIL!B:B, "", 2), IFERROR(_xlfn.XLOOKUP("*"&_xlpm.modelo&"*", UTIL!E:E, UTIL!B:B, "", 2), "")), _xlpm.tipoMod, IF(_xlpm.nomeMod="", "", IFERROR(LEFT(_xlpm.nomeMod, FIND(" ", _xlpm.nomeMod)-1), _xlpm.nomeMod)), _xlpm.dimMod, IFERROR(_xlfn.XLOOKUP("*"&_xlpm.modelo&"*", UTIL!D:D, UTIL!K:K, "", 2), IFERROR(_xlfn.XLOOKUP("*"&_xlpm.modelo&"*", UTIL!E:E, UTIL!K:K, "", 2), "")), _xlpm.tipotxt_antigo, IF(_xlpm.ehTrator, "TRATOR", IFERROR(_xlfn.XLOOKUP(_xlpm.chave, _xlpm.fonte, UTIL!BP:BP, "", 0), IFERROR(_xlfn.XLOOKUP("*"&_xlpm.chave&"*", _xlpm.fonte, UTIL!BP:BP, "", 2), "Não encontrado"))), _xlpm.dimtxt_antigo, IFERROR(_xlfn.XLOOKUP(_xlpm.chave, _xlpm.fonte, UTIL!BY:BY, "", 0), IFERROR(_xlfn.XLOOKUP("*"&_xlpm.chave&"*", _xlpm.fonte, UTIL!BY:BY, "", 2), "Não encontrado")), _xlpm.tipotxt, IF(_xlpm.tipoMod<>"", _xlpm.tipoMod, _xlpm.tipotxt_antigo), _xlpm.dimtxt, IF(_xlpm.dimMod<>"", _xlpm.dimMod, _xlpm.dimtxt_antigo), _xlpm.deTxt, IF(L65="CLIENTE", O65, IF(LEFT(L65,4)="http", L65, "MACPONTA AGRO DE "&L65)), _xlpm.paraBase, IF(M65="CLIENTE", P65, M65), _xlpm.paraTxt, IF(LEFT(_xlpm.paraBase,4)="http", _xlpm.paraBase, "MACPONTA AGRO DE "&_xlpm.paraBase), _xlpm.nfParte, IF(LEN(TRIM(I65))=0, "", " -NF "&TRIM(I65)), "- " & _xlpm.tipotxt & ": *" & G65 & "*" & CHAR(13)&CHAR(10) & "- " & _xlpm.dimtxt & CHAR(13)&CHAR(10) & "- *Cliente*: " & J65 & _xlpm.nfParte & CHAR(13)&CHAR(10) & "- *Obs:* " & Q65 & CHAR(13)&CHAR(10) & CHAR(10) & "- *De*: " & _xlpm.deTxt & CHAR(13)&CHAR(10) & "- *Para*: " & _xlpm.paraTxt & CHAR(13)&CHAR(10) & "- *Ida e volta*: +/- " & TEXT(((D65*1.5)/1440),"h:mm") & "h | " & D65 & "km" )} -> - TRATOR: *1BM6100JTSD602559*_x000D_ - _x000D_ - *Cliente*: HAROLDO L R FILHO -NF109957_x000D_ - *Obs:* Haroldo (51)99902-8053_x000D_ - *De*: MACPONTA AGRO DE GUARAPUAVA_x000D_ - *Para*: https://maps.app.goo.gl/SAQGugLBfo1Uqy2XA?g_st=awb_x000D_ - *Ida e volta*: +/- 11:52h | 475km
A66: RECEBIDO (D) | B66: NÃO DEFINIDO | C66: =IFERROR((D66*1.5)/1440, "?") -> 0.085416667 | D66: 82 | E66: =IFERROR((D66*6),"?") -> 492 | G66: 1BM5080EPS6204421 | H66: 45983 | J66: NÃO INFORMADO- NÃO TEM NF | K66: marcos.ribas | L66: PONTA GROSSA | M66: CLIENTE | N66: DE LOJA PARA DEMONSTRAÇÃO | O66: MPA | P66: https://maps.app.goo.gl/BxL47zGps2wAbAig9 | R66: PONTA GROSSA | S66: TRATOR | T66: =IF( OR( IFERROR(FIND("BM",G66),0)>0, IFERROR(FIND("PY",G66),0)>0 ), MID(TRIM(SUBSTITUTE(SUBSTITUTE(G66,CHAR(160),""),CHAR(9),"")),4,5), MID(TRIM(SUBSTITUTE(SUBSTITUTE(G66,CHAR(160),""),CHAR(9),"")),4,4) ) -> 5080E | U66: {=_xlfn.LET( _xlpm.ch, TRIM(SUBSTITUTE(G66,CHAR(160),"")), _xlpm.ehTrator, OR(IFERROR(FIND("BM",_xlpm.ch),0)>0, IFERROR(FIND("PY",_xlpm.ch),0)>0), _xlpm.chave, IF(_xlpm.ehTrator, MID(_xlpm.ch,4,5), MID(_xlpm.ch,4,4)), _xlpm.fonte, IF(LEN(_xlpm.chave)=5, UTIL!BS:BS, UTIL!BR:BR), _xlpm.modelo, TRIM(SUBSTITUTE(T66,CHAR(160),"")), _xlpm.nomeMod, IFERROR(_xlfn.XLOOKUP("*"&_xlpm.modelo&"*", UTIL!D:D, UTIL!B:B, "", 2), IFERROR(_xlfn.XLOOKUP("*"&_xlpm.modelo&"*", UTIL!E:E, UTIL!B:B, "", 2), "")), _xlpm.tipoMod, IF(_xlpm.nomeMod="", "", IFERROR(LEFT(_xlpm.nomeMod, FIND(" ", _xlpm.nomeMod)-1), _xlpm.nomeMod)), _xlpm.dimMod, IFERROR(_xlfn.XLOOKUP("*"&_xlpm.modelo&"*", UTIL!D:D, UTIL!K:K, "", 2), IFERROR(_xlfn.XLOOKUP("*"&_xlpm.modelo&"*", UTIL!E:E, UTIL!K:K, "", 2), "")), _xlpm.tipotxt_antigo, IF(_xlpm.ehTrator, "TRATOR", IFERROR(_xlfn.XLOOKUP(_xlpm.chave, _xlpm.fonte, UTIL!BP:BP, "", 0), IFERROR(_xlfn.XLOOKUP("*"&_xlpm.chave&"*", _xlpm.fonte, UTIL!BP:BP, "", 2), "Não encontrado"))), _xlpm.dimtxt_antigo, IFERROR(_xlfn.XLOOKUP(_xlpm.chave, _xlpm.fonte, UTIL!BY:BY, "", 0), IFERROR(_xlfn.XLOOKUP("*"&_xlpm.chave&"*", _xlpm.fonte, UTIL!BY:BY, "", 2), "Não encontrado")), _xlpm.tipotxt, IF(_xlpm.tipoMod<>"", _xlpm.tipoMod, _xlpm.tipotxt_antigo), _xlpm.dimtxt, IF(_xlpm.dimMod<>"", _xlpm.dimMod, _xlpm.dimtxt_antigo), _xlpm.deTxt, IF(L66="CLIENTE", O66, IF(LEFT(L66,4)="http", L66, "MACPONTA AGRO DE "&L66)), _xlpm.paraBase, IF(M66="CLIENTE", P66, M66), _xlpm.paraTxt, IF(LEFT(_xlpm.paraBase,4)="http", _xlpm.paraBase, "MACPONTA AGRO DE "&_xlpm.paraBase), _xlpm.nfParte, IF(LEN(TRIM(I66))=0, "", " -NF "&TRIM(I66)), "- " & _xlpm.tipotxt & ": *" & G66 & "*" & CHAR(13)&CHAR(10) & "- " & _xlpm.dimtxt & CHAR(13)&CHAR(10) & "- *Cliente*: " & J66 & _xlpm.nfParte & CHAR(13)&CHAR(10) & "- *Obs:* " & Q66 & CHAR(13)&CHAR(10) & CHAR(10) & "- *De*: " & _xlpm.deTxt & CHAR(13)&CHAR(10) & "- *Para*: " & _xlpm.paraTxt & CHAR(13)&CHAR(10) & "- *Ida e volta*: +/- " & TEXT(((D66*1.5)/1440),"h:mm") & "h | " & D66 & "km" )} -> - TRATOR: *1BM5080EPS6204421*_x000D_ - _x000D_ - *Cliente*: NÃO INFORMADO- NÃO TEM NF_x000D_ - *Obs:* _x000D_ - *De*: MACPONTA AGRO DE PONTA GROSSA_x000D_ - *Para*: https://maps.app.goo.gl/BxL47zGps2wAbAig9_x000D_ - *Ida e volta*: +/- 2:03h | 82km
A67: RECEBIDO (D) | B67: NÃO DEFINIDO | C67: =IFERROR((D67*1.5)/1440, "?") -> 0.15625 | D67: 150 | E67: =IFERROR((D67*6),"?") -> 900 | G67: 1BM5060EES4201644 | H67: 45983 | J67: Conexão JD -NF279152 | K67: carolina.quadros | L67: PONTA GROSSA | M67: CLIENTE | N67: DE LOJA PARA DEMONSTRAÇÃO | O67: MPA | P67: https://maps.app.goo.gl/tbQZRQV4a7fp35NM6 | Q67: Conexão JD - Estática - Palmeira -Água Clara | R67: PONTA GROSSA | S67: TRATOR | T67: =IF( OR( IFERROR(FIND("BM",G67),0)>0, IFERROR(FIND("PY",G67),0)>0 ), MID(TRIM(SUBSTITUTE(SUBSTITUTE(G67,CHAR(160),""),CHAR(9),"")),4,5), MID(TRIM(SUBSTITUTE(SUBSTITUTE(G67,CHAR(160),""),CHAR(9),"")),4,4) ) -> 5060E | U67: {=_xlfn.LET( _xlpm.ch, TRIM(SUBSTITUTE(G67,CHAR(160),"")), _xlpm.ehTrator, OR(IFERROR(FIND("BM",_xlpm.ch),0)>0, IFERROR(FIND("PY",_xlpm.ch),0)>0), _xlpm.chave, IF(_xlpm.ehTrator, MID(_xlpm.ch,4,5), MID(_xlpm.ch,4,4)), _xlpm.fonte, IF(LEN(_xlpm.chave)=5, UTIL!BS:BS, UTIL!BR:BR), _xlpm.modelo, TRIM(SUBSTITUTE(T67,CHAR(160),"")), _xlpm.nomeMod, IFERROR(_xlfn.XLOOKUP("*"&_xlpm.modelo&"*", UTIL!D:D, UTIL!B:B, "", 2), IFERROR(_xlfn.XLOOKUP("*"&_xlpm.modelo&"*", UTIL!E:E, UTIL!B:B, "", 2), "")), _xlpm.tipoMod, IF(_xlpm.nomeMod="", "", IFERROR(LEFT(_xlpm.nomeMod, FIND(" ", _xlpm.nomeMod)-1), _xlpm.nomeMod)), _xlpm.dimMod, IFERROR(_xlfn.XLOOKUP("*"&_xlpm.modelo&"*", UTIL!D:D, UTIL!K:K, "", 2), IFERROR(_xlfn.XLOOKUP("*"&_xlpm.modelo&"*", UTIL!E:E, UTIL!K:K, "", 2), "")), _xlpm.tipotxt_antigo, IF(_xlpm.ehTrator, "TRATOR", IFERROR(_xlfn.XLOOKUP(_xlpm.chave, _xlpm.fonte, UTIL!BP:BP, "", 0), IFERROR(_xlfn.XLOOKUP("*"&_xlpm.chave&"*", _xlpm.fonte, UTIL!BP:BP, "", 2), "Não encontrado"))), _xlpm.dimtxt_antigo, IFERROR(_xlfn.XLOOKUP(_xlpm.chave, _xlpm.fonte, UTIL!BY:BY, "", 0), IFERROR(_xlfn.XLOOKUP("*"&_xlpm.chave&"*", _xlpm.fonte, UTIL!BY:BY, "", 2), "Não encontrado")), _xlpm.tipotxt, IF(_xlpm.tipoMod<>"", _xlpm.tipoMod, _xlpm.tipotxt_antigo), _xlpm.dimtxt, IF(_xlpm.dimMod<>"", _xlpm.dimMod, _xlpm.dimtxt_antigo), _xlpm.deTxt, IF(L67="CLIENTE", O67, IF(LEFT(L67,4)="http", L67, "MACPONTA AGRO DE "&L67)), _xlpm.paraBase, IF(M67="CLIENTE", P67, M67), _xlpm.paraTxt, IF(LEFT(_xlpm.paraBase,4)="http", _xlpm.paraBase, "MACPONTA AGRO DE "&_xlpm.paraBase), _xlpm.nfParte, IF(LEN(TRIM(I67))=0, "", " -NF "&TRIM(I67)), "- " & _xlpm.tipotxt & ": *" & G67 & "*" & CHAR(13)&CHAR(10) & "- " & _xlpm.dimtxt & CHAR(13)&CHAR(10) & "- *Cliente*: " & J67 & _xlpm.nfParte & CHAR(13)&CHAR(10) & "- *Obs:* " & Q67 & CHAR(13)&CHAR(10) & CHAR(10) & "- *De*: " & _xlpm.deTxt & CHAR(13)&CHAR(10) & "- *Para*: " & _xlpm.paraTxt & CHAR(13)&CHAR(10) & "- *Ida e volta*: +/- " & TEXT(((D67*1.5)/1440),"h:mm") & "h | " & D67 & "km" )} -> - TRATOR: *1BM5060EES4201644*_x000D_ - _x000D_ - *Cliente*: Conexão JD -NF279152_x000D_ - *Obs:* Conexão JD - Estática - Palmeira -Água Clara_x000D_ - *De*: MACPONTA AGRO DE PONTA GROSSA_x000D_ - *Para*: https://maps.app.goo.gl/tbQZRQV4a7fp35NM6_x000D_ - *Ida e volta*: +/- 3:45h | 150km
A68: RECEBIDO (D) | B68: NÃO DEFINIDO | C68: =IFERROR((D68*1.5)/1440, "?") -> 0.15625 | D68: 150 | E68: =IFERROR((D68*6),"?") -> 900 | G68: 1BM5080ECS4204234 | H68: 45983 | J68: Conexão JD -NF279152 | K68: carolina.quadros | L68: PONTA GROSSA | M68: CLIENTE | N68: DE LOJA PARA DEMONSTRAÇÃO | O68: MPA | P68: https://maps.app.goo.gl/tbQZRQV4a7fp35NM6 | Q68: Conexão JD - Estática - Palmeira -Água Clara | R68: PONTA GROSSA | S68: TRATOR | T68: =IF( OR( IFERROR(FIND("BM",G68),0)>0, IFERROR(FIND("PY",G68),0)>0 ), MID(TRIM(SUBSTITUTE(SUBSTITUTE(G68,CHAR(160),""),CHAR(9),"")),4,5), MID(TRIM(SUBSTITUTE(SUBSTITUTE(G68,CHAR(160),""),CHAR(9),"")),4,4) ) -> 5080E | U68: {=_xlfn.LET( _xlpm.ch, TRIM(SUBSTITUTE(G68,CHAR(160),"")), _xlpm.ehTrator, OR(IFERROR(FIND("BM",_xlpm.ch),0)>0, IFERROR(FIND("PY",_xlpm.ch),0)>0), _xlpm.chave, IF(_xlpm.ehTrator, MID(_xlpm.ch,4,5), MID(_xlpm.ch,4,4)), _xlpm.fonte, IF(LEN(_xlpm.chave)=5, UTIL!BS:BS, UTIL!BR:BR), _xlpm.modelo, TRIM(SUBSTITUTE(T68,CHAR(160),"")), _xlpm.nomeMod, IFERROR(_xlfn.XLOOKUP("*"&_xlpm.modelo&"*", UTIL!D:D, UTIL!B:B, "", 2), IFERROR(_xlfn.XLOOKUP("*"&_xlpm.modelo&"*", UTIL!E:E, UTIL!B:B, "", 2), "")), _xlpm.tipoMod, IF(_xlpm.nomeMod="", "", IFERROR(LEFT(_xlpm.nomeMod, FIND(" ", _xlpm.nomeMod)-1), _xlpm.nomeMod)), _xlpm.dimMod, IFERROR(_xlfn.XLOOKUP("*"&_xlpm.modelo&"*", UTIL!D:D, UTIL!K:K, "", 2), IFERROR(_xlfn.XLOOKUP("*"&_xlpm.modelo&"*", UTIL!E:E, UTIL!K:K, "", 2), "")), _xlpm.tipotxt_antigo, IF(_xlpm.ehTrator, "TRATOR", IFERROR(_xlfn.XLOOKUP(_xlpm.chave, _xlpm.fonte, UTIL!BP:BP, "", 0), IFERROR(_xlfn.XLOOKUP("*"&_xlpm.chave&"*", _xlpm.fonte, UTIL!BP:BP, "", 2), "Não encontrado"))), _xlpm.dimtxt_antigo, IFERROR(_xlfn.XLOOKUP(_xlpm.chave, _xlpm.fonte, UTIL!BY:BY, "", 0), IFERROR(_xlfn.XLOOKUP("*"&_xlpm.chave&"*", _xlpm.fonte, UTIL!BY:BY, "", 2), "Não encontrado")), _xlpm.tipotxt, IF(_xlpm.tipoMod<>"", _xlpm.tipoMod, _xlpm.tipotxt_antigo), _xlpm.dimtxt, IF(_xlpm.dimMod<>"", _xlpm.dimMod, _xlpm.dimtxt_antigo), _xlpm.deTxt, IF(L68="CLIENTE", O68, IF(LEFT(L68,4)="http", L68, "MACPONTA AGRO DE "&L68)), _xlpm.paraBase, IF(M68="CLIENTE", P68, M68), _xlpm.paraTxt, IF(LEFT(_xlpm.paraBase,4)="http", _xlpm.paraBase, "MACPONTA AGRO DE "&_xlpm.paraBase), _xlpm.nfParte, IF(LEN(TRIM(I68))=0, "", " -NF "&TRIM(I68)), "- " & _xlpm.tipotxt & ": *" & G68 & "*" & CHAR(13)&CHAR(10) & "- " & _xlpm.dimtxt & CHAR(13)&CHAR(10) & "- *Cliente*: " & J68 & _xlpm.nfParte & CHAR(13)&CHAR(10) & "- *Obs:* " & Q68 & CHAR(13)&CHAR(10) & CHAR(10) & "- *De*: " & _xlpm.deTxt & CHAR(13)&CHAR(10) & "- *Para*: " & _xlpm.paraTxt & CHAR(13)&CHAR(10) & "- *Ida e volta*: +/- " & TEXT(((D68*1.5)/1440),"h:mm") & "h | " & D68 & "km" )} -> - TRATOR: *1BM5080ECS4204234*_x000D_ - _x000D_ - *Cliente*: Conexão JD -NF279152_x000D_ - *Obs:* Conexão JD - Estática - Palmeira -Água Clara_x000D_ - *De*: MACPONTA AGRO DE PONTA GROSSA_x000D_ - *Para*: https://maps.app.goo.gl/tbQZRQV4a7fp35NM6_x000D_ - *Ida e volta*: +/- 3:45h | 150km
